[
  {
    "名称": "武汉汇跃天聚技术有限公司",
    "编号": "GR202242000509"
  },
  {
    "名称": "武汉威泰尔科技发展有限公司",
    "编号": "GR202242000510"
  },
  {
    "名称": "武汉博朗星科技有限公司",
    "编号": "GR202242000511"
  },
  {
    "名称": "武汉市博奥特软件技术有限公司",
    "编号": "GR202242000512"
  },
  {
    "名称": "武汉美星科技有限公司",
    "编号": "GR202242000513"
  },
  {
    "名称": "武汉所为不凡能源科技有限公司",
    "编号": "GR202242000514"
  },
  {
    "名称": "湖北华醇食品有限公司",
    "编号": "GR202242000515"
  },
  {
    "名称": "武汉理邦日至科技有限公司",
    "编号": "GR202242000516"
  },
  {
    "名称": "武汉市香芋科技有限公司",
    "编号": "GR202242000517"
  },
  {
    "名称": "湖北富海恒科电气技术有限公司",
    "编号": "GR202242000518"
  },
  {
    "名称": "湖北欧米飞光电科技有限公司",
    "编号": "GR202242000519"
  },
  {
    "名称": "武汉盛泽新材料科技有限公司",
    "编号": "GR202242000520"
  },
  {
    "名称": "湖北寰安康华安全科技发展有限责任公司",
    "编号": "GR202242000521"
  },
  {
    "名称": "赤壁市科斯塔电子科技有限公司",
    "编号": "GR202242000522"
  },
  {
    "名称": "武汉智信联诚科技有限公司",
    "编号": "GR202242000523"
  },
  {
    "名称": "湖北凸凹模具科技股份有限公司",
    "编号": "GR202242000524"
  },
  {
    "名称": "湖北臻诚电气检测有限公司",
    "编号": "GR202242000525"
  },
  {
    "名称": "襄阳捷昌栏艺新型材料有限公司",
    "编号": "GR202242000526"
  },
  {
    "名称": "湖北盛兴纺织科技有限公司",
    "编号": "GR202242000527"
  },
  {
    "名称": "武汉欣向荣金属激光制品有限公司",
    "编号": "GR202242000528"
  },
  {
    "名称": "湖北梦阳药业股份有限公司",
    "编号": "GR202242000529"
  },
  {
    "名称": "武汉恒欣盛科技有限公司",
    "编号": "GR202242000530"
  },
  {
    "名称": "武汉云开智捷科技有限公司",
    "编号": "GR202242000531"
  },
  {
    "名称": "十堰锦天汽车零部件有限公司",
    "编号": "GR202242000532"
  },
  {
    "名称": "湖北福好医疗用品有限公司",
    "编号": "GR202242000533"
  },
  {
    "名称": "武汉燃气热力能源服务有限公司",
    "编号": "GR202242000534"
  },
  {
    "名称": "湖北泰友纸业有限公司",
    "编号": "GR202242000535"
  },
  {
    "名称": "湖北广朋铝业股份有限公司",
    "编号": "GR202242000536"
  },
  {
    "名称": "武汉惟诺达科技有限公司",
    "编号": "GR202242000537"
  },
  {
    "名称": "武汉道格传媒科技有限公司",
    "编号": "GR202242000538"
  },
  {
    "名称": "武汉江蓉智能工程有限公司",
    "编号": "GR202242000539"
  },
  {
    "名称": "武汉华正环境检测技术有限公司",
    "编号": "GR202242000540"
  },
  {
    "名称": "湖北楚春归环保科技工程有限公司",
    "编号": "GR202242000541"
  },
  {
    "名称": "荆州市与时塑业有限公司",
    "编号": "GR202242000542"
  },
  {
    "名称": "武汉巨迪金属管业有限公司",
    "编号": "GR202242000543"
  },
  {
    "名称": "思达尔科技（武汉）有限公司",
    "编号": "GR202242000544"
  },
  {
    "名称": "武汉天一华煜基因科技有限公司",
    "编号": "GR202242000545"
  },
  {
    "名称": "武汉新途汽配制造有限公司",
    "编号": "GR202242000546"
  },
  {
    "名称": "武汉飞虹工程管理咨询有限公司",
    "编号": "GR202242000547"
  },
  {
    "名称": "湖北华之夏种子有限责任公司",
    "编号": "GR202242000548"
  },
  {
    "名称": "武汉天拓宇航智能装备有限公司",
    "编号": "GR202242000549"
  },
  {
    "名称": "湖北冠普橡塑科技有限公司",
    "编号": "GR202242000550"
  },
  {
    "名称": "宜都得胜数码科技有限公司",
    "编号": "GR202242000551"
  },
  {
    "名称": "湖北天之朗环保设备有限公司",
    "编号": "GR202242000552"
  },
  {
    "名称": "襄阳九鼎昊天环保设备有限公司",
    "编号": "GR202242000553"
  },
  {
    "名称": "武汉市智尚设界科技有限公司",
    "编号": "GR202242000554"
  },
  {
    "名称": "武汉超宇测控技术有限公司",
    "编号": "GR202242000555"
  },
  {
    "名称": "中材（宜昌）节能新材料有限公司",
    "编号": "GR202242000556"
  },
  {
    "名称": "湖北美达电器有限公司",
    "编号": "GR202242000557"
  },
  {
    "名称": "欧赛新能源科技股份有限公司",
    "编号": "GR202242000558"
  },
  {
    "名称": "宜昌精宇电子科技有限公司",
    "编号": "GR202242000559"
  },
  {
    "名称": "鄂州市国伟建材有限责任公司",
    "编号": "GR202242000560"
  },
  {
    "名称": "武汉格林美洁净技术工程有限公司",
    "编号": "GR202242000561"
  },
  {
    "名称": "天门市格韵无纺布有限公司",
    "编号": "GR202242000562"
  },
  {
    "名称": "武汉相控信息科技有限公司",
    "编号": "GR202242000563"
  },
  {
    "名称": "武汉博派擎天传媒科技有限公司",
    "编号": "GR202242000564"
  },
  {
    "名称": "武汉黑嘿文化传媒有限公司",
    "编号": "GR202242000565"
  },
  {
    "名称": "武汉麦咚健康科技有限公司",
    "编号": "GR202242000566"
  },
  {
    "名称": "湖北瓦仓谷香生态农业有限公司",
    "编号": "GR202242000567"
  },
  {
    "名称": "湖北尔漫智能科技有限公司",
    "编号": "GR202242000568"
  },
  {
    "名称": "武汉微集思科技有限公司",
    "编号": "GR202242000569"
  },
  {
    "名称": "武汉芳华杰出科技有限公司",
    "编号": "GR202242000570"
  },
  {
    "名称": "湖北火爆机器人科技有限公司",
    "编号": "GR202242000571"
  },
  {
    "名称": "武汉联乐床具有限公司",
    "编号": "GR202242000572"
  },
  {
    "名称": "武汉恩立本模型设计有限公司",
    "编号": "GR202242000573"
  },
  {
    "名称": "湖北格瑞乐环保工程有限公司",
    "编号": "GR202242000574"
  },
  {
    "名称": "襄阳市零壹物联科技有限公司",
    "编号": "GR202242000575"
  },
  {
    "名称": "武汉易通科技有限公司",
    "编号": "GR202242000576"
  },
  {
    "名称": "湖北圣任科技有限公司",
    "编号": "GR202242000577"
  },
  {
    "名称": "武汉山舟软件技术有限公司",
    "编号": "GR202242000578"
  },
  {
    "名称": "武汉熙多科技有限公司",
    "编号": "GR202242000579"
  },
  {
    "名称": "湖北合信智能包装科技有限公司",
    "编号": "GR202242000580"
  },
  {
    "名称": "湖北中部医疗科技有限公司",
    "编号": "GR202242000581"
  },
  {
    "名称": "恩施福硒康农业科技有限公司",
    "编号": "GR202242000582"
  },
  {
    "名称": "武汉随一网络科技有限公司",
    "编号": "GR202242000583"
  },
  {
    "名称": "湖北策鑫智造科技有限责任公司",
    "编号": "GR202242000584"
  },
  {
    "名称": "瑞腾湖北建设集团有限公司",
    "编号": "GR202242000585"
  },
  {
    "名称": "湖北江川水利水电工程有限责任公司",
    "编号": "GR202242000586"
  },
  {
    "名称": "黄石隆欣五金有限公司",
    "编号": "GR202242000587"
  },
  {
    "名称": "武汉拓雅文化传播有限公司",
    "编号": "GR202242000588"
  },
  {
    "名称": "湖北宗坤石斛科技开发有限公司",
    "编号": "GR202242000589"
  },
  {
    "名称": "武汉当玩科技有限公司",
    "编号": "GR202242000590"
  },
  {
    "名称": "荆州市丽之源化工科技股份有限公司",
    "编号": "GR202242000591"
  },
  {
    "名称": "蕲春千年艾科技有限公司",
    "编号": "GR202242000592"
  },
  {
    "名称": "武汉和平大世界新科技有限公司",
    "编号": "GR202242000593"
  },
  {
    "名称": "湖北沃裕新材料科技有限公司",
    "编号": "GR202242000594"
  },
  {
    "名称": "湖北特林节能设备有限公司",
    "编号": "GR202242000595"
  },
  {
    "名称": "武汉瑞祥安科技股份有限公司",
    "编号": "GR202242000596"
  },
  {
    "名称": "武汉长江计算科技有限公司",
    "编号": "GR202242000597"
  },
  {
    "名称": "武汉中地水石环保科技有限公司",
    "编号": "GR202242000598"
  },
  {
    "名称": "康蓝久庭环保科技（湖北）有限公司",
    "编号": "GR202242000599"
  },
  {
    "名称": "武汉市市政路桥有限公司",
    "编号": "GR202242000600"
  },
  {
    "名称": "湖北环峰能源科技有限公司",
    "编号": "GR202242000601"
  },
  {
    "名称": "华途仕实业有限公司",
    "编号": "GR202242000602"
  },
  {
    "名称": "湖北智凌数码科技有限公司",
    "编号": "GR202242000603"
  },
  {
    "名称": "湖北潜江江汉环保有限公司",
    "编号": "GR202242000604"
  },
  {
    "名称": "武汉智宇图新科技有限责任公司",
    "编号": "GR202242000605"
  },
  {
    "名称": "武汉市市政道路排水工程有限公司",
    "编号": "GR202242000606"
  },
  {
    "名称": "湖北凯力专用汽车有限公司",
    "编号": "GR202242000607"
  },
  {
    "名称": "中域高科（武汉）信息技术有限公司",
    "编号": "GR202242000608"
  },
  {
    "名称": "武汉怡清环保工程有限责任公司",
    "编号": "GR202242000609"
  },
  {
    "名称": "湖北志明电子科技有限公司",
    "编号": "GR202242000610"
  },
  {
    "名称": "武汉佑一科技有限公司",
    "编号": "GR202242000611"
  },
  {
    "名称": "武汉联信普惠信息科技有限公司",
    "编号": "GR202242000612"
  },
  {
    "名称": "湖北领智装配建筑科技有限公司",
    "编号": "GR202242000613"
  },
  {
    "名称": "襄阳敏杰星新型建材实业有限公司",
    "编号": "GR202242000614"
  },
  {
    "名称": "湖北恒奥铝业有限公司",
    "编号": "GR202242000615"
  },
  {
    "名称": "同共科技（赤壁）有限公司",
    "编号": "GR202242000616"
  },
  {
    "名称": "武汉现代都市农业规划设计院股份有限公司",
    "编号": "GR202242000617"
  },
  {
    "名称": "万向通达股份公司",
    "编号": "GR202242000618"
  },
  {
    "名称": "湖北凯欣环保科技有限公司",
    "编号": "GR202242000619"
  },
  {
    "名称": "武汉壹鑫才学科技有限公司",
    "编号": "GR202242000620"
  },
  {
    "名称": "湖北大叶光学制造有限公司",
    "编号": "GR202242000621"
  },
  {
    "名称": "湖北省森瑞达钢化玻璃科技有限公司",
    "编号": "GR202242000622"
  },
  {
    "名称": "武汉铁骨网络科技有限公司",
    "编号": "GR202242000623"
  },
  {
    "名称": "武穴市长江矿业有限责任公司",
    "编号": "GR202242000624"
  },
  {
    "名称": "武汉鑫岳光电科技有限公司",
    "编号": "GR202242000625"
  },
  {
    "名称": "湖北李泽园食品有限公司",
    "编号": "GR202242000626"
  },
  {
    "名称": "宜昌弘盛达混凝土有限公司",
    "编号": "GR202242000627"
  },
  {
    "名称": "湖北保宁科技有限公司",
    "编号": "GR202242000628"
  },
  {
    "名称": "宜昌伟易达科技有限公司",
    "编号": "GR202242000629"
  },
  {
    "名称": "武汉弗雷德斯科技发展有限公司",
    "编号": "GR202242000630"
  },
  {
    "名称": "湖北伊冉网络科技服务有限公司",
    "编号": "GR202242000631"
  },
  {
    "名称": "武汉博汇油田工程服务有限公司",
    "编号": "GR202242000632"
  },
  {
    "名称": "湖北欧润船舶工程有限公司",
    "编号": "GR202242000633"
  },
  {
    "名称": "宜昌江森船务有限公司",
    "编号": "GR202242000634"
  },
  {
    "名称": "武汉朗迪远程医疗科技有限公司",
    "编号": "GR202242000635"
  },
  {
    "名称": "荆州市鑫振发户外用品有限公司",
    "编号": "GR202242000636"
  },
  {
    "名称": "襄阳杰亿达软件技术有限公司",
    "编号": "GR202242000637"
  },
  {
    "名称": "湖北新联测科技有限公司",
    "编号": "GR202242000638"
  },
  {
    "名称": "黄梅县志民粮油贸易有限公司",
    "编号": "GR202242000639"
  },
  {
    "名称": "星光玉龙机械（湖北）有限公司",
    "编号": "GR202242000640"
  },
  {
    "名称": "宜昌鼎顺检测有限公司",
    "编号": "GR202242000641"
  },
  {
    "名称": "湖北世纪伟业防腐科技有限公司",
    "编号": "GR202242000642"
  },
  {
    "名称": "湖北鼎艾科技有限公司",
    "编号": "GR202242000643"
  },
  {
    "名称": "湖北凌励网络科技有限公司",
    "编号": "GR202242000644"
  },
  {
    "名称": "武汉优艾自动化技术有限公司",
    "编号": "GR202242000645"
  },
  {
    "名称": "湖北武洲新材料科技有限公司",
    "编号": "GR202242000646"
  },
  {
    "名称": "武汉光创源科技有限公司",
    "编号": "GR202242000647"
  },
  {
    "名称": "随州市康美电子有限公司",
    "编号": "GR202242000648"
  },
  {
    "名称": "钟祥市龙富食品有限公司",
    "编号": "GR202242000649"
  },
  {
    "名称": "黑八蕉（武汉）网络科技有限公司",
    "编号": "GR202242000650"
  },
  {
    "名称": "湖北江南专用特种汽车有限公司",
    "编号": "GR202242000651"
  },
  {
    "名称": "黄冈市华窑中博窑炉技术有限公司",
    "编号": "GR202242000652"
  },
  {
    "名称": "武汉天聚云信息技术有限公司",
    "编号": "GR202242000653"
  },
  {
    "名称": "湖北博英精工科技股份有限公司",
    "编号": "GR202242000654"
  },
  {
    "名称": "襄阳富襄现代农业开发有限公司",
    "编号": "GR202242000655"
  },
  {
    "名称": "武汉利科夫科技有限公司",
    "编号": "GR202242000656"
  },
  {
    "名称": "武汉莱斯贝尔科技有限公司",
    "编号": "GR202242000657"
  },
  {
    "名称": "巴东县水务公司",
    "编号": "GR202242000658"
  },
  {
    "名称": "武汉易晨创想科技有限公司",
    "编号": "GR202242000659"
  },
  {
    "名称": "湖北龙澳系统工程有限公司",
    "编号": "GR202242000660"
  },
  {
    "名称": "武汉乐橙云科技有限公司",
    "编号": "GR202242000661"
  },
  {
    "名称": "枝江市鹏达机械有限责任公司",
    "编号": "GR202242000662"
  },
  {
    "名称": "湖北安耐得建筑系统有限公司",
    "编号": "GR202242000663"
  },
  {
    "名称": "武汉中和博瑞电气有限公司",
    "编号": "GR202242000664"
  },
  {
    "名称": "湖北海震科创技术有限公司",
    "编号": "GR202242000665"
  },
  {
    "名称": "荆州市美江劳保用品股份有限公司",
    "编号": "GR202242000666"
  },
  {
    "名称": "武汉鑫凯力通信工程有限公司",
    "编号": "GR202242000667"
  },
  {
    "名称": "宜都市友源实业有限公司",
    "编号": "GR202242000668"
  },
  {
    "名称": "喜色包装（武汉）有限公司",
    "编号": "GR202242000669"
  },
  {
    "名称": "昌群精细工业（宜昌）有限公司",
    "编号": "GR202242000670"
  },
  {
    "名称": "清研新能源汽车工程中心（襄阳）有限公司",
    "编号": "GR202242000671"
  },
  {
    "名称": "武汉二月二科技有限公司",
    "编号": "GR202242000672"
  },
  {
    "名称": "武汉联呈精密工业有限公司",
    "编号": "GR202242000673"
  },
  {
    "名称": "武汉亚舟星科技有限公司",
    "编号": "GR202242000674"
  },
  {
    "名称": "湖北罗工科技有限责任公司",
    "编号": "GR202242000675"
  },
  {
    "名称": "湖北科普达光电材料有限公司",
    "编号": "GR202242000676"
  },
  {
    "名称": "孝昌县鑫波农业发展股份有限公司",
    "编号": "GR202242000677"
  },
  {
    "名称": "黄冈市华精科技有限公司",
    "编号": "GR202242000678"
  },
  {
    "名称": "武汉华扬天乐生物科技有限公司",
    "编号": "GR202242000679"
  },
  {
    "名称": "武汉鑫晟翰翔科技有限公司",
    "编号": "GR202242000680"
  },
  {
    "名称": "武汉乾能皓源科技有限公司",
    "编号": "GR202242000681"
  },
  {
    "名称": "湖北科迈捷环保科技有限公司",
    "编号": "GR202242000682"
  },
  {
    "名称": "湖北荔众新材料科技有限公司",
    "编号": "GR202242000683"
  },
  {
    "名称": "东风华神汽车有限公司",
    "编号": "GR202242000684"
  },
  {
    "名称": "湖北原驰智能科技有限公司",
    "编号": "GR202242000685"
  },
  {
    "名称": "武汉光谷瑞源智能技术有限公司",
    "编号": "GR202242000686"
  },
  {
    "名称": "宜昌智腾科技有限公司",
    "编号": "GR202242000687"
  },
  {
    "名称": "荆门市坚峰新型建材有限公司",
    "编号": "GR202242000688"
  },
  {
    "名称": "湖北卡乐尔新材料科技有限公司",
    "编号": "GR202242000689"
  },
  {
    "名称": "武汉极木组建筑设计有限公司",
    "编号": "GR202242000690"
  },
  {
    "名称": "武汉博昇光电股份有限公司",
    "编号": "GR202242000691"
  },
  {
    "名称": "武汉瑞思科机电工程有限公司",
    "编号": "GR202242000692"
  },
  {
    "名称": "湖北省鄂西北工程勘察有限责任公司",
    "编号": "GR202242000693"
  },
  {
    "名称": "武汉奇好科技有限公司",
    "编号": "GR202242000694"
  },
  {
    "名称": "襄阳市凯达包装商标彩印有限公司",
    "编号": "GR202242000695"
  },
  {
    "名称": "湖北高速通电子科技有限公司",
    "编号": "GR202242000696"
  },
  {
    "名称": "武汉高明兰光电科技有限公司",
    "编号": "GR202242000697"
  },
  {
    "名称": "湖北菲尔博德环保科技有限责任公司",
    "编号": "GR202242000698"
  },
  {
    "名称": "襄阳爱迪电子科技有限公司",
    "编号": "GR202242000699"
  },
  {
    "名称": "湖北中图勘测规划设计有限公司",
    "编号": "GR202242000700"
  },
  {
    "名称": "襄阳海诚科技有限公司",
    "编号": "GR202242000701"
  },
  {
    "名称": "湖北华美阳光生物科技有限公司",
    "编号": "GR202242000702"
  },
  {
    "名称": "武汉纳多德网络技术有限公司",
    "编号": "GR202242000703"
  },
  {
    "名称": "湖北长锐光电科技有限公司",
    "编号": "GR202242000704"
  },
  {
    "名称": "洪湖市一泰科技有限公司",
    "编号": "GR202242000705"
  },
  {
    "名称": "湖北金欧米智能科技有限公司",
    "编号": "GR202242000706"
  },
  {
    "名称": "宜昌市大楚医疗器械设备股份有限公司",
    "编号": "GR202242000707"
  },
  {
    "名称": "咸宁市明瑞塑料包装股份有限公司",
    "编号": "GR202242000708"
  },
  {
    "名称": "湖北中煜环保科技有限公司",
    "编号": "GR202242000709"
  },
  {
    "名称": "湖北集发新材料科技有限公司",
    "编号": "GR202242000710"
  },
  {
    "名称": "湖北三晶生物科技股份有限公司",
    "编号": "GR202242000711"
  },
  {
    "名称": "湖北楚天电缆实业有限公司",
    "编号": "GR202242000712"
  },
  {
    "名称": "武汉纳捷利拓信息技术有限公司",
    "编号": "GR202242000713"
  },
  {
    "名称": "湖北上风风机有限公司",
    "编号": "GR202242000714"
  },
  {
    "名称": "众瑞速联（武汉）科技有限公司",
    "编号": "GR202242000715"
  },
  {
    "名称": "武汉荣智电气科技有限公司",
    "编号": "GR202242000716"
  },
  {
    "名称": "荆州市宇清信息科技有限公司",
    "编号": "GR202242000717"
  },
  {
    "名称": "湖北泓达建设集团有限公司",
    "编号": "GR202242000718"
  },
  {
    "名称": "湖北好食味食品有限公司",
    "编号": "GR202242000719"
  },
  {
    "名称": "湖北登峰高强螺栓有限公司",
    "编号": "GR202242000720"
  },
  {
    "名称": "湖北泰和石化设备有限公司",
    "编号": "GR202242000721"
  },
  {
    "名称": "武汉维普科技有限公司",
    "编号": "GR202242000722"
  },
  {
    "名称": "当阳市金德利印务有限公司",
    "编号": "GR202242000723"
  },
  {
    "名称": "武汉鑫丰腾工程科技有限公司",
    "编号": "GR202242000724"
  },
  {
    "名称": "湖北浩阳新能源有限公司",
    "编号": "GR202242000725"
  },
  {
    "名称": "武汉飞天智能工程有限责任公司",
    "编号": "GR202242000726"
  },
  {
    "名称": "黄石微美生活网络科技有限公司",
    "编号": "GR202242000727"
  },
  {
    "名称": "武汉融创诚机电技术有限公司",
    "编号": "GR202242000728"
  },
  {
    "名称": "湖北宇宿新能源科技有限公司",
    "编号": "GR202242000729"
  },
  {
    "名称": "武汉特柏尔电子技术有限公司",
    "编号": "GR202242000730"
  },
  {
    "名称": "武汉洛霖智翼科技有限公司",
    "编号": "GR202242000731"
  },
  {
    "名称": "湖北鑫之源精密铸造有限公司",
    "编号": "GR202242000732"
  },
  {
    "名称": "湖北辉煌机械制造有限责任公司",
    "编号": "GR202242000733"
  },
  {
    "名称": "武汉佳成生物制品有限公司",
    "编号": "GR202242000734"
  },
  {
    "名称": "湖北南邦创电科技有限公司",
    "编号": "GR202242000735"
  },
  {
    "名称": "南漳致远农业科技有限公司",
    "编号": "GR202242000736"
  },
  {
    "名称": "湖北蒂坶茶业有限公司",
    "编号": "GR202242000737"
  },
  {
    "名称": "湖北利鸿科技有限公司",
    "编号": "GR202242000738"
  },
  {
    "名称": "武汉春江生物科技股份有限公司",
    "编号": "GR202242000739"
  },
  {
    "名称": "湖北广盛建设集团有限责任公司",
    "编号": "GR202242000740"
  },
  {
    "名称": "湖北岚湖华源智能机械包装有限公司",
    "编号": "GR202242000741"
  },
  {
    "名称": "湖北中建三局建筑工程技术有限责任公司",
    "编号": "GR202242000742"
  },
  {
    "名称": "湖北永业行评估咨询有限公司",
    "编号": "GR202242000743"
  },
  {
    "名称": "武汉国博能源管理有限公司",
    "编号": "GR202242000744"
  },
  {
    "名称": "武汉比邻科技发展有限公司",
    "编号": "GR202242000745"
  },
  {
    "名称": "湖北特种电机制造有限公司",
    "编号": "GR202242000746"
  },
  {
    "名称": "湖北天运消音防振新材料有限公司",
    "编号": "GR202242000747"
  },
  {
    "名称": "武汉衡通公路勘察设计院有限公司",
    "编号": "GR202242000748"
  },
  {
    "名称": "湖北易拓网云科技发展有限公司",
    "编号": "GR202242000749"
  },
  {
    "名称": "大冶市展旺新材料科技有限公司",
    "编号": "GR202242000750"
  },
  {
    "名称": "湖北瑞特威科技股份有限公司",
    "编号": "GR202242000751"
  },
  {
    "名称": "武汉英欧韦特科技有限公司",
    "编号": "GR202242000752"
  },
  {
    "名称": "湖北橙阳科技有限公司",
    "编号": "GR202242000753"
  },
  {
    "名称": "湖北美圣雅恒新材料科技有限公司",
    "编号": "GR202242000754"
  },
  {
    "名称": "宜昌市科达环保工程有限公司",
    "编号": "GR202242000755"
  },
  {
    "名称": "武汉市科达耐火有限责任公司",
    "编号": "GR202242000756"
  },
  {
    "名称": "湖北环沙再生资源有限公司",
    "编号": "GR202242000757"
  },
  {
    "名称": "武汉华上科技有限公司",
    "编号": "GR202242000758"
  },
  {
    "名称": "武汉三江航天固德生物科技有限公司",
    "编号": "GR202242000759"
  },
  {
    "名称": "湖北易云智能科技发展有限责任公司",
    "编号": "GR202242000760"
  },
  {
    "名称": "武汉微智创大科技有限公司",
    "编号": "GR202242000761"
  },
  {
    "名称": "湖北钟祥众兴玻璃钢有限公司",
    "编号": "GR202242000762"
  },
  {
    "名称": "湖北中建鸿友建设有限公司",
    "编号": "GR202242000763"
  },
  {
    "名称": "湖北创意模具股份有限公司",
    "编号": "GR202242000764"
  },
  {
    "名称": "武汉盛图勘测设计有限公司",
    "编号": "GR202242000765"
  },
  {
    "名称": "湖北力拓能源化工装备有限公司",
    "编号": "GR202242000766"
  },
  {
    "名称": "武汉润德工程技术有限公司",
    "编号": "GR202242000767"
  },
  {
    "名称": "宜昌农田管家无人机科技有限公司",
    "编号": "GR202242000768"
  },
  {
    "名称": "武汉德希科技有限公司",
    "编号": "GR202242000769"
  },
  {
    "名称": "湖北沛丰生物科技股份有限公司",
    "编号": "GR202242000770"
  },
  {
    "名称": "湖北恒宇纵横科技有限公司",
    "编号": "GR202242000771"
  },
  {
    "名称": "湖北爱鑫医疗科技有限公司",
    "编号": "GR202242000772"
  },
  {
    "名称": "荆州市隆华石油化工有限公司",
    "编号": "GR202242000773"
  },
  {
    "名称": "天门市金江粮机有限公司",
    "编号": "GR202242000774"
  },
  {
    "名称": "荆州市红叶针织服饰有限公司",
    "编号": "GR202242000775"
  },
  {
    "名称": "武汉米字能源科技有限公司",
    "编号": "GR202242000776"
  },
  {
    "名称": "小河奔流科技集团有限公司",
    "编号": "GR202242000777"
  },
  {
    "名称": "钟祥市富铭辉金属表面处理有限公司",
    "编号": "GR202242000778"
  },
  {
    "名称": "巴东县兴发水泥制品有限公司",
    "编号": "GR202242000779"
  },
  {
    "名称": "荆州市江汉众力实业有限公司",
    "编号": "GR202242000780"
  },
  {
    "名称": "武汉沃特曼计量科技有限公司",
    "编号": "GR202242000781"
  },
  {
    "名称": "湖北龙辅药业有限公司",
    "编号": "GR202242000782"
  },
  {
    "名称": "武汉天空蓝环保科技有限公司",
    "编号": "GR202242000783"
  },
  {
    "名称": "武汉麦迪嘉机电科技有限公司",
    "编号": "GR202242000784"
  },
  {
    "名称": "宜昌市水利水电勘察设计院有限公司",
    "编号": "GR202242000785"
  },
  {
    "名称": "湖北隆泰达塑业有限公司",
    "编号": "GR202242000786"
  },
  {
    "名称": "武汉新骏高科技有限公司",
    "编号": "GR202242000787"
  },
  {
    "名称": "武汉华源新力电气设备有限公司",
    "编号": "GR202242000788"
  },
  {
    "名称": "武汉诚迈软件科技有限公司",
    "编号": "GR202242000789"
  },
  {
    "名称": "宜昌奥佳新材料科技有限公司",
    "编号": "GR202242000790"
  },
  {
    "名称": "武汉合诚众智科技有限公司",
    "编号": "GR202242000791"
  },
  {
    "名称": "湖北天威汽车有限公司",
    "编号": "GR202242000792"
  },
  {
    "名称": "湖北太子药业有限公司",
    "编号": "GR202242000793"
  },
  {
    "名称": "武汉兀艺工舍文化有限公司",
    "编号": "GR202242000794"
  },
  {
    "名称": "湖北万安环保石化设备有限公司",
    "编号": "GR202242000795"
  },
  {
    "名称": "湖北省亨德利医疗器械有限公司",
    "编号": "GR202242000796"
  },
  {
    "名称": "武汉沙特利生物器材有限公司",
    "编号": "GR202242000797"
  },
  {
    "名称": "湖北中水长江生态保护研究院有限公司",
    "编号": "GR202242000798"
  },
  {
    "名称": "湖北星地智链科技有限公司",
    "编号": "GR202242000799"
  },
  {
    "名称": "黄石东贝铸造有限公司",
    "编号": "GR202242000800"
  },
  {
    "名称": "武汉厚诺科技有限公司",
    "编号": "GR202242000801"
  },
  {
    "名称": "湖北奥马电子科技有限公司",
    "编号": "GR202242000802"
  },
  {
    "名称": "武汉创蒲电子有限公司",
    "编号": "GR202242000803"
  },
  {
    "名称": "湖北浩建净化科技工程有限公司",
    "编号": "GR202242000804"
  },
  {
    "名称": "湖北船王特种焊材有限公司",
    "编号": "GR202242000805"
  },
  {
    "名称": "武汉科能电气有限公司",
    "编号": "GR202242000806"
  },
  {
    "名称": "宜昌优智科技有限公司",
    "编号": "GR202242000807"
  },
  {
    "名称": "武汉博思安科技有限公司",
    "编号": "GR202242000808"
  },
  {
    "名称": "荆州市福星塑料科技开发有限公司",
    "编号": "GR202242000809"
  },
  {
    "名称": "湖北智荆高新种业科技有限公司",
    "编号": "GR202242000810"
  },
  {
    "名称": "武汉宜田科技发展有限公司",
    "编号": "GR202242000811"
  },
  {
    "名称": "湖北垚美软瓷有限公司",
    "编号": "GR202242000812"
  },
  {
    "名称": "长阳安品源电子科技有限公司",
    "编号": "GR202242000813"
  },
  {
    "名称": "湖北凯蒂园林景观工程有限公司",
    "编号": "GR202242000814"
  },
  {
    "名称": "湖北省黍源农业发展有限公司",
    "编号": "GR202242000815"
  },
  {
    "名称": "湖北安一辰光电科技有限公司",
    "编号": "GR202242000816"
  },
  {
    "名称": "湖北中德焊接技术有限公司",
    "编号": "GR202242000817"
  },
  {
    "名称": "麻城市华林商砼建材有限公司",
    "编号": "GR202242000818"
  },
  {
    "名称": "武汉鸿谷致远科技有限公司",
    "编号": "GR202242000819"
  },
  {
    "名称": "宜昌金宝乐器制造有限公司",
    "编号": "GR202242000820"
  },
  {
    "名称": "武汉帆腾科技有限公司",
    "编号": "GR202242000821"
  },
  {
    "名称": "湖北麻城鑫蓝翔石业有限公司",
    "编号": "GR202242000822"
  },
  {
    "名称": "随州市安康玻璃制品有限公司",
    "编号": "GR202242000823"
  },
  {
    "名称": "襄阳天盾科技实业有限公司",
    "编号": "GR202242000824"
  },
  {
    "名称": "湖北双航机电装备科技有限公司",
    "编号": "GR202242000825"
  },
  {
    "名称": "武汉丰普科技股份有限公司",
    "编号": "GR202242000826"
  },
  {
    "名称": "盛火（湖北）农业科技有限公司",
    "编号": "GR202242000827"
  },
  {
    "名称": "中电华骋科技有限公司",
    "编号": "GR202242000828"
  },
  {
    "名称": "湖北兆盈嘉泰精密科技有限公司",
    "编号": "GR202242000829"
  },
  {
    "名称": "湖北江宸新能源科技有限公司",
    "编号": "GR202242000830"
  },
  {
    "名称": "湖北宝源木业有限公司",
    "编号": "GR202242000831"
  },
  {
    "名称": "湖北五方光电股份有限公司",
    "编号": "GR202242000832"
  },
  {
    "名称": "黄石博威翔自动化设备有限公司",
    "编号": "GR202242000833"
  },
  {
    "名称": "湖北顺富医疗器械科技有限公司",
    "编号": "GR202242000834"
  },
  {
    "名称": "武汉森澜生物科技有限公司",
    "编号": "GR202242000835"
  },
  {
    "名称": "中科烽云（武汉）信息科技有限公司",
    "编号": "GR202242000836"
  },
  {
    "名称": "湖北天泰辐照股份有限公司",
    "编号": "GR202242000837"
  },
  {
    "名称": "湖北思源水务工程技术有限公司",
    "编号": "GR202242000838"
  },
  {
    "名称": "武汉市中润精细化学品有限公司",
    "编号": "GR202242000839"
  },
  {
    "名称": "武汉蝶舞领秀公关策划咨询有限公司",
    "编号": "GR202242000840"
  },
  {
    "名称": "湖北辉图工业装备有限公司",
    "编号": "GR202242000841"
  },
  {
    "名称": "武汉豪铭电力科技有限公司",
    "编号": "GR202242000842"
  },
  {
    "名称": "襄阳东昇机械有限公司",
    "编号": "GR202242000843"
  },
  {
    "名称": "湖北顺合装备科技股份有限公司",
    "编号": "GR202242000844"
  },
  {
    "名称": "湖北天顺生态环境科技有限公司",
    "编号": "GR202242000845"
  },
  {
    "名称": "湖北蓝锐时代科技有限公司",
    "编号": "GR202242000846"
  },
  {
    "名称": "南漳富元鼎航空器材配件有限公司",
    "编号": "GR202242000847"
  },
  {
    "名称": "枣阳制胜宝汽车零部件有限公司",
    "编号": "GR202242000848"
  },
  {
    "名称": "湖北傅阿姨食品股份有限公司",
    "编号": "GR202242000849"
  },
  {
    "名称": "湖北嘉一三维高科股份有限公司",
    "编号": "GR202242000850"
  },
  {
    "名称": "武汉宏远天成科技有限公司",
    "编号": "GR202242000851"
  },
  {
    "名称": "武汉天烁激光有限公司",
    "编号": "GR202242000852"
  },
  {
    "名称": "湖北赛沃斯网络科技有限公司",
    "编号": "GR202242000853"
  },
  {
    "名称": "湖北众越信息技术有限公司",
    "编号": "GR202242000854"
  },
  {
    "名称": "武汉星迪工贸有限公司",
    "编号": "GR202242000855"
  },
  {
    "名称": "荆门林达新材料科技股份有限公司",
    "编号": "GR202242000856"
  },
  {
    "名称": "湖北亿家艾生物科技有限公司",
    "编号": "GR202242000857"
  },
  {
    "名称": "湖北统领塑胶科技有限公司",
    "编号": "GR202242000858"
  },
  {
    "名称": "武汉恒电高测电气有限公司",
    "编号": "GR202242000859"
  },
  {
    "名称": "武汉华柏环保科技有限公司",
    "编号": "GR202242000860"
  },
  {
    "名称": "武汉市依翎针织有限责任公司",
    "编号": "GR202242000861"
  },
  {
    "名称": "潜江市新龙玻璃有限责任公司",
    "编号": "GR202242000862"
  },
  {
    "名称": "武汉市海泰机械有限公司",
    "编号": "GR202242000863"
  },
  {
    "名称": "湖北荣梦环保科技有限公司",
    "编号": "GR202242000864"
  },
  {
    "名称": "黄石市钜晟重型汽车配件有限公司",
    "编号": "GR202242000865"
  },
  {
    "名称": "武汉卓凡高科信息技术有限公司",
    "编号": "GR202242000866"
  },
  {
    "名称": "湖北瑞兴铝塑模板科技有限公司",
    "编号": "GR202242000867"
  },
  {
    "名称": "武汉珈安消防技术服务有限公司",
    "编号": "GR202242000868"
  },
  {
    "名称": "襄阳康劲动力科技有限公司",
    "编号": "GR202242000869"
  },
  {
    "名称": "襄阳天力达机电工程有限公司",
    "编号": "GR202242000870"
  },
  {
    "名称": "钟祥市进鑫纺织有限公司",
    "编号": "GR202242000871"
  },
  {
    "名称": "湖北众宇电工材料有限公司",
    "编号": "GR202242000872"
  },
  {
    "名称": "红安县红友机耕船有限公司",
    "编号": "GR202242000873"
  },
  {
    "名称": "湖北宝联石材有限公司",
    "编号": "GR202242000874"
  },
  {
    "名称": "中国重汽集团湖北华威专用汽车有限公司",
    "编号": "GR202242000875"
  },
  {
    "名称": "力方武汉数字科技有限公司",
    "编号": "GR202242000876"
  },
  {
    "名称": "湖北元天工程有限公司",
    "编号": "GR202242000877"
  },
  {
    "名称": "湖北绿城体育产业有限公司",
    "编号": "GR202242000878"
  },
  {
    "名称": "武汉一起跳动科技有限公司",
    "编号": "GR202242000879"
  },
  {
    "名称": "湖北云道网络科技有限公司",
    "编号": "GR202242000880"
  },
  {
    "名称": "武汉华大教师教育发展研究院有限公司",
    "编号": "GR202242000881"
  },
  {
    "名称": "十堰普瑞实业有限公司",
    "编号": "GR202242000882"
  },
  {
    "名称": "湖北华震新材料有限公司",
    "编号": "GR202242000883"
  },
  {
    "名称": "武汉市华敏智造科技有限责任公司",
    "编号": "GR202242000884"
  },
  {
    "名称": "咸宁在线网络有限公司",
    "编号": "GR202242000885"
  },
  {
    "名称": "湖北微硕新材料有限公司",
    "编号": "GR202242000886"
  },
  {
    "名称": "湖北三雄科技发展有限公司",
    "编号": "GR202242000887"
  },
  {
    "名称": "湖北腾龙种业有限公司",
    "编号": "GR202242000888"
  },
  {
    "名称": "武汉源威智能科技有限公司",
    "编号": "GR202242000889"
  },
  {
    "名称": "荆门法麦克斯农业科技有限公司",
    "编号": "GR202242000890"
  },
  {
    "名称": "武汉翱飞科技有限公司",
    "编号": "GR202242000891"
  },
  {
    "名称": "大山合集团保康绿生现代农业有限公司",
    "编号": "GR202242000892"
  },
  {
    "名称": "湖北辰朗科技有限公司",
    "编号": "GR202242000893"
  },
  {
    "名称": "湖北志特新材料科技有限公司",
    "编号": "GR202242000894"
  },
  {
    "名称": "武汉华讯世纪文化传媒有限公司",
    "编号": "GR202242000895"
  },
  {
    "名称": "武汉力登维汽车部件有限公司",
    "编号": "GR202242000896"
  },
  {
    "名称": "湖北中迅长青科技有限公司",
    "编号": "GR202242000897"
  },
  {
    "名称": "湖北新塔医疗科技有限公司",
    "编号": "GR202242000898"
  },
  {
    "名称": "湖北骐盛医药科技有限公司",
    "编号": "GR202242000899"
  },
  {
    "名称": "武汉亚为电子科技有限公司",
    "编号": "GR202242000900"
  },
  {
    "名称": "武汉飞能达激光技术有限公司",
    "编号": "GR202242000901"
  },
  {
    "名称": "武汉昱辉鸿科技有限公司",
    "编号": "GR202242000902"
  },
  {
    "名称": "湖北擎岩智能桩工有限公司",
    "编号": "GR202242000903"
  },
  {
    "名称": "湖北宜化集团化工机械设备制造安装有限公司",
    "编号": "GR202242000904"
  },
  {
    "名称": "湖北时迈绿化工程有限公司",
    "编号": "GR202242000905"
  },
  {
    "名称": "湖北冠众通科技有限公司",
    "编号": "GR202242000906"
  },
  {
    "名称": "葵花药业集团湖北武当有限公司",
    "编号": "GR202242000907"
  },
  {
    "名称": "武汉和青源环保科技有限公司",
    "编号": "GR202242000908"
  },
  {
    "名称": "宜昌兴越新材料有限公司",
    "编号": "GR202242000909"
  },
  {
    "名称": "武汉柏思特智能科技有限公司",
    "编号": "GR202242000910"
  },
  {
    "名称": "武汉致一检测技术有限公司",
    "编号": "GR202242000911"
  },
  {
    "名称": "湖北仙彩色母粒有限公司",
    "编号": "GR202242000912"
  },
  {
    "名称": "湖北开明高新科技有限公司",
    "编号": "GR202242000913"
  },
  {
    "名称": "湖北高韬智电科技有限公司",
    "编号": "GR202242000914"
  },
  {
    "名称": "武汉织云软件有限公司",
    "编号": "GR202242000915"
  },
  {
    "名称": "湖北神工动画设计有限公司",
    "编号": "GR202242000916"
  },
  {
    "名称": "武汉九创科技有限公司",
    "编号": "GR202242000917"
  },
  {
    "名称": "湖北四喜达新型材料有限公司",
    "编号": "GR202242000918"
  },
  {
    "名称": "武汉民丰科技有限公司",
    "编号": "GR202242000919"
  },
  {
    "名称": "武汉网佳光电子技术有限公司",
    "编号": "GR202242000920"
  },
  {
    "名称": "湖北森鑫汽车零部件有限公司",
    "编号": "GR202242000921"
  },
  {
    "名称": "湖北中交航胜科技有限公司",
    "编号": "GR202242000922"
  },
  {
    "名称": "湖北回盛生物科技有限公司",
    "编号": "GR202242000923"
  },
  {
    "名称": "湖北永晟农业科技有限公司",
    "编号": "GR202242000924"
  },
  {
    "名称": "湖北汉高工程咨询有限公司",
    "编号": "GR202242000925"
  },
  {
    "名称": "湖北数华科技有限公司",
    "编号": "GR202242000926"
  },
  {
    "名称": "十堰冠达汽车零部件有限公司",
    "编号": "GR202242000927"
  },
  {
    "名称": "枣阳宁远电器设备有限公司",
    "编号": "GR202242000928"
  },
  {
    "名称": "湖北洋田塑料制品有限公司",
    "编号": "GR202242000929"
  },
  {
    "名称": "武汉联合药业有限责任公司",
    "编号": "GR202242000930"
  },
  {
    "名称": "湖北允升科技工业园有限公司",
    "编号": "GR202242000931"
  },
  {
    "名称": "钟祥市鑫宏祥锌钢科技有限公司",
    "编号": "GR202242000932"
  },
  {
    "名称": "襄阳司方德电子有限公司",
    "编号": "GR202242000933"
  },
  {
    "名称": "武汉华中航空测控技术有限公司",
    "编号": "GR202242000934"
  },
  {
    "名称": "湖北赤焰热能工程有限公司",
    "编号": "GR202242000935"
  },
  {
    "名称": "襄阳高鑫达机电技术有限公司",
    "编号": "GR202242000936"
  },
  {
    "名称": "武汉轻度科技有限公司",
    "编号": "GR202242000937"
  },
  {
    "名称": "湖北居久安新型节能材料工程股份有限公司",
    "编号": "GR202242000938"
  },
  {
    "名称": "湖北易净清洁用品有限公司",
    "编号": "GR202242000939"
  },
  {
    "名称": "湖北道地药材科技有限公司",
    "编号": "GR202242000940"
  },
  {
    "名称": "湖北聚易起信息科技有限公司",
    "编号": "GR202242000941"
  },
  {
    "名称": "湖北金玉兰医药科技有限公司",
    "编号": "GR202242000942"
  },
  {
    "名称": "湖北雅比家用纺织品有限公司",
    "编号": "GR202242000943"
  },
  {
    "名称": "湖北租呗网络信息技术有限公司",
    "编号": "GR202242000944"
  },
  {
    "名称": "麻城市通达阻尼材料股份有限公司",
    "编号": "GR202242000945"
  },
  {
    "名称": "湖北力威汽车有限公司",
    "编号": "GR202242000946"
  },
  {
    "名称": "格瑞复斯（武汉）生化科技股份有限公司",
    "编号": "GR202242000947"
  },
  {
    "名称": "湖北壹想联合电子科技有限公司",
    "编号": "GR202242000948"
  },
  {
    "名称": "武汉泽想教育科技有限公司",
    "编号": "GR202242000949"
  },
  {
    "名称": "湖北恒晟石化设备有限公司",
    "编号": "GR202242000950"
  },
  {
    "名称": "黄冈市维科曼医用材料有限责任公司",
    "编号": "GR202242000951"
  },
  {
    "名称": "湖北鑫鹰环保科技股份有限公司",
    "编号": "GR202242000952"
  },
  {
    "名称": "湖北乌山春茶业股份有限公司",
    "编号": "GR202242000953"
  },
  {
    "名称": "武汉力兴（火炬）电源有限公司",
    "编号": "GR202242000954"
  },
  {
    "名称": "武汉尚高软件有限公司",
    "编号": "GR202242000955"
  },
  {
    "名称": "武汉宏利达机电工程有限公司",
    "编号": "GR202242000956"
  },
  {
    "名称": "武汉智斗科技有限公司",
    "编号": "GR202242000957"
  },
  {
    "名称": "武汉三澍精密科技有限公司",
    "编号": "GR202242000958"
  },
  {
    "名称": "武汉幻城经纬科技有限公司",
    "编号": "GR202242000959"
  },
  {
    "名称": "丹江口市丰达工贸有限公司",
    "编号": "GR202242000960"
  },
  {
    "名称": "枝江盛懋船业有限公司",
    "编号": "GR202242000961"
  },
  {
    "名称": "湖北豪丰农业装备有限公司",
    "编号": "GR202242000962"
  },
  {
    "名称": "湖北中科铜箔科技有限公司",
    "编号": "GR202242000963"
  },
  {
    "名称": "武汉安扬激光技术股份有限公司",
    "编号": "GR202242000964"
  },
  {
    "名称": "宏图天逸（武汉）科技有限公司",
    "编号": "GR202242000965"
  },
  {
    "名称": "咸宁市荣大防腐技术有限责任公司",
    "编号": "GR202242000966"
  },
  {
    "名称": "湖北天冠环保工程技术股份有限公司",
    "编号": "GR202242000967"
  },
  {
    "名称": "湖北优泰特种纸有限公司",
    "编号": "GR202242000968"
  },
  {
    "名称": "湖北博盛数字教育服务有限公司",
    "编号": "GR202242000969"
  },
  {
    "名称": "湖北鸿运万鑫建筑工程有限公司",
    "编号": "GR202242000970"
  },
  {
    "名称": "武汉广能电力工程有限公司",
    "编号": "GR202242000971"
  },
  {
    "名称": "襄阳驰瑞机械有限公司",
    "编号": "GR202242000972"
  },
  {
    "名称": "宜昌协鸿重工机械有限公司",
    "编号": "GR202242000973"
  },
  {
    "名称": "武汉烨禹森汽车技术有限公司",
    "编号": "GR202242000974"
  },
  {
    "名称": "湖北诚远专用汽车有限公司",
    "编号": "GR202242000975"
  },
  {
    "名称": "普利技术潜江有限公司",
    "编号": "GR202242000976"
  },
  {
    "名称": "武汉圣熔铸造科技有限公司",
    "编号": "GR202242000977"
  },
  {
    "名称": "精欧控制阀门集团有限公司",
    "编号": "GR202242000978"
  },
  {
    "名称": "武汉轻购云科技有限公司",
    "编号": "GR202242000979"
  },
  {
    "名称": "黄石建华机械股份有限公司",
    "编号": "GR202242000980"
  },
  {
    "名称": "湖北元拓铝合金模架制造有限公司",
    "编号": "GR202242000981"
  },
  {
    "名称": "湖北天奇力帝汽车零部件有限公司",
    "编号": "GR202242000982"
  },
  {
    "名称": "荆州市江陵申达电气有限公司",
    "编号": "GR202242000983"
  },
  {
    "名称": "湖北省慧田生物科技有限公司",
    "编号": "GR202242000984"
  },
  {
    "名称": "中信数智（武汉）科技有限公司",
    "编号": "GR202242000985"
  },
  {
    "名称": "湖北智欧科技有限公司",
    "编号": "GR202242000986"
  },
  {
    "名称": "湖北公信安全科技有限公司",
    "编号": "GR202242000987"
  },
  {
    "名称": "武汉久胜机械科技有限公司",
    "编号": "GR202242000988"
  },
  {
    "名称": "湖北米泊智能科技有限公司",
    "编号": "GR202242000989"
  },
  {
    "名称": "武汉智奥欣科技有限公司",
    "编号": "GR202242000990"
  },
  {
    "名称": "武汉市幸运坐标信息技术有限公司",
    "编号": "GR202242000991"
  },
  {
    "名称": "湖北天宜机械股份有限公司",
    "编号": "GR202242000992"
  },
  {
    "名称": "湖北浠玻实业有限公司",
    "编号": "GR202242000993"
  },
  {
    "名称": "武汉国之安科技发展有限公司",
    "编号": "GR202242000994"
  },
  {
    "名称": "湖北国恒金缘通讯有限公司",
    "编号": "GR202242000995"
  },
  {
    "名称": "恒智普惠（武汉）数字科技有限公司",
    "编号": "GR202242000996"
  },
  {
    "名称": "黄石市中天机械制造有限责任公司",
    "编号": "GR202242000997"
  },
  {
    "名称": "襄阳久卓机械科技有限公司",
    "编号": "GR202242000998"
  },
  {
    "名称": "武汉九龙云天信息科技有限公司",
    "编号": "GR202242000999"
  },
  {
    "名称": "湖北罗黛蒂工贸股份有限公司",
    "编号": "GR202242001000"
  },
  {
    "名称": "枣阳市博润纺织有限公司",
    "编号": "GR202242001001"
  },
  {
    "名称": "嘉施利（应城）化肥有限公司",
    "编号": "GR202242001002"
  },
  {
    "名称": "荆门市国弘模具有限公司",
    "编号": "GR202242001003"
  },
  {
    "名称": "湖北英瑞德信息技术有限公司",
    "编号": "GR202242001004"
  },
  {
    "名称": "武汉唯众智创科技有限公司",
    "编号": "GR202242001005"
  },
  {
    "名称": "湖北凌晟药业股份有限公司",
    "编号": "GR202242001006"
  },
  {
    "名称": "湖北恒贸茶油有限公司",
    "编号": "GR202242001007"
  },
  {
    "名称": "湖北龙翔生物制品发展有限公司",
    "编号": "GR202242001008"
  },
  {
    "名称": "武汉精熔潮电气科技有限公司",
    "编号": "GR202242001009"
  },
  {
    "名称": "湖北创梦天地文化传播有限公司",
    "编号": "GR202242001010"
  },
  {
    "名称": "咸丰县炬鑫矿业有限公司",
    "编号": "GR202242001011"
  },
  {
    "名称": "湖北翔农化肥有限公司",
    "编号": "GR202242001012"
  },
  {
    "名称": "湖北剑威电气科技有限公司",
    "编号": "GR202242001013"
  },
  {
    "名称": "宜昌瑞纳网络科技有限公司",
    "编号": "GR202242001014"
  },
  {
    "名称": "湖北蔚蓝通用航空科技股份有限公司",
    "编号": "GR202242001015"
  },
  {
    "名称": "绿拓（湖北）资源循环利用有限公司",
    "编号": "GR202242001016"
  },
  {
    "名称": "武汉银色工坊文化科技有限公司",
    "编号": "GR202242001017"
  },
  {
    "名称": "湖北振启科技有限公司",
    "编号": "GR202242001018"
  },
  {
    "名称": "武汉大泽乡云科技有限公司",
    "编号": "GR202242001019"
  },
  {
    "名称": "湖北碧拓新材料科技有限公司",
    "编号": "GR202242001020"
  },
  {
    "名称": "湖北天力汽车零部件制造有限公司",
    "编号": "GR202242001021"
  },
  {
    "名称": "十堰市中仁汽车零部件有限公司",
    "编号": "GR202242001022"
  },
  {
    "名称": "湖北晶华电子科技有限公司",
    "编号": "GR202242001023"
  },
  {
    "名称": "武汉上大恒精热处理技术有限公司",
    "编号": "GR202242001024"
  },
  {
    "名称": "襄阳程河工艺品有限责任公司",
    "编号": "GR202242001025"
  },
  {
    "名称": "湖北鑫亚格环境建设有限公司",
    "编号": "GR202242001026"
  },
  {
    "名称": "湖北净天环保设备有限公司",
    "编号": "GR202242001027"
  },
  {
    "名称": "襄阳博力精工机械有限公司",
    "编号": "GR202242001028"
  },
  {
    "名称": "武汉瑞泽园生物环保科技股份有限公司",
    "编号": "GR202242001029"
  },
  {
    "名称": "湖北奥嘉达模具科技有限公司",
    "编号": "GR202242001030"
  },
  {
    "名称": "宜昌峡能电科能源科技有限公司",
    "编号": "GR202242001031"
  },
  {
    "名称": "湖北康晨安宝矿业设备有限责任公司",
    "编号": "GR202242001032"
  },
  {
    "名称": "建始县节龙工贸有限责任公司",
    "编号": "GR202242001033"
  },
  {
    "名称": "湖北萌升农业科技有限公司",
    "编号": "GR202242001034"
  },
  {
    "名称": "湖北金恒昌纺织有限公司",
    "编号": "GR202242001035"
  },
  {
    "名称": "武汉泽瑞网科信息技术有限公司",
    "编号": "GR202242001036"
  },
  {
    "名称": "宜昌市方源水利水电工程有限公司",
    "编号": "GR202242001037"
  },
  {
    "名称": "大冶祺峰动力制冷设备有限公司",
    "编号": "GR202242001038"
  },
  {
    "名称": "湖北省鄂西地质勘察设计院有限公司",
    "编号": "GR202242001039"
  },
  {
    "名称": "湖北邦鑫纺织科技实业有限公司",
    "编号": "GR202242001040"
  },
  {
    "名称": "赤壁神山兴农科技有限公司",
    "编号": "GR202242001041"
  },
  {
    "名称": "湖北中电德力电气有限公司",
    "编号": "GR202242001042"
  },
  {
    "名称": "湖北龙王垭茶业有限公司",
    "编号": "GR202242001043"
  },
  {
    "名称": "湖北先驰交通装备有限公司",
    "编号": "GR202242001044"
  },
  {
    "名称": "湖北卓众之众防水材料有限公司",
    "编号": "GR202242001045"
  },
  {
    "名称": "武汉益拓科技有限公司",
    "编号": "GR202242001046"
  },
  {
    "名称": "宜昌宜信通科技有限公司",
    "编号": "GR202242001047"
  },
  {
    "名称": "湖北华固高分子材料有限公司",
    "编号": "GR202242001048"
  },
  {
    "名称": "湖北绿建杭萧钢结构有限公司",
    "编号": "GR202242001049"
  },
  {
    "名称": "大冶市古冶玻璃有限公司",
    "编号": "GR202242001050"
  },
  {
    "名称": "湖北卓尔雪龙纺织有限公司",
    "编号": "GR202242001051"
  },
  {
    "名称": "武汉桃乐茜科技有限公司",
    "编号": "GR202242001052"
  },
  {
    "名称": "恩施西特优生态农业开发有限公司",
    "编号": "GR202242001053"
  },
  {
    "名称": "鄂州品泓生物科技有限公司",
    "编号": "GR202242001054"
  },
  {
    "名称": "湖北奕宏精密制造有限公司",
    "编号": "GR202242001055"
  },
  {
    "名称": "湖北楚龙兴家具股份有限公司",
    "编号": "GR202242001056"
  },
  {
    "名称": "武汉九中机械有限公司",
    "编号": "GR202242001057"
  },
  {
    "名称": "湖北乾奥建设工程有限公司",
    "编号": "GR202242001058"
  },
  {
    "名称": "宜昌三一机械有限公司",
    "编号": "GR202242001059"
  },
  {
    "名称": "武汉金中厨环保科技有限公司",
    "编号": "GR202242001060"
  },
  {
    "名称": "天门顺康纸业有限公司",
    "编号": "GR202242001061"
  },
  {
    "名称": "湖北省麻城市和丰精密机械有限公司",
    "编号": "GR202242001062"
  },
  {
    "名称": "九州通医疗信息科技（武汉）有限公司",
    "编号": "GR202242001063"
  },
  {
    "名称": "湖北广发纸业有限公司",
    "编号": "GR202242001064"
  },
  {
    "名称": "湖北创投汇网络科技有限公司",
    "编号": "GR202242001065"
  },
  {
    "名称": "湖北新钢环保科技有限公司",
    "编号": "GR202242001066"
  },
  {
    "名称": "武汉捷隆汽车电动转向系统有限公司",
    "编号": "GR202242001067"
  },
  {
    "名称": "武汉新视点信息技术有限公司",
    "编号": "GR202242001068"
  },
  {
    "名称": "湖北楚隆智能科技有限公司",
    "编号": "GR202242001069"
  },
  {
    "名称": "武汉方的猫科技有限公司",
    "编号": "GR202242001070"
  },
  {
    "名称": "黄石斯普机电有限公司",
    "编号": "GR202242001071"
  },
  {
    "名称": "军创大数据发展有限公司",
    "编号": "GR202242001072"
  },
  {
    "名称": "麻城锦顺石业开发有限公司",
    "编号": "GR202242001073"
  },
  {
    "名称": "武汉昆泽机电设备有限公司",
    "编号": "GR202242001074"
  },
  {
    "名称": "湖北华鑫光电有限公司",
    "编号": "GR202242001075"
  },
  {
    "名称": "武汉德科达自动化有限公司",
    "编号": "GR202242001076"
  },
  {
    "名称": "武汉鑫泽宇防水材料科技有限公司",
    "编号": "GR202242001077"
  },
  {
    "名称": "三信希尔福科技（武汉）有限公司",
    "编号": "GR202242001078"
  },
  {
    "名称": "宜昌顺德建设工程检测有限公司",
    "编号": "GR202242001079"
  },
  {
    "名称": "荷斯（武汉）水系统有限公司",
    "编号": "GR202242001080"
  },
  {
    "名称": "武汉佑康科技有限公司",
    "编号": "GR202242001081"
  },
  {
    "名称": "武汉麦鑫利药业有限公司",
    "编号": "GR202242001082"
  },
  {
    "名称": "湖北惠大臭氧生物科技股份有限公司",
    "编号": "GR202242001083"
  },
  {
    "名称": "武汉军安信达智能科技有限公司",
    "编号": "GR202242001084"
  },
  {
    "名称": "宜都力华新型建材有限公司",
    "编号": "GR202242001085"
  },
  {
    "名称": "湖北汇合专用汽车有限公司",
    "编号": "GR202242001086"
  },
  {
    "名称": "湖北海巍云科技有限公司",
    "编号": "GR202242001087"
  },
  {
    "名称": "武汉中博绿亚生物科技有限公司",
    "编号": "GR202242001088"
  },
  {
    "名称": "荆州市赛猛石油机械股份有限公司",
    "编号": "GR202242001089"
  },
  {
    "名称": "武汉鸿誉翔模具科技有限公司",
    "编号": "GR202242001090"
  },
  {
    "名称": "罗博科技（武汉）有限公司",
    "编号": "GR202242001091"
  },
  {
    "名称": "武汉市风奥科技股份有限公司",
    "编号": "GR202242001092"
  },
  {
    "名称": "武汉擎光创智光电技术有限公司",
    "编号": "GR202242001093"
  },
  {
    "名称": "武汉中信互联科技有限公司",
    "编号": "GR202242001094"
  },
  {
    "名称": "湖北瑞力汽车有限公司",
    "编号": "GR202242001095"
  },
  {
    "名称": "湖北溢德科技股份有限公司",
    "编号": "GR202242001096"
  },
  {
    "名称": "武汉水院电气有限责任公司",
    "编号": "GR202242001097"
  },
  {
    "名称": "武汉市恺美达网络科技有限公司",
    "编号": "GR202242001098"
  },
  {
    "名称": "武汉易驹所科技有限公司",
    "编号": "GR202242001099"
  },
  {
    "名称": "武汉谦豫科技有限公司",
    "编号": "GR202242001100"
  },
  {
    "名称": "湖北华窑中盟窑炉设备有限公司",
    "编号": "GR202242001101"
  },
  {
    "名称": "十堰市惠文药业有限公司",
    "编号": "GR202242001102"
  },
  {
    "名称": "秭归县开明建筑有限责任公司",
    "编号": "GR202242001103"
  },
  {
    "名称": "湖北永兴机电科技工程有限公司",
    "编号": "GR202242001104"
  },
  {
    "名称": "襄阳欣天宸环保技术有限公司",
    "编号": "GR202242001105"
  },
  {
    "名称": "武汉智凯科技有限公司",
    "编号": "GR202242001106"
  },
  {
    "名称": "武汉鸿义信息科技有限公司",
    "编号": "GR202242001107"
  },
  {
    "名称": "武汉子序科技股份有限公司",
    "编号": "GR202242001108"
  },
  {
    "名称": "湖北迈创专用车有限公司",
    "编号": "GR202242001109"
  },
  {
    "名称": "武汉市巴斯特管业科技有限公司",
    "编号": "GR202242001110"
  },
  {
    "名称": "武汉秀影互动科技有限公司",
    "编号": "GR202242001111"
  },
  {
    "名称": "湖北睿赛新能源科技有限公司",
    "编号": "GR202242001112"
  },
  {
    "名称": "荆门志远环保设备有限公司",
    "编号": "GR202242001113"
  },
  {
    "名称": "湖北太宝科技有限公司",
    "编号": "GR202242001114"
  },
  {
    "名称": "安陆市华誉金属网机制造有限公司",
    "编号": "GR202242001115"
  },
  {
    "名称": "湖北曲辰农业科技有限公司",
    "编号": "GR202242001116"
  },
  {
    "名称": "武汉泰豪电源技术有限公司",
    "编号": "GR202242001117"
  },
  {
    "名称": "湖北嘉鑫环保新材料科技有限公司",
    "编号": "GR202242001118"
  },
  {
    "名称": "武汉星宇纺机有限公司",
    "编号": "GR202242001119"
  },
  {
    "名称": "武汉中人瑞众汽车零部件产业有限公司",
    "编号": "GR202242001120"
  },
  {
    "名称": "湖北灵慧云网络科技有限公司",
    "编号": "GR202242001121"
  },
  {
    "名称": "湖北华钦麒科技有限公司",
    "编号": "GR202242001122"
  },
  {
    "名称": "武汉善为信息科技有限公司",
    "编号": "GR202242001123"
  },
  {
    "名称": "武汉弘康健基因诊断技术有限公司",
    "编号": "GR202242001124"
  },
  {
    "名称": "武汉大博海消防智能科技有限公司",
    "编号": "GR202242001125"
  },
  {
    "名称": "武汉中天华晨科技有限公司",
    "编号": "GR202242001126"
  },
  {
    "名称": "湖北江升新材料有限公司",
    "编号": "GR202242001127"
  },
  {
    "名称": "湖北圣堃环保科技股份有限公司",
    "编号": "GR202242001128"
  },
  {
    "名称": "湖北燕兴建筑机械有限公司",
    "编号": "GR202242001129"
  },
  {
    "名称": "武汉云图互联科技股份有限公司",
    "编号": "GR202242001130"
  },
  {
    "名称": "武汉智化科技有限公司",
    "编号": "GR202242001131"
  },
  {
    "名称": "武汉凯通环保科技有限公司",
    "编号": "GR202242001132"
  },
  {
    "名称": "宜昌三泰科技有限公司",
    "编号": "GR202242001133"
  },
  {
    "名称": "湖北三固建材科技有限公司",
    "编号": "GR202242001134"
  },
  {
    "名称": "丹江口市旭永工贸有限公司",
    "编号": "GR202242001135"
  },
  {
    "名称": "宜昌市新丰机电设备制造有限公司",
    "编号": "GR202242001136"
  },
  {
    "名称": "湖北恒意达汽车部件有限公司",
    "编号": "GR202242001137"
  },
  {
    "名称": "湖北华一专用汽车有限公司",
    "编号": "GR202242001138"
  },
  {
    "名称": "湖北亚美环保工程有限公司",
    "编号": "GR202242001139"
  },
  {
    "名称": "十堰科威机电装备股份有限公司",
    "编号": "GR202242001140"
  },
  {
    "名称": "湖北福恩鞋业有限公司",
    "编号": "GR202242001141"
  },
  {
    "名称": "黄石山立包装设备有限公司",
    "编号": "GR202242001142"
  },
  {
    "名称": "襄阳市一嘉仓储货架设备有限公司",
    "编号": "GR202242001143"
  },
  {
    "名称": "丹江口市益国塑胶有限公司",
    "编号": "GR202242001144"
  },
  {
    "名称": "湖北霸衫科技有限公司",
    "编号": "GR202242001145"
  },
  {
    "名称": "武汉朗德电气有限公司",
    "编号": "GR202242001146"
  },
  {
    "名称": "湖北赛尔新能源材料有限公司",
    "编号": "GR202242001147"
  },
  {
    "名称": "湖北安众科技有限公司",
    "编号": "GR202242001148"
  },
  {
    "名称": "宜昌昌耀变压器有限公司",
    "编号": "GR202242001149"
  },
  {
    "名称": "武汉诺威奇科技有限公司",
    "编号": "GR202242001150"
  },
  {
    "名称": "武汉炎荣压铸件有限公司",
    "编号": "GR202242001151"
  },
  {
    "名称": "武汉新天地塑木包装有限公司",
    "编号": "GR202242001152"
  },
  {
    "名称": "湖北江环环保科技有限公司",
    "编号": "GR202242001153"
  },
  {
    "名称": "湖北江山华科数字设备科技有限公司",
    "编号": "GR202242001154"
  },
  {
    "名称": "中冶南方武汉工程咨询管理有限公司",
    "编号": "GR202242001155"
  },
  {
    "名称": "黄石市佳兴生物科技有限公司",
    "编号": "GR202242001156"
  },
  {
    "名称": "湖北龙之泉农业发展股份有限公司",
    "编号": "GR202242001157"
  },
  {
    "名称": "湖北欧雷玛科技有限公司",
    "编号": "GR202242001158"
  },
  {
    "名称": "武汉纵横天地空间信息技术有限公司",
    "编号": "GR202242001159"
  },
  {
    "名称": "湖北奕蕴科技有限公司",
    "编号": "GR202242001160"
  },
  {
    "名称": "麻城市福兴石材工艺制品有限公司",
    "编号": "GR202242001161"
  },
  {
    "名称": "武汉迈谷菲网络科技有限公司",
    "编号": "GR202242001162"
  },
  {
    "名称": "湖北土老憨生态农业科技股份有限公司",
    "编号": "GR202242001163"
  },
  {
    "名称": "谱线光电科技（武汉）有限公司",
    "编号": "GR202242001164"
  },
  {
    "名称": "湖北钟格塑料管有限公司",
    "编号": "GR202242001165"
  },
  {
    "名称": "武汉美佳源环境工程有限公司",
    "编号": "GR202242001166"
  },
  {
    "名称": "武汉弘景医疗科技发展有限公司",
    "编号": "GR202242001167"
  },
  {
    "名称": "武汉出山科技有限公司",
    "编号": "GR202242001168"
  },
  {
    "名称": "襄阳市建恒电气有限公司",
    "编号": "GR202242001169"
  },
  {
    "名称": "潜江市昌云纺织有限公司",
    "编号": "GR202242001170"
  },
  {
    "名称": "鄂州三江东顺船业有限公司",
    "编号": "GR202242001171"
  },
  {
    "名称": "湖北腾辰科技股份有限公司",
    "编号": "GR202242001172"
  },
  {
    "名称": "武汉博科瑞工业科技开发有限公司",
    "编号": "GR202242001173"
  },
  {
    "名称": "宜昌泽美新材料有限公司",
    "编号": "GR202242001174"
  },
  {
    "名称": "湖北瑞邦石化装备科技有限公司",
    "编号": "GR202242001175"
  },
  {
    "名称": "武汉中和车身股份有限公司",
    "编号": "GR202242001176"
  },
  {
    "名称": "武汉慧友佳华电子有限公司",
    "编号": "GR202242001177"
  },
  {
    "名称": "武汉尚网互联科技有限公司",
    "编号": "GR202242001178"
  },
  {
    "名称": "武汉星创优品科技有限公司",
    "编号": "GR202242001179"
  },
  {
    "名称": "武汉易瑞信息技术股份有限公司",
    "编号": "GR202242001180"
  },
  {
    "名称": "武汉楚天艾科生物科技集团有限公司",
    "编号": "GR202242001181"
  },
  {
    "名称": "武汉德玛吉展览有限公司",
    "编号": "GR202242001182"
  },
  {
    "名称": "湖北邦之德牧业科技有限公司",
    "编号": "GR202242001183"
  },
  {
    "名称": "枣阳市高科化工有限公司",
    "编号": "GR202242001184"
  },
  {
    "名称": "武汉时胜生物科技有限公司",
    "编号": "GR202242001185"
  },
  {
    "名称": "武汉恒安土石方工程有限公司",
    "编号": "GR202242001186"
  },
  {
    "名称": "湖北鑫汉源地毯有限公司",
    "编号": "GR202242001187"
  },
  {
    "名称": "英山世强工具有限公司",
    "编号": "GR202242001188"
  },
  {
    "名称": "湖北数简科技有限公司",
    "编号": "GR202242001189"
  },
  {
    "名称": "湖北民大农牧发展有限公司",
    "编号": "GR202242001190"
  },
  {
    "名称": "武汉正雅科技有限公司",
    "编号": "GR202242001191"
  },
  {
    "名称": "武汉顺威赛特工程塑料有限公司",
    "编号": "GR202242001192"
  },
  {
    "名称": "博云时代（武汉）信息技术有限公司",
    "编号": "GR202242001193"
  },
  {
    "名称": "湖北广盛建筑产业化科技有限公司",
    "编号": "GR202242001194"
  },
  {
    "名称": "埃斯顿（湖北）机器人工程有限公司",
    "编号": "GR202242001195"
  },
  {
    "名称": "湖北冠誉塑料包装股份有限公司",
    "编号": "GR202242001196"
  },
  {
    "名称": "武汉特车科技工程有限公司",
    "编号": "GR202242001197"
  },
  {
    "名称": "海卓（武汉）自动化科技有限公司",
    "编号": "GR202242001198"
  },
  {
    "名称": "湖北宜美特全息科技有限公司",
    "编号": "GR202242001199"
  },
  {
    "名称": "湖北方鼎科技发展有限公司",
    "编号": "GR202242001200"
  },
  {
    "名称": "湖北康强医疗器械有限公司",
    "编号": "GR202242001201"
  },
  {
    "名称": "武汉峰岭科技有限公司",
    "编号": "GR202242001202"
  },
  {
    "名称": "武汉卓育软件开发有限公司",
    "编号": "GR202242001203"
  },
  {
    "名称": "湖北省赤壁市合力耐磨铸件机械有限公司",
    "编号": "GR202242001204"
  },
  {
    "名称": "当阳安通机动车检测有限公司",
    "编号": "GR202242001205"
  },
  {
    "名称": "武汉科云信息技术有限公司",
    "编号": "GR202242001206"
  },
  {
    "名称": "武汉球道木科技有限公司",
    "编号": "GR202242001207"
  },
  {
    "名称": "荆州市汇龙手袋有限公司",
    "编号": "GR202242001208"
  },
  {
    "名称": "武汉鸿泰消防工程有限公司",
    "编号": "GR202242001209"
  },
  {
    "名称": "湖北五环专用汽车有限公司",
    "编号": "GR202242001210"
  },
  {
    "名称": "定颖电子（黄石）有限公司",
    "编号": "GR202242001211"
  },
  {
    "名称": "湖北丰帛纺织有限公司",
    "编号": "GR202242001212"
  },
  {
    "名称": "湖北金色阳光创客教育有限公司",
    "编号": "GR202242001213"
  },
  {
    "名称": "荆州环球汽车零部件制造有限公司",
    "编号": "GR202242001214"
  },
  {
    "名称": "湖北永祥新型建材有限公司",
    "编号": "GR202242001215"
  },
  {
    "名称": "武汉军创智云科技有限公司",
    "编号": "GR202242001216"
  },
  {
    "名称": "湖北沃凯克生物科技有限公司",
    "编号": "GR202242001217"
  },
  {
    "名称": "武汉艾崴科技有限公司",
    "编号": "GR202242001218"
  },
  {
    "名称": "武汉华中创百科技有限公司",
    "编号": "GR202242001219"
  },
  {
    "名称": "武汉市承远市政工程设计有限公司",
    "编号": "GR202242001220"
  },
  {
    "名称": "湖北思腾科技有限公司",
    "编号": "GR202242001221"
  },
  {
    "名称": "武汉吉欧信海洋科技股份有限公司",
    "编号": "GR202242001222"
  },
  {
    "名称": "亿涛建设集团有限公司",
    "编号": "GR202242001223"
  },
  {
    "名称": "湖北襄测质量技术服务有限公司",
    "编号": "GR202242001224"
  },
  {
    "名称": "武汉英特瑞智能装备有限公司",
    "编号": "GR202242001225"
  },
  {
    "名称": "武汉市巧研电子科技有限公司",
    "编号": "GR202242001226"
  },
  {
    "名称": "十堰恒泽工贸有限公司",
    "编号": "GR202242001227"
  },
  {
    "名称": "武汉湘伟模塑有限公司",
    "编号": "GR202242001228"
  },
  {
    "名称": "宣恩县长腾茶业有限公司",
    "编号": "GR202242001229"
  },
  {
    "名称": "湖北东润木业有限公司",
    "编号": "GR202242001230"
  },
  {
    "名称": "武汉卓佰环境科技有限公司",
    "编号": "GR202242001231"
  },
  {
    "名称": "湖北无忧车管家网络科技服务有限公司",
    "编号": "GR202242001232"
  },
  {
    "名称": "湖北实美科技有限公司",
    "编号": "GR202242001233"
  },
  {
    "名称": "湖北雷电通智能检测技术发展有限公司",
    "编号": "GR202242001234"
  },
  {
    "名称": "武汉仲联诚鉴检测技术有限公司",
    "编号": "GR202242001235"
  },
  {
    "名称": "宜昌晟达暖通科技有限公司",
    "编号": "GR202242001236"
  },
  {
    "名称": "良品铺子营养食品有限责任公司",
    "编号": "GR202242001237"
  },
  {
    "名称": "利川市兴达商砼有限责任公司",
    "编号": "GR202242001238"
  },
  {
    "名称": "武汉华迈视通科技有限公司",
    "编号": "GR202242001239"
  },
  {
    "名称": "武汉安德信检测设备有限公司",
    "编号": "GR202242001240"
  },
  {
    "名称": "武汉光韵文化传播有限公司",
    "编号": "GR202242001241"
  },
  {
    "名称": "湖北九端茶业有限公司",
    "编号": "GR202242001242"
  },
  {
    "名称": "武汉九西新材料有限公司",
    "编号": "GR202242001243"
  },
  {
    "名称": "湖北太升包装有限公司",
    "编号": "GR202242001244"
  },
  {
    "名称": "武汉海芯船舶技术有限公司",
    "编号": "GR202242001245"
  },
  {
    "名称": "武汉华远汽车零部件有限公司",
    "编号": "GR202242001246"
  },
  {
    "名称": "武汉量子互娱科技有限公司",
    "编号": "GR202242001247"
  },
  {
    "名称": "荆州市道荣道路工程材料有限公司",
    "编号": "GR202242001248"
  },
  {
    "名称": "湖北渝楚荣久机电有限公司",
    "编号": "GR202242001249"
  },
  {
    "名称": "湖北华耀生物科技有限公司",
    "编号": "GR202242001250"
  },
  {
    "名称": "湖北致合通机械有限公司",
    "编号": "GR202242001251"
  },
  {
    "名称": "武汉梓火科技有限公司",
    "编号": "GR202242001252"
  },
  {
    "名称": "湖北福星新材料科技有限公司",
    "编号": "GR202242001253"
  },
  {
    "名称": "利川市远志中药材有限责任公司",
    "编号": "GR202242001254"
  },
  {
    "名称": "湖北飞德慕体育用品有限公司",
    "编号": "GR202242001255"
  },
  {
    "名称": "宜昌筑诚检测技术有限公司",
    "编号": "GR202242001256"
  },
  {
    "名称": "武汉天喻教育科技有限公司",
    "编号": "GR202242001257"
  },
  {
    "名称": "湖北福广制药有限公司",
    "编号": "GR202242001258"
  },
  {
    "名称": "武汉简实信息技术有限公司",
    "编号": "GR202242001259"
  },
  {
    "名称": "武汉中旗光电科技有限公司",
    "编号": "GR202242001260"
  },
  {
    "名称": "武汉恒泰弘安安全科技有限公司",
    "编号": "GR202242001261"
  },
  {
    "名称": "武汉沅盈科技有限公司",
    "编号": "GR202242001262"
  },
  {
    "名称": "湖北盟科纸业有限公司",
    "编号": "GR202242001263"
  },
  {
    "名称": "湖北韵智捷家具有限公司",
    "编号": "GR202242001264"
  },
  {
    "名称": "武汉昊广智联科技有限公司",
    "编号": "GR202242001265"
  },
  {
    "名称": "荆州市紫荆龙创机械制造有限公司",
    "编号": "GR202242001266"
  },
  {
    "名称": "湖北捷祥测控技术有限公司",
    "编号": "GR202242001267"
  },
  {
    "名称": "湖北力莱科技有限公司",
    "编号": "GR202242001268"
  },
  {
    "名称": "中冶武汉冶金建筑研究院有限公司",
    "编号": "GR202242001269"
  },
  {
    "名称": "荆门融媒网络科技有限公司",
    "编号": "GR202242001270"
  },
  {
    "名称": "湖北赛德检测有限责任公司",
    "编号": "GR202242001271"
  },
  {
    "名称": "武汉行芝达自动化科技有限公司",
    "编号": "GR202242001272"
  },
  {
    "名称": "宜昌正信建筑工程试验检测有限公司",
    "编号": "GR202242001273"
  },
  {
    "名称": "武汉思古科技有限公司",
    "编号": "GR202242001274"
  },
  {
    "名称": "湖北罗迪斯克户外用品有限公司",
    "编号": "GR202242001275"
  },
  {
    "名称": "武汉九享大众科技有限公司",
    "编号": "GR202242001276"
  },
  {
    "名称": "湖北珑川新型建材股份有限公司",
    "编号": "GR202242001277"
  },
  {
    "名称": "荆门市世鑫自动化科技有限公司",
    "编号": "GR202242001278"
  },
  {
    "名称": "宜昌思创新材料科技有限公司",
    "编号": "GR202242001279"
  },
  {
    "名称": "武汉科创伟业生物科技有限公司",
    "编号": "GR202242001280"
  },
  {
    "名称": "湖北大江环科防腐工程技术有限公司",
    "编号": "GR202242001281"
  },
  {
    "名称": "湖北华信机械发展有限公司",
    "编号": "GR202242001282"
  },
  {
    "名称": "武汉创宇极网络科技有限公司",
    "编号": "GR202242001283"
  },
  {
    "名称": "襄阳中车电机技术有限公司",
    "编号": "GR202242001284"
  },
  {
    "名称": "武汉卓越优创机电设备有限公司",
    "编号": "GR202242001285"
  },
  {
    "名称": "湖北耀佳勘测规划设计有限公司",
    "编号": "GR202242001286"
  },
  {
    "名称": "曙光网络科技有限公司",
    "编号": "GR202242001287"
  },
  {
    "名称": "监利县楚天粮油机械有限公司",
    "编号": "GR202242001288"
  },
  {
    "名称": "湖北湘高高压开关有限公司",
    "编号": "GR202242001289"
  },
  {
    "名称": "孝感安华纺织有限公司",
    "编号": "GR202242001290"
  },
  {
    "名称": "荆州市佳源纺织有限公司",
    "编号": "GR202242001291"
  },
  {
    "名称": "湖北天丝纺织科技有限公司",
    "编号": "GR202242001292"
  },
  {
    "名称": "湖北今力智能科技有限公司",
    "编号": "GR202242001293"
  },
  {
    "名称": "襄阳利匠精工制造有限公司",
    "编号": "GR202242001294"
  },
  {
    "名称": "湖北鼎荣精密工业有限公司",
    "编号": "GR202242001295"
  },
  {
    "名称": "湖北达瑞智能科技有限公司",
    "编号": "GR202242001296"
  },
  {
    "名称": "黄冈市瑞安纸品包装有限公司",
    "编号": "GR202242001297"
  },
  {
    "名称": "湖北澳利龙食品股份有限公司",
    "编号": "GR202242001298"
  },
  {
    "名称": "湖北白兆山水泥有限公司",
    "编号": "GR202242001299"
  },
  {
    "名称": "湖北天瑞天成工贸股份有限公司",
    "编号": "GR202242001300"
  },
  {
    "名称": "湖北景深安全技术有限公司",
    "编号": "GR202242001301"
  },
  {
    "名称": "湖北金力特电气有限公司",
    "编号": "GR202242001302"
  },
  {
    "名称": "武汉开思新材料有限公司",
    "编号": "GR202242001303"
  },
  {
    "名称": "湖北省宝沃新能源科技有限公司",
    "编号": "GR202242001304"
  },
  {
    "名称": "普莱晶科技（宜昌）有限公司",
    "编号": "GR202242001305"
  },
  {
    "名称": "湖北水之韵食品有限公司",
    "编号": "GR202242001306"
  },
  {
    "名称": "星源（十堰）悬架有限公司",
    "编号": "GR202242001307"
  },
  {
    "名称": "湖北中昌顺建设工程有限公司",
    "编号": "GR202242001308"
  },
  {
    "名称": "宜昌千鸿再生资源有限公司",
    "编号": "GR202242001309"
  },
  {
    "名称": "武汉市天真教育科技有限公司",
    "编号": "GR202242001310"
  },
  {
    "名称": "湖北首通电磁线科技股份有限公司",
    "编号": "GR202242001311"
  },
  {
    "名称": "湖北汉新特种汽车制造装备有限公司",
    "编号": "GR202242001312"
  },
  {
    "名称": "武汉科想分析检测技术有限公司",
    "编号": "GR202242001313"
  },
  {
    "名称": "武汉斑马出行科技有限公司",
    "编号": "GR202242001314"
  },
  {
    "名称": "襄阳亚力工业设备有限公司",
    "编号": "GR202242001315"
  },
  {
    "名称": "枝江市华豪科技有限公司",
    "编号": "GR202242001316"
  },
  {
    "名称": "湖北庆中科技有限公司",
    "编号": "GR202242001317"
  },
  {
    "名称": "湖北格莱德光电子器件有限公司",
    "编号": "GR202242001318"
  },
  {
    "名称": "武汉市人机科技有限公司",
    "编号": "GR202242001319"
  },
  {
    "名称": "武汉市卓冉科技有限公司",
    "编号": "GR202242001320"
  },
  {
    "名称": "湖北三安光电有限公司",
    "编号": "GR202242001321"
  },
  {
    "名称": "武汉巨盛网络科技有限公司",
    "编号": "GR202242001322"
  },
  {
    "名称": "潜江方圆钛白有限公司",
    "编号": "GR202242001323"
  },
  {
    "名称": "武汉毳雨环保科技有限责任公司",
    "编号": "GR202242001324"
  },
  {
    "名称": "襄阳沃江源食品有限公司",
    "编号": "GR202242001325"
  },
  {
    "名称": "武汉铭德相合投资管理有限公司",
    "编号": "GR202242001326"
  },
  {
    "名称": "宜昌华鼎建筑工程有限公司",
    "编号": "GR202242001327"
  },
  {
    "名称": "湖北麻城市嘉丰石材有限公司",
    "编号": "GR202242001328"
  },
  {
    "名称": "武汉游道互动科技有限公司",
    "编号": "GR202242001329"
  },
  {
    "名称": "武汉威亚汽车饰件有限公司",
    "编号": "GR202242001330"
  },
  {
    "名称": "武汉孟德科技有限公司",
    "编号": "GR202242001331"
  },
  {
    "名称": "松滋市璐达科技有限公司",
    "编号": "GR202242001332"
  },
  {
    "名称": "武汉谱尔思仪器有限公司",
    "编号": "GR202242001333"
  },
  {
    "名称": "湖北共发米业有限公司",
    "编号": "GR202242001334"
  },
  {
    "名称": "芯创（天门）电子科技有限公司",
    "编号": "GR202242001335"
  },
  {
    "名称": "武汉灵龙创智科技有限公司",
    "编号": "GR202242001336"
  },
  {
    "名称": "武汉市谱众联合科技有限公司",
    "编号": "GR202242001337"
  },
  {
    "名称": "应城乐华厨卫有限公司",
    "编号": "GR202242001338"
  },
  {
    "名称": "武汉梦竞科技有限公司",
    "编号": "GR202242001339"
  },
  {
    "名称": "湖北康正药业有限公司",
    "编号": "GR202242001340"
  },
  {
    "名称": "湖北国龙纺织科技有限公司",
    "编号": "GR202242001341"
  },
  {
    "名称": "湖北龙齐宏盛科技有限公司",
    "编号": "GR202242001342"
  },
  {
    "名称": "宜昌华诚生物（宜都）有限公司",
    "编号": "GR202242001343"
  },
  {
    "名称": "武汉领普科技有限公司",
    "编号": "GR202242001344"
  },
  {
    "名称": "玉柴东特专用汽车有限公司",
    "编号": "GR202242001345"
  },
  {
    "名称": "湖北光宏通信科技有限公司",
    "编号": "GR202242001346"
  },
  {
    "名称": "黑木科技（武汉）有限公司",
    "编号": "GR202242001347"
  },
  {
    "名称": "武汉航城智慧科技有限公司",
    "编号": "GR202242001348"
  },
  {
    "名称": "鄂州三江港宏文包装有限公司",
    "编号": "GR202242001349"
  },
  {
    "名称": "武汉贝参药业股份有限公司",
    "编号": "GR202242001350"
  },
  {
    "名称": "湖北莎丽绿色建材科技有限公司",
    "编号": "GR202242001351"
  },
  {
    "名称": "湖北东欣古建材料科技有限公司",
    "编号": "GR202242001352"
  },
  {
    "名称": "湖北建科国际工程有限公司",
    "编号": "GR202242001353"
  },
  {
    "名称": "湖北标迪电气有限公司",
    "编号": "GR202242001354"
  },
  {
    "名称": "湖北精圭锆业有限公司",
    "编号": "GR202242001355"
  },
  {
    "名称": "湖北高铁炜佳科技有限公司",
    "编号": "GR202242001356"
  },
  {
    "名称": "武汉做自己科技有限公司",
    "编号": "GR202242001357"
  },
  {
    "名称": "武汉缔游科技有限公司",
    "编号": "GR202242001358"
  },
  {
    "名称": "长园天弓智能停车系统（湖北）有限公司",
    "编号": "GR202242001359"
  },
  {
    "名称": "咸宁仓禾日用品有限公司",
    "编号": "GR202242001360"
  },
  {
    "名称": "蕲春县银兴米业有限公司",
    "编号": "GR202242001361"
  },
  {
    "名称": "随州市众星汽车内饰件有限责任公司",
    "编号": "GR202242001362"
  },
  {
    "名称": "武汉云霁灼灿技术有限公司",
    "编号": "GR202242001363"
  },
  {
    "名称": "湖北兴发凌志新材料有限公司",
    "编号": "GR202242001364"
  },
  {
    "名称": "宜昌市有为彩印有限公司",
    "编号": "GR202242001365"
  },
  {
    "名称": "宜昌智安天下智能技术有限公司",
    "编号": "GR202242001366"
  },
  {
    "名称": "武汉极限视界科技有限公司",
    "编号": "GR202242001367"
  },
  {
    "名称": "武汉熠盛汽车技术有限公司",
    "编号": "GR202242001368"
  },
  {
    "名称": "武汉湖江科技有限公司",
    "编号": "GR202242001369"
  },
  {
    "名称": "武汉拾光熵简科技有限公司",
    "编号": "GR202242001370"
  },
  {
    "名称": "武汉海华石油化工设备制造有限公司",
    "编号": "GR202242001371"
  },
  {
    "名称": "湖北诚利时代交通设施有限公司",
    "编号": "GR202242001372"
  },
  {
    "名称": "湖北昊源建设工程有限公司",
    "编号": "GR202242001373"
  },
  {
    "名称": "武汉市辛纳电子科技有限公司",
    "编号": "GR202242001374"
  },
  {
    "名称": "湖北九泰安全环保技术有限公司",
    "编号": "GR202242001375"
  },
  {
    "名称": "武汉源字符信息技术有限责任公司",
    "编号": "GR202242001376"
  },
  {
    "名称": "武汉中楚聚裕科技技术有限公司",
    "编号": "GR202242001377"
  },
  {
    "名称": "武汉科稳测控技术有限公司",
    "编号": "GR202242001378"
  },
  {
    "名称": "纷达（武汉）科技发展有限公司",
    "编号": "GR202242001379"
  },
  {
    "名称": "湖北中职检测研究院有限公司",
    "编号": "GR202242001380"
  },
  {
    "名称": "黄石成大精密机械制造有限公司",
    "编号": "GR202242001381"
  },
  {
    "名称": "宜昌北斗测绘有限公司",
    "编号": "GR202242001382"
  },
  {
    "名称": "麻城市众磊新型建筑材料有限公司",
    "编号": "GR202242001383"
  },
  {
    "名称": "湖北美尔格电子股份有限公司",
    "编号": "GR202242001384"
  },
  {
    "名称": "湖北高森特钢制品股份有限公司",
    "编号": "GR202242001385"
  },
  {
    "名称": "瑞风能源（武汉）工程技术有限公司",
    "编号": "GR202242001386"
  },
  {
    "名称": "武汉蓝海智控科技有限公司",
    "编号": "GR202242001387"
  },
  {
    "名称": "湖北安逸智控环保科技有限公司",
    "编号": "GR202242001388"
  },
  {
    "名称": "武汉东碧环保科技有限公司",
    "编号": "GR202242001389"
  },
  {
    "名称": "谷城展旺机械有限公司",
    "编号": "GR202242001390"
  },
  {
    "名称": "湖北鑫宝马弹簧有限公司",
    "编号": "GR202242001391"
  },
  {
    "名称": "武汉鑫灵锐网络技术有限公司",
    "编号": "GR202242001392"
  },
  {
    "名称": "欧颂德婴童用品（湖北）有限公司",
    "编号": "GR202242001393"
  },
  {
    "名称": "武汉第二电线电缆有限公司",
    "编号": "GR202242001394"
  },
  {
    "名称": "武汉大唐通信科技有限责任公司",
    "编号": "GR202242001395"
  },
  {
    "名称": "武汉斯佳康医疗科技开发有限公司",
    "编号": "GR202242001396"
  },
  {
    "名称": "宜昌江山建设工程有限公司",
    "编号": "GR202242001397"
  },
  {
    "名称": "荆州市正圆机械制造有限公司",
    "编号": "GR202242001398"
  },
  {
    "名称": "襄阳锐特精密机械有限公司",
    "编号": "GR202242001399"
  },
  {
    "名称": "武汉诚迅科技有限公司",
    "编号": "GR202242001400"
  },
  {
    "名称": "武汉奥恒胜科技有限公司",
    "编号": "GR202242001401"
  },
  {
    "名称": "湖北辰光信息科技有限公司",
    "编号": "GR202242001402"
  },
  {
    "名称": "武汉新能源接入装备与技术研究院有限公司",
    "编号": "GR202242001403"
  },
  {
    "名称": "湖北金祥瑞科技有限公司",
    "编号": "GR202242001404"
  },
  {
    "名称": "湖北磊雅鑫盛石业有限公司",
    "编号": "GR202242001405"
  },
  {
    "名称": "湖北华宜矿科智能输送设备有限公司",
    "编号": "GR202242001406"
  },
  {
    "名称": "湖北华欣有机硅新材料有限公司",
    "编号": "GR202242001407"
  },
  {
    "名称": "武汉创智空间科技有限公司",
    "编号": "GR202242001408"
  },
  {
    "名称": "宜昌大川科技有限公司",
    "编号": "GR202242001409"
  },
  {
    "名称": "襄阳御泰汽车科技有限公司",
    "编号": "GR202242001410"
  },
  {
    "名称": "武汉氪信数据科技有限公司",
    "编号": "GR202242001411"
  },
  {
    "名称": "东风友联（十堰）汽车饰件有限公司",
    "编号": "GR202242001412"
  },
  {
    "名称": "武汉格林泰克科技有限公司",
    "编号": "GR202242001413"
  },
  {
    "名称": "湖北省大洋智通科技有限公司",
    "编号": "GR202242001414"
  },
  {
    "名称": "宜都市徽仁环保科技有限公司",
    "编号": "GR202242001415"
  },
  {
    "名称": "武汉小数点科技发展有限公司",
    "编号": "GR202242001416"
  },
  {
    "名称": "武汉脑赛思仪器设备有限公司",
    "编号": "GR202242001417"
  },
  {
    "名称": "武汉凌云建筑装饰工程有限公司",
    "编号": "GR202242001418"
  },
  {
    "名称": "湖北宝通电工有限公司",
    "编号": "GR202242001419"
  },
  {
    "名称": "武汉中航通用科技有限公司",
    "编号": "GR202242001420"
  },
  {
    "名称": "荆州市凯文生物科技有限公司",
    "编号": "GR202242001421"
  },
  {
    "名称": "宜昌楚能变压器有限公司",
    "编号": "GR202242001422"
  },
  {
    "名称": "武汉恒创达汽车零部件有限公司",
    "编号": "GR202242001423"
  },
  {
    "名称": "武汉世纪聚星网络科技有限公司",
    "编号": "GR202242001424"
  },
  {
    "名称": "金源（荆州）环保科技有限公司",
    "编号": "GR202242001425"
  },
  {
    "名称": "荆门维航制造科技有限公司",
    "编号": "GR202242001426"
  },
  {
    "名称": "湖北玲珑壹通卡科技有限公司",
    "编号": "GR202242001427"
  },
  {
    "名称": "武汉兴农粮油设备有限责任公司",
    "编号": "GR202242001428"
  },
  {
    "名称": "双星东风轮胎有限公司",
    "编号": "GR202242001429"
  },
  {
    "名称": "武汉创新昭阳科技有限公司",
    "编号": "GR202242001430"
  },
  {
    "名称": "黄石中都装配式科技有限公司",
    "编号": "GR202242001431"
  },
  {
    "名称": "湖北大象生态农业发展有限公司",
    "编号": "GR202242001432"
  },
  {
    "名称": "湖北辉创重型工程有限公司",
    "编号": "GR202242001433"
  },
  {
    "名称": "湖北科领重工有限公司",
    "编号": "GR202242001434"
  },
  {
    "名称": "湖北武铁山桥轨道装备有限公司",
    "编号": "GR202242001435"
  },
  {
    "名称": "湖北裕大华华立染织有限公司",
    "编号": "GR202242001436"
  },
  {
    "名称": "武汉赛朗智能技术有限公司",
    "编号": "GR202242001437"
  },
  {
    "名称": "武汉新能瑞鑫仪表科技有限公司",
    "编号": "GR202242001438"
  },
  {
    "名称": "湖北华磁电子科技有限公司",
    "编号": "GR202242001439"
  },
  {
    "名称": "武汉三宇机械有限公司",
    "编号": "GR202242001440"
  },
  {
    "名称": "武汉洁净易超净技术有限公司",
    "编号": "GR202242001441"
  },
  {
    "名称": "湖北天霖新材料有限公司",
    "编号": "GR202242001442"
  },
  {
    "名称": "咸宁市福达医疗用品股份有限公司",
    "编号": "GR202242001443"
  },
  {
    "名称": "武汉合力亿捷科技有限公司",
    "编号": "GR202242001444"
  },
  {
    "名称": "湖北鼎正织造有限公司",
    "编号": "GR202242001445"
  },
  {
    "名称": "湖北中香农业科技股份有限公司",
    "编号": "GR202242001446"
  },
  {
    "名称": "麻城市胜兴尾矿循环利用有限公司",
    "编号": "GR202242001447"
  },
  {
    "名称": "湖北拓普斯智能装备有限公司",
    "编号": "GR202242001448"
  },
  {
    "名称": "武汉瑞联光通信技术有限公司",
    "编号": "GR202242001449"
  },
  {
    "名称": "武汉诺一数字技术有限公司",
    "编号": "GR202242001450"
  },
  {
    "名称": "华高电气（湖北）有限公司",
    "编号": "GR202242001451"
  },
  {
    "名称": "湖北博思软件信息技术有限公司",
    "编号": "GR202242001452"
  },
  {
    "名称": "京山博森机械制造有限公司",
    "编号": "GR202242001453"
  },
  {
    "名称": "灯塔财经信息有限公司",
    "编号": "GR202242001454"
  },
  {
    "名称": "宜昌慧正环保工程有限公司",
    "编号": "GR202242001455"
  },
  {
    "名称": "湖北北斗天汇科技有限公司",
    "编号": "GR202242001456"
  },
  {
    "名称": "武汉华源晨泰健康生物科技有限公司",
    "编号": "GR202242001457"
  },
  {
    "名称": "武汉腾创网络建设工程有限公司",
    "编号": "GR202242001458"
  },
  {
    "名称": "湖北典强机械设备有限公司",
    "编号": "GR202242001459"
  },
  {
    "名称": "湖北省宇涛特种纤维股份有限公司",
    "编号": "GR202242001460"
  },
  {
    "名称": "武汉上果互动科技有限公司",
    "编号": "GR202242001461"
  },
  {
    "名称": "宜昌昌耀电力成套设备有限公司",
    "编号": "GR202242001462"
  },
  {
    "名称": "武汉舜鑫泽模具热处理有限公司",
    "编号": "GR202242001463"
  },
  {
    "名称": "武汉德晟祥科技有限公司",
    "编号": "GR202242001464"
  },
  {
    "名称": "湖北铭振金属科技有限公司",
    "编号": "GR202242001465"
  },
  {
    "名称": "武汉天畅弘达科技有限公司",
    "编号": "GR202242001466"
  },
  {
    "名称": "湖北景合包装制品有限公司",
    "编号": "GR202242001467"
  },
  {
    "名称": "广水市迅发橡胶密封件有限公司",
    "编号": "GR202242001468"
  },
  {
    "名称": "武汉市鸿骏四维科技有限公司",
    "编号": "GR202242001469"
  },
  {
    "名称": "武汉华天园林集团有限公司",
    "编号": "GR202242001470"
  },
  {
    "名称": "武汉博特睿达智能科技有限公司",
    "编号": "GR202242001471"
  },
  {
    "名称": "武汉冠楠家具配套有限公司",
    "编号": "GR202242001472"
  },
  {
    "名称": "武汉量投网络科技有限公司",
    "编号": "GR202242001473"
  },
  {
    "名称": "武汉蓝筹科技有限公司",
    "编号": "GR202242001474"
  },
  {
    "名称": "武汉金东方智能景观股份有限公司",
    "编号": "GR202242001475"
  },
  {
    "名称": "广水轻工机械有限责任公司",
    "编号": "GR202242001476"
  },
  {
    "名称": "湖北思云山技术有限公司",
    "编号": "GR202242001477"
  },
  {
    "名称": "十堰市双兴净化器有限公司",
    "编号": "GR202242001478"
  },
  {
    "名称": "湖北睿能科技有限公司",
    "编号": "GR202242001479"
  },
  {
    "名称": "湖北博兴复合材料股份有限公司",
    "编号": "GR202242001480"
  },
  {
    "名称": "武汉麦特建筑科技有限公司",
    "编号": "GR202242001481"
  },
  {
    "名称": "湖北三峰透平装备股份有限公司",
    "编号": "GR202242001482"
  },
  {
    "名称": "武汉宇科天创网络科技有限公司",
    "编号": "GR202242001483"
  },
  {
    "名称": "宜昌新宜运机械有限公司",
    "编号": "GR202242001484"
  },
  {
    "名称": "湖北中硕环保有限公司",
    "编号": "GR202242001485"
  },
  {
    "名称": "湖北修凡科技有限公司",
    "编号": "GR202242001486"
  },
  {
    "名称": "湖北飞歌科技股份有限公司",
    "编号": "GR202242001487"
  },
  {
    "名称": "武汉欣海远航科技研发有限公司",
    "编号": "GR202242001488"
  },
  {
    "名称": "湖北精工工业建筑系统有限公司",
    "编号": "GR202242001489"
  },
  {
    "名称": "武汉波瑞特斯光纤传感科技有限公司",
    "编号": "GR202242001490"
  },
  {
    "名称": "湖北泰山建材有限公司",
    "编号": "GR202242001491"
  },
  {
    "名称": "襄阳市俭鼎玻璃钢有限责任公司",
    "编号": "GR202242001492"
  },
  {
    "名称": "武汉美瑞科技有限公司",
    "编号": "GR202242001493"
  },
  {
    "名称": "微晟（武汉）技术有限公司",
    "编号": "GR202242001494"
  },
  {
    "名称": "湖北讯罗科技有限公司",
    "编号": "GR202242001495"
  },
  {
    "名称": "武汉世纪精能科技发展有限公司",
    "编号": "GR202242001496"
  },
  {
    "名称": "览易（武汉）智能数据服务有限公司",
    "编号": "GR202242001497"
  },
  {
    "名称": "中水信通科技（武汉）有限公司",
    "编号": "GR202242001498"
  },
  {
    "名称": "武汉云极天成信息科技有限公司",
    "编号": "GR202242001499"
  },
  {
    "名称": "湖北兴投建设工程有限公司",
    "编号": "GR202242001500"
  },
  {
    "名称": "沙洋弘润建材有限公司",
    "编号": "GR202242001501"
  },
  {
    "名称": "武汉思能物联网科技有限公司",
    "编号": "GR202242001502"
  },
  {
    "名称": "武汉齐飞电气有限公司",
    "编号": "GR202242001503"
  },
  {
    "名称": "湖北齐星模具制造股份有限公司",
    "编号": "GR202242001504"
  },
  {
    "名称": "武汉光为通信科技有限公司",
    "编号": "GR202242001505"
  },
  {
    "名称": "中京（武汉）工程技术有限公司",
    "编号": "GR202242001506"
  },
  {
    "名称": "湖北三众环境建设工程有限公司",
    "编号": "GR202242001507"
  },
  {
    "名称": "武汉亢德科技发展有限公司",
    "编号": "GR202242001508"
  },
  {
    "名称": "武汉惠付通科技有限公司",
    "编号": "GR202242001509"
  },
  {
    "名称": "湖北明阳同辉包装有限公司",
    "编号": "GR202242001510"
  },
  {
    "名称": "武汉锐晶激光芯片技术有限公司",
    "编号": "GR202242001511"
  },
  {
    "名称": "天门瑞升塑网有限公司",
    "编号": "GR202242001512"
  },
  {
    "名称": "彦影科技（湖北）有限公司",
    "编号": "GR202242001513"
  },
  {
    "名称": "荆州荆龙航天科技有限公司",
    "编号": "GR202242001514"
  },
  {
    "名称": "湖北三众车桥股份有限公司",
    "编号": "GR202242001515"
  },
  {
    "名称": "湖北高能鹏富环保科技有限公司",
    "编号": "GR202242001516"
  },
  {
    "名称": "武汉华通通风设备有限公司",
    "编号": "GR202242001517"
  },
  {
    "名称": "武汉朗维科技有限公司",
    "编号": "GR202242001518"
  },
  {
    "名称": "湖北华钧检测有限公司",
    "编号": "GR202242001519"
  },
  {
    "名称": "武汉市志信信息科技有限公司",
    "编号": "GR202242001520"
  },
  {
    "名称": "武汉市沃农肥业有限公司",
    "编号": "GR202242001521"
  },
  {
    "名称": "湖北万松堂大健康医药集团有限公司",
    "编号": "GR202242001522"
  },
  {
    "名称": "中数在线（湖北）信息技术有限公司",
    "编号": "GR202242001523"
  },
  {
    "名称": "武汉维新智云科技有限公司",
    "编号": "GR202242001524"
  },
  {
    "名称": "武汉市黄鹤塑料有限公司",
    "编号": "GR202242001525"
  },
  {
    "名称": "湖北德隆纺织有限公司",
    "编号": "GR202242001526"
  },
  {
    "名称": "武汉新大创新水处理技术有限公司",
    "编号": "GR202242001527"
  },
  {
    "名称": "武汉伯远生物科技有限公司",
    "编号": "GR202242001528"
  },
  {
    "名称": "武汉勇韵科技有限公司",
    "编号": "GR202242001529"
  },
  {
    "名称": "荆门瑞佳昊食品有限公司",
    "编号": "GR202242001530"
  },
  {
    "名称": "凯丽科技（湖北）有限公司",
    "编号": "GR202242001531"
  },
  {
    "名称": "优毅时代武汉科技有限公司",
    "编号": "GR202242001532"
  },
  {
    "名称": "武汉麦纳工业有限公司",
    "编号": "GR202242001533"
  },
  {
    "名称": "武汉万实停易充科技有限公司",
    "编号": "GR202242001534"
  },
  {
    "名称": "湖北长峰电工材料有限公司",
    "编号": "GR202242001535"
  },
  {
    "名称": "湖北荣喜能源环保建设有限公司",
    "编号": "GR202242001536"
  },
  {
    "名称": "湖北千发仁光学水晶科技有限公司",
    "编号": "GR202242001537"
  },
  {
    "名称": "武汉伟立德新能源有限公司",
    "编号": "GR202242001538"
  },
  {
    "名称": "湖北永阳材料股份有限公司",
    "编号": "GR202242001539"
  },
  {
    "名称": "湖北苏信新能源技术有限公司",
    "编号": "GR202242001540"
  },
  {
    "名称": "黄冈双成自动控制设备有限公司",
    "编号": "GR202242001541"
  },
  {
    "名称": "湖北亿纬动力有限公司",
    "编号": "GR202242001542"
  },
  {
    "名称": "黄石鑫华轮毂有限公司",
    "编号": "GR202242001543"
  },
  {
    "名称": "武汉中安信通信息技术有限公司",
    "编号": "GR202242001544"
  },
  {
    "名称": "十堰世通模具制造有限公司",
    "编号": "GR202242001545"
  },
  {
    "名称": "湖北瑞谱信息科技有限公司",
    "编号": "GR202242001546"
  },
  {
    "名称": "湖北楚峰建科集团荆州开元新材股份有限公司",
    "编号": "GR202242001547"
  },
  {
    "名称": "荆州紫辰通信科技有限公司",
    "编号": "GR202242001548"
  },
  {
    "名称": "武汉英玩科技有限公司",
    "编号": "GR202242001549"
  },
  {
    "名称": "武汉钧泽科技有限公司",
    "编号": "GR202242001550"
  },
  {
    "名称": "湖北富奕达电子科技有限公司",
    "编号": "GR202242001551"
  },
  {
    "名称": "湖北美标康盛动力科技有限公司",
    "编号": "GR202242001552"
  },
  {
    "名称": "宜昌凯正新型材料有限公司",
    "编号": "GR202242001553"
  },
  {
    "名称": "稳健医疗（黄冈）有限公司",
    "编号": "GR202242001554"
  },
  {
    "名称": "光奥科技（武汉）有限公司",
    "编号": "GR202242001555"
  },
  {
    "名称": "武汉数字智能信息科技有限公司",
    "编号": "GR202242001556"
  },
  {
    "名称": "湖北红岸车辆科技有限公司",
    "编号": "GR202242001557"
  },
  {
    "名称": "武汉盛泽源科技有限公司",
    "编号": "GR202242001558"
  },
  {
    "名称": "襄阳市金煌食品有限公司",
    "编号": "GR202242001559"
  },
  {
    "名称": "上海延安药业（湖北）有限公司",
    "编号": "GR202242001560"
  },
  {
    "名称": "咸丰县陈向食品有限公司",
    "编号": "GR202242001561"
  },
  {
    "名称": "湖北省兴发磷化工研究院有限公司",
    "编号": "GR202242001562"
  },
  {
    "名称": "武汉睿瀛新媒文化传播有限责任公司",
    "编号": "GR202242001563"
  },
  {
    "名称": "武汉慧远智控科技有限公司",
    "编号": "GR202242001564"
  },
  {
    "名称": "江陵县诚康商品混凝土有限公司",
    "编号": "GR202242001565"
  },
  {
    "名称": "武汉联镇科技有限公司",
    "编号": "GR202242001566"
  },
  {
    "名称": "万绍德环保科技（武汉）有限公司",
    "编号": "GR202242001567"
  },
  {
    "名称": "武汉市天泉慧源环保科技有限公司",
    "编号": "GR202242001568"
  },
  {
    "名称": "襄阳绿凯环保科技有限公司",
    "编号": "GR202242001569"
  },
  {
    "名称": "湖北欧本钢结构有限公司",
    "编号": "GR202242001570"
  },
  {
    "名称": "湖北华瑞建材科技有限公司",
    "编号": "GR202242001571"
  },
  {
    "名称": "东风（十堰）车身部件有限责任公司",
    "编号": "GR202242001572"
  },
  {
    "名称": "天门市天安建材有限公司",
    "编号": "GR202242001573"
  },
  {
    "名称": "武汉多来增值电信技术有限公司",
    "编号": "GR202242001574"
  },
  {
    "名称": "湖北精益高精铜板带有限公司",
    "编号": "GR202242001575"
  },
  {
    "名称": "襄阳辰智自动化技术有限公司",
    "编号": "GR202242001576"
  },
  {
    "名称": "襄阳美金环轴承有限公司",
    "编号": "GR202242001577"
  },
  {
    "名称": "武汉双顺网络通信技术有限公司",
    "编号": "GR202242001578"
  },
  {
    "名称": "松滋市掘运建材有限责任公司",
    "编号": "GR202242001579"
  },
  {
    "名称": "宜昌市蓝深科技有限责任公司",
    "编号": "GR202242001580"
  },
  {
    "名称": "亚科因（武汉）生物技术有限公司",
    "编号": "GR202242001581"
  },
  {
    "名称": "湖北正弦电力工程咨询有限公司",
    "编号": "GR202242001582"
  },
  {
    "名称": "湖北华崟智控科技有限公司",
    "编号": "GR202242001583"
  },
  {
    "名称": "湖北多瑞药业有限公司",
    "编号": "GR202242001584"
  },
  {
    "名称": "黄石华鸿机械有限公司",
    "编号": "GR202242001585"
  },
  {
    "名称": "湖北丰普研磨科技有限公司",
    "编号": "GR202242001586"
  },
  {
    "名称": "武汉鑫拓力工程技术有限公司",
    "编号": "GR202242001587"
  },
  {
    "名称": "湖北润宝环硕环保科技有限公司",
    "编号": "GR202242001588"
  },
  {
    "名称": "湖北众邦新能源有限公司",
    "编号": "GR202242001589"
  },
  {
    "名称": "湖北格纳斯新材料有限公司",
    "编号": "GR202242001590"
  },
  {
    "名称": "湖北海立田汽车部件有限公司",
    "编号": "GR202242001591"
  },
  {
    "名称": "武汉市民用建筑设计研究院有限责任公司",
    "编号": "GR202242001592"
  },
  {
    "名称": "湖北长坂桥环保科技有限公司",
    "编号": "GR202242001593"
  },
  {
    "名称": "湖北长才机电有限公司",
    "编号": "GR202242001594"
  },
  {
    "名称": "钟祥亿源生物科技有限公司",
    "编号": "GR202242001595"
  },
  {
    "名称": "武汉金力软件有限公司",
    "编号": "GR202242001596"
  },
  {
    "名称": "荆州市友大金属制品有限公司",
    "编号": "GR202242001597"
  },
  {
    "名称": "十堰安联汽车零部件有限公司",
    "编号": "GR202242001598"
  },
  {
    "名称": "湖北点赞科技有限公司",
    "编号": "GR202242001599"
  },
  {
    "名称": "麻城市众旺石业有限公司",
    "编号": "GR202242001600"
  },
  {
    "名称": "东风汽车紧固件有限公司",
    "编号": "GR202242001601"
  },
  {
    "名称": "武汉市万达门业有限公司",
    "编号": "GR202242001602"
  },
  {
    "名称": "湖北骆驼海峡新型蓄电池有限公司",
    "编号": "GR202242001603"
  },
  {
    "名称": "武汉拜必优科技有限公司",
    "编号": "GR202242001604"
  },
  {
    "名称": "湖北浩瀚检测技术有限公司",
    "编号": "GR202242001605"
  },
  {
    "名称": "武汉易升物流设备有限公司",
    "编号": "GR202242001606"
  },
  {
    "名称": "十堰知名实业发展有限公司",
    "编号": "GR202242001607"
  },
  {
    "名称": "宜昌软信网络科技有限公司",
    "编号": "GR202242001608"
  },
  {
    "名称": "武汉市夏睿琪科技有限公司",
    "编号": "GR202242001609"
  },
  {
    "名称": "湖北申路专用汽车有限公司",
    "编号": "GR202242001610"
  },
  {
    "名称": "武汉贝格泰克数控直驱机械有限公司",
    "编号": "GR202242001611"
  },
  {
    "名称": "湖北省武穴市特种钢铸造有限公司",
    "编号": "GR202242001612"
  },
  {
    "名称": "武汉东湖大数据交易中心股份有限公司",
    "编号": "GR202242001613"
  },
  {
    "名称": "湖北三环汽车方向机有限公司",
    "编号": "GR202242001614"
  },
  {
    "名称": "武汉路西法网络科技有限公司",
    "编号": "GR202242001615"
  },
  {
    "名称": "武汉综合交通研究院有限公司",
    "编号": "GR202242001616"
  },
  {
    "名称": "武汉联开检测科技有限公司",
    "编号": "GR202242001617"
  },
  {
    "名称": "襄阳奥东电气有限公司",
    "编号": "GR202242001618"
  },
  {
    "名称": "湖北翔华模具科技股份有限公司",
    "编号": "GR202242001619"
  },
  {
    "名称": "黄石元祥模具材料有限公司",
    "编号": "GR202242001620"
  },
  {
    "名称": "湖北琴海普尔数码有限公司",
    "编号": "GR202242001621"
  },
  {
    "名称": "武汉国际矿业权交易中心有限公司",
    "编号": "GR202242001622"
  },
  {
    "名称": "大容环境湖北有限公司",
    "编号": "GR202242001623"
  },
  {
    "名称": "襄阳创锋机械制造有限公司",
    "编号": "GR202242001624"
  },
  {
    "名称": "湖北金马汽车管路系统有限公司",
    "编号": "GR202242001625"
  },
  {
    "名称": "武汉锦辰数科技术有限公司",
    "编号": "GR202242001626"
  },
  {
    "名称": "武汉英瑞普环保科技发展有限公司",
    "编号": "GR202242001627"
  },
  {
    "名称": "武汉九武光电技术有限公司",
    "编号": "GR202242001628"
  },
  {
    "名称": "武汉仁鑫安实业有限公司",
    "编号": "GR202242001629"
  },
  {
    "名称": "武汉市和利时电力科技有限公司",
    "编号": "GR202242001630"
  },
  {
    "名称": "湖北三六重工有限公司",
    "编号": "GR202242001631"
  },
  {
    "名称": "襄阳汉伟化工科技有限公司",
    "编号": "GR202242001632"
  },
  {
    "名称": "十堰瑞虎机械科技有限公司",
    "编号": "GR202242001633"
  },
  {
    "名称": "武汉科诺生物科技股份有限公司",
    "编号": "GR202242001634"
  },
  {
    "名称": "武汉长江科创科技发展有限公司",
    "编号": "GR202242001635"
  },
  {
    "名称": "湖北中瓷万佳新材料科技股份有限公司",
    "编号": "GR202242001636"
  },
  {
    "名称": "武汉讯锡云科技有限公司",
    "编号": "GR202242001637"
  },
  {
    "名称": "武汉炫幕科技有限公司",
    "编号": "GR202242001638"
  },
  {
    "名称": "宜昌喜旺食品有限公司",
    "编号": "GR202242001639"
  },
  {
    "名称": "湖北凌然环保科技有限公司",
    "编号": "GR202242001640"
  },
  {
    "名称": "武汉开明高新科技有限公司",
    "编号": "GR202242001641"
  },
  {
    "名称": "武汉泰坦互娱网络科技有限公司",
    "编号": "GR202242001642"
  },
  {
    "名称": "大冶市正明铝业有限责任公司",
    "编号": "GR202242001643"
  },
  {
    "名称": "湖北央中巨石信息技术有限公司",
    "编号": "GR202242001644"
  },
  {
    "名称": "武汉捷誉峰科技有限公司",
    "编号": "GR202242001645"
  },
  {
    "名称": "湖北敏能汽车零部件有限公司",
    "编号": "GR202242001646"
  },
  {
    "名称": "湖北云兴钢构制造有限公司",
    "编号": "GR202242001647"
  },
  {
    "名称": "湖北童话工艺礼品有限公司",
    "编号": "GR202242001648"
  },
  {
    "名称": "湖北凯龙楚兴化工集团有限公司",
    "编号": "GR202242001649"
  },
  {
    "名称": "沙洋秦江人造板有限公司",
    "编号": "GR202242001650"
  },
  {
    "名称": "十堰深思科技有限公司",
    "编号": "GR202242001651"
  },
  {
    "名称": "湖北鼎欣工程咨询有限公司",
    "编号": "GR202242001652"
  },
  {
    "名称": "湖北京信通模塑科技有限公司",
    "编号": "GR202242001653"
  },
  {
    "名称": "湖北龙兴腾达汽车零部件有限公司",
    "编号": "GR202242001654"
  },
  {
    "名称": "武汉海德斯路科技有限公司",
    "编号": "GR202242001655"
  },
  {
    "名称": "湖北天欣塑料配件股份有限公司",
    "编号": "GR202242001656"
  },
  {
    "名称": "咸宁市洪盛模具科技有限公司",
    "编号": "GR202242001657"
  },
  {
    "名称": "武汉松捷科技有限公司",
    "编号": "GR202242001658"
  },
  {
    "名称": "麻城市大恒汽车零部件股份有限公司",
    "编号": "GR202242001659"
  },
  {
    "名称": "湖北侨光石化装备股份有限公司",
    "编号": "GR202242001660"
  },
  {
    "名称": "湖北波力特照明有限公司",
    "编号": "GR202242001661"
  },
  {
    "名称": "十堰达力热系统科技有限公司",
    "编号": "GR202242001662"
  },
  {
    "名称": "武汉百育智慧科技有限公司",
    "编号": "GR202242001663"
  },
  {
    "名称": "黄石法姆药业股份有限公司",
    "编号": "GR202242001664"
  },
  {
    "名称": "湖北申田新材料科技有限公司",
    "编号": "GR202242001665"
  },
  {
    "名称": "湖北神丹健康食品有限公司",
    "编号": "GR202242001666"
  },
  {
    "名称": "荆州市怦然心动文化传媒有限公司",
    "编号": "GR202242001667"
  },
  {
    "名称": "武汉网贤信息技术有限公司",
    "编号": "GR202242001668"
  },
  {
    "名称": "湖北科谱瑞环境资源科技有限公司",
    "编号": "GR202242001669"
  },
  {
    "名称": "襄阳昊瑞模具有限公司",
    "编号": "GR202242001670"
  },
  {
    "名称": "湖北纽睿德防务科技有限公司",
    "编号": "GR202242001671"
  },
  {
    "名称": "武汉普诺展览展示有限公司",
    "编号": "GR202242001672"
  },
  {
    "名称": "湖北欧斯兰环保材料有限公司",
    "编号": "GR202242001673"
  },
  {
    "名称": "武汉翼玖车服科技有限公司",
    "编号": "GR202242001674"
  },
  {
    "名称": "武汉捷讯信息技术有限公司",
    "编号": "GR202242001675"
  },
  {
    "名称": "十堰东风三立车灯有限公司",
    "编号": "GR202242001676"
  },
  {
    "名称": "湖北双兴石膏股份有限公司",
    "编号": "GR202242001677"
  },
  {
    "名称": "汉川市凯特塑料制品股份有限公司",
    "编号": "GR202242001678"
  },
  {
    "名称": "湖北蜜秀影视传媒有限公司",
    "编号": "GR202242001679"
  },
  {
    "名称": "湖北优软汽车科技有限公司",
    "编号": "GR202242001680"
  },
  {
    "名称": "湖北鼎祥钢铁炉料有限公司",
    "编号": "GR202242001681"
  },
  {
    "名称": "襄阳豪聪机电有限公司",
    "编号": "GR202242001682"
  },
  {
    "名称": "湖北农科谷生态科技有限公司",
    "编号": "GR202242001683"
  },
  {
    "名称": "湖北百康光电科技有限公司",
    "编号": "GR202242001684"
  },
  {
    "名称": "武汉利楚商务服务有限公司",
    "编号": "GR202242001685"
  },
  {
    "名称": "宜昌宇宏通达新型路面材料有限责任公司",
    "编号": "GR202242001686"
  },
  {
    "名称": "武汉海德克机电有限公司",
    "编号": "GR202242001687"
  },
  {
    "名称": "武汉珞珈弘毅电气技术有限公司",
    "编号": "GR202242001688"
  },
  {
    "名称": "武汉颍河感知科技有限公司",
    "编号": "GR202242001689"
  },
  {
    "名称": "湖北省哈福生物化学有限公司",
    "编号": "GR202242001690"
  },
  {
    "名称": "湖北钠斯网络科技有限公司",
    "编号": "GR202242001691"
  },
  {
    "名称": "中建三局工程设计有限公司",
    "编号": "GR202242001692"
  },
  {
    "名称": "宜昌西部化工有限公司",
    "编号": "GR202242001693"
  },
  {
    "名称": "湖北高翔节能科技有限责任公司",
    "编号": "GR202242001694"
  },
  {
    "名称": "武汉艾联科技有限公司",
    "编号": "GR202242001695"
  },
  {
    "名称": "湖北友丰科技有限公司",
    "编号": "GR202242001696"
  },
  {
    "名称": "翊鹏（湖北）实业有限公司",
    "编号": "GR202242001697"
  },
  {
    "名称": "武汉集远智慧科技有限公司",
    "编号": "GR202242001698"
  },
  {
    "名称": "湖北省九宫山茶业有限公司",
    "编号": "GR202242001699"
  },
  {
    "名称": "湖北天雪制冷科技有限公司",
    "编号": "GR202242001700"
  },
  {
    "名称": "武汉市麦田映象文化传播有限公司",
    "编号": "GR202242001701"
  },
  {
    "名称": "武汉利环康实验设备有限公司",
    "编号": "GR202242001702"
  },
  {
    "名称": "黄石市华石材料科技有限公司",
    "编号": "GR202242001703"
  },
  {
    "名称": "湖北惠生药业有限公司",
    "编号": "GR202242001704"
  },
  {
    "名称": "武汉有文心文化传媒有限公司",
    "编号": "GR202242001705"
  },
  {
    "名称": "湖北润力专用汽车有限公司",
    "编号": "GR202242001706"
  },
  {
    "名称": "襄阳西顿自动化仪表有限公司",
    "编号": "GR202242001707"
  },
  {
    "名称": "海生源（湖北）环保能源有限公司",
    "编号": "GR202242001708"
  },
  {
    "名称": "武汉厚溥数字科技有限公司",
    "编号": "GR202242001709"
  },
  {
    "名称": "湖北裕发电气有限公司",
    "编号": "GR202242001710"
  },
  {
    "名称": "武汉鼎盛恒润仪器有限公司",
    "编号": "GR202242001711"
  },
  {
    "名称": "湖北捷玛换热设备制造有限公司",
    "编号": "GR202242001712"
  },
  {
    "名称": "湖北脉源通档案管理有限公司",
    "编号": "GR202242001713"
  },
  {
    "名称": "湖北力芯半导体有限公司",
    "编号": "GR202242001714"
  },
  {
    "名称": "武汉垒图信息科技有限公司",
    "编号": "GR202242001715"
  },
  {
    "名称": "宜城华康光学有限责任公司",
    "编号": "GR202242001716"
  },
  {
    "名称": "中电科创智联（武汉）有限责任公司",
    "编号": "GR202242001717"
  },
  {
    "名称": "武汉乐友文化传媒有限公司",
    "编号": "GR202242001718"
  },
  {
    "名称": "武汉人和睿视科技有限公司",
    "编号": "GR202242001719"
  },
  {
    "名称": "泽腾过滤设备（湖北）有限公司",
    "编号": "GR202242001720"
  },
  {
    "名称": "纯水一号环保科技（湖北）有限公司",
    "编号": "GR202242001721"
  },
  {
    "名称": "湖北亨威铝业有限公司",
    "编号": "GR202242001722"
  },
  {
    "名称": "武汉鸿诚工程咨询管理有限责任公司",
    "编号": "GR202242001723"
  },
  {
    "名称": "湖北山叶环保科技股份有限公司",
    "编号": "GR202242001724"
  },
  {
    "名称": "湖北云雷信息技术有限公司",
    "编号": "GR202242001725"
  },
  {
    "名称": "武汉威和光电股份有限公司",
    "编号": "GR202242001726"
  },
  {
    "名称": "湖北新辉船用机械有限公司",
    "编号": "GR202242001727"
  },
  {
    "名称": "湖北海星通信科技有限公司",
    "编号": "GR202242001728"
  },
  {
    "名称": "天门市怡天新能源开发有限公司",
    "编号": "GR202242001729"
  },
  {
    "名称": "武汉盛博达启科技有限公司",
    "编号": "GR202242001730"
  },
  {
    "名称": "武汉烁德金属制品有限公司",
    "编号": "GR202242001731"
  },
  {
    "名称": "荆门市华源荆蓝防水科技有限公司",
    "编号": "GR202242001732"
  },
  {
    "名称": "武汉智瑞捷电气技术有限公司",
    "编号": "GR202242001733"
  },
  {
    "名称": "钟祥市鸿晖纺织有限公司",
    "编号": "GR202242001734"
  },
  {
    "名称": "博联众科（武汉）科技有限公司",
    "编号": "GR202242001735"
  },
  {
    "名称": "武汉美鹿科技有限公司",
    "编号": "GR202242001736"
  },
  {
    "名称": "武汉兴创智能科技有限公司",
    "编号": "GR202242001737"
  },
  {
    "名称": "湖北瑞诺施新材料有限公司",
    "编号": "GR202242001738"
  },
  {
    "名称": "武汉康泰威新材料技术有限公司",
    "编号": "GR202242001739"
  },
  {
    "名称": "吉和昌新材料（荆门）有限公司",
    "编号": "GR202242001740"
  },
  {
    "名称": "武汉众腾智创信息技术有限公司",
    "编号": "GR202242001741"
  },
  {
    "名称": "赤壁市中亮光电科技有限公司",
    "编号": "GR202242001742"
  },
  {
    "名称": "武汉正达康元生物科技有限公司",
    "编号": "GR202242001743"
  },
  {
    "名称": "子非鱼（湖北）信息科技有限公司",
    "编号": "GR202242001744"
  },
  {
    "名称": "中软信通（宜昌）科技有限公司",
    "编号": "GR202242001745"
  },
  {
    "名称": "湖北航宇精工科技有限公司",
    "编号": "GR202242001746"
  },
  {
    "名称": "武汉云途信息系统有限公司",
    "编号": "GR202242001747"
  },
  {
    "名称": "湖北一致魔芋生物科技股份有限公司",
    "编号": "GR202242001748"
  },
  {
    "名称": "湖北丰合医疗器械有限公司",
    "编号": "GR202242001749"
  },
  {
    "名称": "湖北利普达管业科技有限公司",
    "编号": "GR202242001750"
  },
  {
    "名称": "武汉沃德自动化技术有限公司",
    "编号": "GR202242001751"
  },
  {
    "名称": "湖北东润阿科米汽车有限公司",
    "编号": "GR202242001752"
  },
  {
    "名称": "湖北翊通铸业有限公司",
    "编号": "GR202242001753"
  },
  {
    "名称": "湖北隆信裕再生资源有限公司",
    "编号": "GR202242001754"
  },
  {
    "名称": "武汉中云互联科技有限公司",
    "编号": "GR202242001755"
  },
  {
    "名称": "鄂州蓝工水务有限公司",
    "编号": "GR202242001756"
  },
  {
    "名称": "湖北君立方网络科技有限公司",
    "编号": "GR202242001757"
  },
  {
    "名称": "湖北讯甲科技有限公司",
    "编号": "GR202242001758"
  },
  {
    "名称": "十堰同创传动技术有限公司",
    "编号": "GR202242001759"
  },
  {
    "名称": "武汉易摩特科技有限公司",
    "编号": "GR202242001760"
  },
  {
    "名称": "武汉市富仁空调设备有限公司",
    "编号": "GR202242001761"
  },
  {
    "名称": "湖北维尔信息技术有限公司",
    "编号": "GR202242001762"
  },
  {
    "名称": "湖北新明珠绿色建材科技有限公司",
    "编号": "GR202242001763"
  },
  {
    "名称": "中铁大桥局第七工程有限公司",
    "编号": "GR202242001764"
  },
  {
    "名称": "湖北英草堂药业有限公司",
    "编号": "GR202242001765"
  },
  {
    "名称": "武汉思维通达软件有限公司",
    "编号": "GR202242001766"
  },
  {
    "名称": "湖北鼎高智能装备有限公司",
    "编号": "GR202242001767"
  },
  {
    "名称": "黄石市鑫溢新材料科技有限公司",
    "编号": "GR202242001768"
  },
  {
    "名称": "武汉光庭信息技术股份有限公司",
    "编号": "GR202242001769"
  },
  {
    "名称": "宜昌迈威机械制造有限公司",
    "编号": "GR202242001770"
  },
  {
    "名称": "湖北帝成环卫科技有限公司",
    "编号": "GR202242001771"
  },
  {
    "名称": "武汉橙智信息技术有限公司",
    "编号": "GR202242001772"
  },
  {
    "名称": "湖北海讯泰克机械制造有限责任公司",
    "编号": "GR202242001773"
  },
  {
    "名称": "湖北华贵食品有限公司",
    "编号": "GR202242001774"
  },
  {
    "名称": "武汉心驰神往科技有限公司",
    "编号": "GR202242001775"
  },
  {
    "名称": "荆州市新东源防水材料有限公司",
    "编号": "GR202242001776"
  },
  {
    "名称": "十堰中合农业科技发展有限公司",
    "编号": "GR202242001777"
  },
  {
    "名称": "麻城市德应米业股份有限公司",
    "编号": "GR202242001778"
  },
  {
    "名称": "湖北鲲腾新能源科技有限公司",
    "编号": "GR202242001779"
  },
  {
    "名称": "宜昌海博软件科技有限公司",
    "编号": "GR202242001780"
  },
  {
    "名称": "宜都长江机械设备有限公司",
    "编号": "GR202242001781"
  },
  {
    "名称": "湖北嵘钢汽车零部件科技有限公司",
    "编号": "GR202242001782"
  },
  {
    "名称": "武汉慧康利兹食品有限公司",
    "编号": "GR202242001783"
  },
  {
    "名称": "武汉吉百瑞科技有限责任公司",
    "编号": "GR202242001784"
  },
  {
    "名称": "湖北启明科技有限公司",
    "编号": "GR202242001785"
  },
  {
    "名称": "湖北协利纺织有限公司",
    "编号": "GR202242001786"
  },
  {
    "名称": "襄阳三方缘建设工程质量检测有限公司",
    "编号": "GR202242001787"
  },
  {
    "名称": "襄阳天工电通网络科技有限公司",
    "编号": "GR202242001788"
  },
  {
    "名称": "捷云巨和（武汉）科技有限公司",
    "编号": "GR202242001789"
  },
  {
    "名称": "湖北中科产业技术研究院有限公司",
    "编号": "GR202242001790"
  },
  {
    "名称": "东风汽车动力零部件有限公司",
    "编号": "GR202242001791"
  },
  {
    "名称": "宜昌寰发网络科技有限公司",
    "编号": "GR202242001792"
  },
  {
    "名称": "武汉蓝晶优创激光科技有限公司",
    "编号": "GR202242001793"
  },
  {
    "名称": "宜昌一凡船舶设计有限公司",
    "编号": "GR202242001794"
  },
  {
    "名称": "武汉友琪科技有限公司",
    "编号": "GR202242001795"
  },
  {
    "名称": "百里半（武汉）网络技术有限公司",
    "编号": "GR202242001796"
  },
  {
    "名称": "黄冈宏文盛人防工程有限公司",
    "编号": "GR202242001797"
  },
  {
    "名称": "武汉谷泰软件科技有限公司",
    "编号": "GR202242001798"
  },
  {
    "名称": "湖北科瑞半导体技术有限公司",
    "编号": "GR202242001799"
  },
  {
    "名称": "智伟燊（武汉）能源科技有限公司",
    "编号": "GR202242001800"
  },
  {
    "名称": "宜昌云友软件有限公司",
    "编号": "GR202242001801"
  },
  {
    "名称": "中国葛洲坝集团市政工程有限公司",
    "编号": "GR202242001802"
  },
  {
    "名称": "康诚科瑞医药研发（武汉）有限公司",
    "编号": "GR202242001803"
  },
  {
    "名称": "武汉市海睿科创科技有限公司",
    "编号": "GR202242001804"
  },
  {
    "名称": "湖北蕲春中健米业有限公司",
    "编号": "GR202242001805"
  },
  {
    "名称": "武汉麦思威科技有限公司",
    "编号": "GR202242001806"
  },
  {
    "名称": "湖北凯美铝业有限公司",
    "编号": "GR202242001807"
  },
  {
    "名称": "湖北神电汽车电机有限公司",
    "编号": "GR202242001808"
  },
  {
    "名称": "武汉杰品金属制品有限公司",
    "编号": "GR202242001809"
  },
  {
    "名称": "襄阳普菲斯联合动力科技有限公司",
    "编号": "GR202242001810"
  },
  {
    "名称": "武汉丹港生物科技有限公司",
    "编号": "GR202242001811"
  },
  {
    "名称": "武汉建荣岩土工程有限公司",
    "编号": "GR202242001812"
  },
  {
    "名称": "武汉赤辰科技有限公司",
    "编号": "GR202242001813"
  },
  {
    "名称": "精晶科技（湖北）有限公司",
    "编号": "GR202242001814"
  },
  {
    "名称": "武汉市艾梦科技有限公司",
    "编号": "GR202242001815"
  },
  {
    "名称": "武汉高科恒大光电股份有限公司",
    "编号": "GR202242001816"
  },
  {
    "名称": "咸宁三六传动设备股份有限公司",
    "编号": "GR202242001817"
  },
  {
    "名称": "湖北绿林口环保建材有限公司",
    "编号": "GR202242001818"
  },
  {
    "名称": "湖北司克嘉耐磨橡胶制品有限公司",
    "编号": "GR202242001819"
  },
  {
    "名称": "湖北鄂南新华印刷包装股份有限公司",
    "编号": "GR202242001820"
  },
  {
    "名称": "湖北伟通管业科技有限公司",
    "编号": "GR202242001821"
  },
  {
    "名称": "湖北德重精线有限公司",
    "编号": "GR202242001822"
  },
  {
    "名称": "武汉纵岳信息技术有限公司",
    "编号": "GR202242001823"
  },
  {
    "名称": "强惠富（武汉）科技有限公司",
    "编号": "GR202242001824"
  },
  {
    "名称": "武汉赛津科技有限公司",
    "编号": "GR202242001825"
  },
  {
    "名称": "武汉伟嘉生物技术有限公司",
    "编号": "GR202242001826"
  },
  {
    "名称": "湖北森宇齿轮传动股份有限公司",
    "编号": "GR202242001827"
  },
  {
    "名称": "湖北中涂科技有限公司",
    "编号": "GR202242001828"
  },
  {
    "名称": "楚天智能科技有限公司",
    "编号": "GR202242001829"
  },
  {
    "名称": "湖北天斌机械有限公司",
    "编号": "GR202242001830"
  },
  {
    "名称": "湖北东联天禹新材料有限公司",
    "编号": "GR202242001831"
  },
  {
    "名称": "襄阳誉德模具有限公司",
    "编号": "GR202242001832"
  },
  {
    "名称": "十堰市明诚线缆有限公司",
    "编号": "GR202242001833"
  },
  {
    "名称": "咸宁方片互娱网络有限公司",
    "编号": "GR202242001834"
  },
  {
    "名称": "武汉龙智信医疗投资管理有限公司",
    "编号": "GR202242001835"
  },
  {
    "名称": "武汉合利坚智能科技有限公司",
    "编号": "GR202242001836"
  },
  {
    "名称": "湖北天碧再生资源有限公司",
    "编号": "GR202242001837"
  },
  {
    "名称": "武汉星智绘空间信息技术有限公司",
    "编号": "GR202242001838"
  },
  {
    "名称": "湖北既济源电力发展有限公司",
    "编号": "GR202242001839"
  },
  {
    "名称": "武汉旭思科技有限公司",
    "编号": "GR202242001840"
  },
  {
    "名称": "武汉交发船舶设计有限公司",
    "编号": "GR202242001841"
  },
  {
    "名称": "湖北骏源豆制品股份有限公司",
    "编号": "GR202242001842"
  },
  {
    "名称": "武汉微谷科技有限公司",
    "编号": "GR202242001843"
  },
  {
    "名称": "湖北积健实业有限公司",
    "编号": "GR202242001844"
  },
  {
    "名称": "宜昌冠力成电子科技有限公司",
    "编号": "GR202242001845"
  },
  {
    "名称": "武汉造风者教育科技有限公司",
    "编号": "GR202242001846"
  },
  {
    "名称": "湖北兴兴环保科技有限公司",
    "编号": "GR202242001847"
  },
  {
    "名称": "湖北祺美中检联检测有限公司",
    "编号": "GR202242001848"
  },
  {
    "名称": "湖北金源麻纺织科技有限公司",
    "编号": "GR202242001849"
  },
  {
    "名称": "武汉趣心里科技有限公司",
    "编号": "GR202242001850"
  },
  {
    "名称": "武汉中博电气设备制造有限公司",
    "编号": "GR202242001851"
  },
  {
    "名称": "武汉善音科技有限公司",
    "编号": "GR202242001852"
  },
  {
    "名称": "湖北佳玛驰生态农业有限公司",
    "编号": "GR202242001853"
  },
  {
    "名称": "湖北圣火钙业有限公司",
    "编号": "GR202242001854"
  },
  {
    "名称": "湖北亚普诺迪科技发展有限公司",
    "编号": "GR202242001855"
  },
  {
    "名称": "黄石市东楚铝加工技术研究院有限公司",
    "编号": "GR202242001856"
  },
  {
    "名称": "湖北久星源复合材料有限公司",
    "编号": "GR202242001857"
  },
  {
    "名称": "湖北智领物联智能制造有限公司",
    "编号": "GR202242001858"
  },
  {
    "名称": "湖北蓝砚智能科技有限公司",
    "编号": "GR202242001859"
  },
  {
    "名称": "武汉禾瑞工程设计有限公司",
    "编号": "GR202242001860"
  },
  {
    "名称": "武汉方圆保温材料有限公司",
    "编号": "GR202242001861"
  },
  {
    "名称": "湖北大鹏网络科技有限公司",
    "编号": "GR202242001862"
  },
  {
    "名称": "崇阳航欣纺织有限公司",
    "编号": "GR202242001863"
  },
  {
    "名称": "武汉特盟信息技术有限公司",
    "编号": "GR202242001864"
  },
  {
    "名称": "湖北远程汽车部件有限公司",
    "编号": "GR202242001865"
  },
  {
    "名称": "武汉兆航精密工业有限公司",
    "编号": "GR202242001866"
  },
  {
    "名称": "武汉宇测科技有限公司",
    "编号": "GR202242001867"
  },
  {
    "名称": "武汉三米科技有限公司",
    "编号": "GR202242001868"
  },
  {
    "名称": "武汉锦瑞技术有限公司",
    "编号": "GR202242001869"
  },
  {
    "名称": "襄阳鹏启电子有限公司",
    "编号": "GR202242001870"
  },
  {
    "名称": "湖北厚品生物科技有限公司",
    "编号": "GR202242001871"
  },
  {
    "名称": "拜尔液压动力（武汉）股份有限公司",
    "编号": "GR202242001872"
  },
  {
    "名称": "黄石创世达换热设备有限公司",
    "编号": "GR202242001873"
  },
  {
    "名称": "湖北山太子农业科技有限公司",
    "编号": "GR202242001874"
  },
  {
    "名称": "武汉天航科技有限公司",
    "编号": "GR202242001875"
  },
  {
    "名称": "十堰天巽汽车零部件股份有限公司",
    "编号": "GR202242001876"
  },
  {
    "名称": "当阳市富豪实业有限责任公司",
    "编号": "GR202242001877"
  },
  {
    "名称": "湖北华夏科显电子有限公司",
    "编号": "GR202242001878"
  },
  {
    "名称": "湖北鑫越海汽车零部件有限公司",
    "编号": "GR202242001879"
  },
  {
    "名称": "武汉联兴环保科技有限公司",
    "编号": "GR202242001880"
  },
  {
    "名称": "武汉麦达电子有限公司",
    "编号": "GR202242001881"
  },
  {
    "名称": "襄阳泽东化工集团股份有限公司",
    "编号": "GR202242001882"
  },
  {
    "名称": "武汉科恒工控工程有限责任公司",
    "编号": "GR202242001883"
  },
  {
    "名称": "湖北天利化建工程有限公司",
    "编号": "GR202242001884"
  },
  {
    "名称": "湖北通泰众恒机电科技有限公司",
    "编号": "GR202242001885"
  },
  {
    "名称": "湖北天龙石墨碳业有限公司",
    "编号": "GR202242001886"
  },
  {
    "名称": "武汉恒升建筑科技开发工程有限公司",
    "编号": "GR202242001887"
  },
  {
    "名称": "武汉至唯科技有限公司",
    "编号": "GR202242001888"
  },
  {
    "名称": "湖北金正邦电子技术有限责任公司",
    "编号": "GR202242001889"
  },
  {
    "名称": "荆州市今印印务有限公司",
    "编号": "GR202242001890"
  },
  {
    "名称": "湖北省匠心智观文化传播有限公司",
    "编号": "GR202242001891"
  },
  {
    "名称": "湖北省麻城市华闽石材有限公司",
    "编号": "GR202242001892"
  },
  {
    "名称": "湖北省智云冷锋环保科技有限公司",
    "编号": "GR202242001893"
  },
  {
    "名称": "湖北晶昱玻璃制品有限公司",
    "编号": "GR202242001894"
  },
  {
    "名称": "襄阳科威电气有限公司",
    "编号": "GR202242001895"
  },
  {
    "名称": "武汉中地云申科技有限公司",
    "编号": "GR202242001896"
  },
  {
    "名称": "东风悦享科技有限公司",
    "编号": "GR202242001897"
  },
  {
    "名称": "晶全照明科技有限公司",
    "编号": "GR202242001898"
  },
  {
    "名称": "湖北鑫来利陶瓷发展有限公司",
    "编号": "GR202242001899"
  },
  {
    "名称": "湖北邱氏节能建材高新技术股份有限公司",
    "编号": "GR202242001900"
  },
  {
    "名称": "宜昌砼富公路养护有限公司",
    "编号": "GR202242001901"
  },
  {
    "名称": "荆州市元泽石油设备有限公司",
    "编号": "GR202242001902"
  },
  {
    "名称": "宜昌精联电子科技有限公司",
    "编号": "GR202242001903"
  },
  {
    "名称": "武汉实为信息技术股份有限公司",
    "编号": "GR202242001904"
  },
  {
    "名称": "武汉精达自控仪表有限公司",
    "编号": "GR202242001905"
  },
  {
    "名称": "湖北安源安全环保科技有限公司",
    "编号": "GR202242001906"
  }
]