[
  {
    "名称": "大连云智慧通科技有限公司",
    "编号": "GR202421200860"
  },
  {
    "名称": "三峡新能源大连发电有限公司",
    "编号": "GR202421200861"
  },
  {
    "名称": "大连辽南起重机器有限公司",
    "编号": "GR202421200862"
  },
  {
    "名称": "大连科森环境工程有限公司",
    "编号": "GR202421200863"
  },
  {
    "名称": "大连铧友工业有限公司",
    "编号": "GR202421200864"
  },
  {
    "名称": "大连富士发英有限公司",
    "编号": "GR202421200865"
  },
  {
    "名称": "大连恒辉信创科技有限公司",
    "编号": "GR202421200866"
  },
  {
    "名称": "大连慧森精密机械有限公司",
    "编号": "GR202421200867"
  },
  {
    "名称": "缔奇盛世(大连)体育科技有限公司",
    "编号": "GR202421200868"
  },
  {
    "名称": "吉日门窗（大连）有限公司",
    "编号": "GR202421200869"
  },
  {
    "名称": "大连市思远信息科技有限公司",
    "编号": "GR202421200870"
  },
  {
    "名称": "大连睿琪石化泵业有限公司",
    "编号": "GR202421200871"
  },
  {
    "名称": "大连中比动力电池有限公司",
    "编号": "GR202421200872"
  },
  {
    "名称": "大连元合智汇科技有限公司",
    "编号": "GR202421200873"
  },
  {
    "名称": "兰泰克传动设备（大连保税区）有限公司",
    "编号": "GR202421200874"
  },
  {
    "名称": "大连乐博尔液压设备制造有限公司",
    "编号": "GR202421200875"
  },
  {
    "名称": "大连辽安中科实业有限公司",
    "编号": "GR202421200876"
  },
  {
    "名称": "大连桦通环保设备科技有限公司",
    "编号": "GR202421200877"
  },
  {
    "名称": "大连启源节能环保科技有限公司",
    "编号": "GR202421200878"
  },
  {
    "名称": "大连诚通工程技术有限公司",
    "编号": "GR202421200879"
  },
  {
    "名称": "中车大连电力牵引研发中心有限公司",
    "编号": "GR202421200880"
  },
  {
    "名称": "乾佰熙（大连）生物科技有限公司",
    "编号": "GR202421200881"
  },
  {
    "名称": "大连铭悦精工有限公司",
    "编号": "GR202421200882"
  },
  {
    "名称": "大连爱碧克空调配件有限公司",
    "编号": "GR202421200883"
  },
  {
    "名称": "大连瀚宇精密模具有限公司",
    "编号": "GR202421200884"
  },
  {
    "名称": "大连麦子信息技术有限公司",
    "编号": "GR202421200885"
  },
  {
    "名称": "大连久鼎祥瑞特种工程技术研究院有限公司",
    "编号": "GR202421200886"
  },
  {
    "名称": "宜嘉仁信息科技（大连）有限公司",
    "编号": "GR202421200887"
  },
  {
    "名称": "大连国润金属制品有限公司",
    "编号": "GR202421200888"
  },
  {
    "名称": "大连东冶天成工业装备有限公司",
    "编号": "GR202421200889"
  },
  {
    "名称": "大连群策鼎高信息科技有限公司",
    "编号": "GR202421200890"
  },
  {
    "名称": "大连弘信泰电子有限公司",
    "编号": "GR202421200891"
  },
  {
    "名称": "中汇(大连)智能设备技术有限公司",
    "编号": "GR202421200892"
  },
  {
    "名称": "大连市沃德鑫兴自控设备有限公司",
    "编号": "GR202421200893"
  },
  {
    "名称": "大连荣德科技有限公司",
    "编号": "GR202421200894"
  },
  {
    "名称": "大连助企科技有限公司",
    "编号": "GR202421200895"
  },
  {
    "名称": "大连执象信息有限公司",
    "编号": "GR202421200896"
  },
  {
    "名称": "大连正大清源建筑材料有限公司",
    "编号": "GR202421200897"
  },
  {
    "名称": "大连天汇服装有限公司",
    "编号": "GR202421200898"
  },
  {
    "名称": "大连跃飞建筑咨询有限公司",
    "编号": "GR202421200899"
  },
  {
    "名称": "大连天意精密机械有限公司",
    "编号": "GR202421200900"
  },
  {
    "名称": "大连上丰选矿药剂有限公司",
    "编号": "GR202421200901"
  },
  {
    "名称": "大连金昇印务有限公司",
    "编号": "GR202421200902"
  },
  {
    "名称": "延长中科（大连）能源科技股份有限公司",
    "编号": "GR202421200903"
  },
  {
    "名称": "大连铭阳纸制品有限公司",
    "编号": "GR202421200904"
  },
  {
    "名称": "大连利明电力电气有限公司",
    "编号": "GR202421200905"
  },
  {
    "名称": "智辰航科智能制造（大连）有限公司",
    "编号": "GR202421200906"
  },
  {
    "名称": "大连榴客食品有限公司",
    "编号": "GR202421200907"
  },
  {
    "名称": "瓦房店爱国轴承研究院有限公司",
    "编号": "GR202421200908"
  },
  {
    "名称": "大连南港机械制造有限公司",
    "编号": "GR202421200909"
  },
  {
    "名称": "大连优服信息技术有限公司",
    "编号": "GR202421200910"
  },
  {
    "名称": "大连凯御电子有限公司",
    "编号": "GR202421200911"
  },
  {
    "名称": "职道（大连）企业管理咨询有限公司",
    "编号": "GR202421200912"
  },
  {
    "名称": "宇泰工业科技（大连）有限公司",
    "编号": "GR202421200913"
  },
  {
    "名称": "田马农业（大连）有限公司",
    "编号": "GR202421200914"
  },
  {
    "名称": "大连宏伟液压重工有限公司",
    "编号": "GR202421200915"
  },
  {
    "名称": "大连鸣鸿机械制造有限公司",
    "编号": "GR202421200916"
  },
  {
    "名称": "大连华邦化学有限公司",
    "编号": "GR202421200917"
  },
  {
    "名称": "大连大山铜业有限公司",
    "编号": "GR202421200918"
  },
  {
    "名称": "大连渤鑫金属热处理有限公司",
    "编号": "GR202421200919"
  },
  {
    "名称": "大连卓远云科技有限公司",
    "编号": "GR202421200920"
  },
  {
    "名称": "大连锦辉盛世科技有限公司",
    "编号": "GR202421200921"
  },
  {
    "名称": "大连速渲科技有限公司",
    "编号": "GR202421200922"
  },
  {
    "名称": "大连中航钢研特种材料有限公司",
    "编号": "GR202421200923"
  },
  {
    "名称": "大连铁丰轨道交通装备有限责任公司",
    "编号": "GR202421200924"
  },
  {
    "名称": "大连华璟科技有限公司",
    "编号": "GR202421200925"
  },
  {
    "名称": "中有为(大连)精密光电科技有限公司",
    "编号": "GR202421200926"
  },
  {
    "名称": "大连市裕隆金属结构有限公司",
    "编号": "GR202421200927"
  },
  {
    "名称": "大连金氏重工有限公司",
    "编号": "GR202421200928"
  },
  {
    "名称": "大连瑞恒德科技有限公司",
    "编号": "GR202421200929"
  },
  {
    "名称": "大连金百味面业有限公司",
    "编号": "GR202421200930"
  },
  {
    "名称": "大连晟东电子有限公司",
    "编号": "GR202421200931"
  },
  {
    "名称": "大连海米视界信息技术有限公司",
    "编号": "GR202421200932"
  },
  {
    "名称": "大连民生科技发展有限公司",
    "编号": "GR202421200933"
  },
  {
    "名称": "大连天鹏恒宇精密机械有限公司",
    "编号": "GR202421200934"
  },
  {
    "名称": "大连富成包装有限公司",
    "编号": "GR202421200935"
  },
  {
    "名称": "次世代模塑科技(大连)有限公司",
    "编号": "GR202421200936"
  },
  {
    "名称": "大连新希望智造精密工具有限公司",
    "编号": "GR202421200937"
  },
  {
    "名称": "大连瑞冠创新科技有限公司",
    "编号": "GR202421200938"
  },
  {
    "名称": "大连博路精密机械有限公司",
    "编号": "GR202421200939"
  },
  {
    "名称": "大连希梵文化科技发展有限公司",
    "编号": "GR202421200940"
  },
  {
    "名称": "翰麒（大连）企业管理有限公司",
    "编号": "GR202421200941"
  },
  {
    "名称": "辽宁宜隆能源技术有限公司",
    "编号": "GR202421200942"
  },
  {
    "名称": "大连合兴电子有限公司",
    "编号": "GR202421200943"
  },
  {
    "名称": "芽津电子（大连）有限公司",
    "编号": "GR202421200944"
  },
  {
    "名称": "大连兴元深冷阀门有限公司",
    "编号": "GR202421200945"
  },
  {
    "名称": "大连诚隆钢结构制作有限公司",
    "编号": "GR202421200946"
  },
  {
    "名称": "大连桑拓生物新技术有限公司",
    "编号": "GR202421200947"
  },
  {
    "名称": "大连卓美新材料科技有限公司",
    "编号": "GR202421200948"
  },
  {
    "名称": "大连弘润全谷物食品有限公司",
    "编号": "GR202421200949"
  },
  {
    "名称": "大连兆寰现代建筑科技有限公司",
    "编号": "GR202421200950"
  },
  {
    "名称": "大连同旺蜂窝纸制品有限公司",
    "编号": "GR202421200951"
  },
  {
    "名称": "大连智慧星云科技有限公司",
    "编号": "GR202421200952"
  },
  {
    "名称": "欧利塔（大连）汽车用品有限公司",
    "编号": "GR202421200953"
  },
  {
    "名称": "语祯物联网信息科技（大连）有限公司",
    "编号": "GR202421200954"
  },
  {
    "名称": "学术纵横（大连）人才管理咨询有限公司",
    "编号": "GR202421200955"
  },
  {
    "名称": "大连中玺科技有限公司",
    "编号": "GR202421200956"
  },
  {
    "名称": "大连恒聚机电工程有限公司",
    "编号": "GR202421200957"
  },
  {
    "名称": "大连联创兄弟网络科技文化有限公司",
    "编号": "GR202421200958"
  },
  {
    "名称": "大连富灿安科技有限公司",
    "编号": "GR202421200959"
  },
  {
    "名称": "大连智多科技有限公司",
    "编号": "GR202421200960"
  },
  {
    "名称": "大连三合基申科技发展有限公司",
    "编号": "GR202421200961"
  },
  {
    "名称": "大连三丰盛重工机械有限公司",
    "编号": "GR202421200962"
  },
  {
    "名称": "大连睿恒科技有限公司",
    "编号": "GR202421200963"
  },
  {
    "名称": "大连盛瑞德流体设备有限公司",
    "编号": "GR202421200964"
  },
  {
    "名称": "大连九国春生物制品有限公司",
    "编号": "GR202421200965"
  },
  {
    "名称": "大连丰佳鑫业金属制品有限公司",
    "编号": "GR202421200966"
  },
  {
    "名称": "大连炫蓝科技有限公司",
    "编号": "GR202421200967"
  },
  {
    "名称": "大连海普润滑密封技术有限公司",
    "编号": "GR202421200968"
  },
  {
    "名称": "大连宇坤德隆科技发展有限公司",
    "编号": "GR202421200969"
  },
  {
    "名称": "大连北方精工金属制品有限公司",
    "编号": "GR202421200970"
  },
  {
    "名称": "林恩贝尔科技（大连）有限公司",
    "编号": "GR202421200971"
  },
  {
    "名称": "大连经济技术开发区雄鹏物流设备有限公司",
    "编号": "GR202421200972"
  },
  {
    "名称": "大连云建数科科技有限公司",
    "编号": "GR202421200973"
  },
  {
    "名称": "大连乐成机器人科技有限公司",
    "编号": "GR202421200974"
  },
  {
    "名称": "中车大连机车车辆有限公司",
    "编号": "GR202421200975"
  },
  {
    "名称": "大连新汇电力科技有限公司",
    "编号": "GR202421200976"
  },
  {
    "名称": "大连隆欣机械有限公司",
    "编号": "GR202421200977"
  },
  {
    "名称": "大连冰山嘉德自动化有限公司",
    "编号": "GR202421200978"
  },
  {
    "名称": "捷丰凯瑞物流科技（大连）有限公司",
    "编号": "GR202421200979"
  },
  {
    "名称": "大连太平防水工程有限公司",
    "编号": "GR202421200980"
  },
  {
    "名称": "大连劳雷石油化工泵制造有限公司",
    "编号": "GR202421200981"
  },
  {
    "名称": "大连恺昌环境工程有限公司",
    "编号": "GR202421200982"
  },
  {
    "名称": "大连智能创新产业中心有限公司",
    "编号": "GR202421200983"
  },
  {
    "名称": "卫达建设集团有限公司",
    "编号": "GR202421200984"
  },
  {
    "名称": "大连星航起重吊具有限公司",
    "编号": "GR202421200985"
  },
  {
    "名称": "大连铭良食品有限公司",
    "编号": "GR202421200986"
  },
  {
    "名称": "一汽解放大连柴油机有限公司",
    "编号": "GR202421200987"
  },
  {
    "名称": "大连海诺克自动化技术有限公司",
    "编号": "GR202421200988"
  },
  {
    "名称": "锦祥照明系统（大连）有限公司",
    "编号": "GR202421200989"
  },
  {
    "名称": "博驰冷冻机（大连）有限公司",
    "编号": "GR202421200990"
  },
  {
    "名称": "大连汪洋环境工程有限公司",
    "编号": "GR202421200991"
  },
  {
    "名称": "大连源庆电器设备制造有限公司",
    "编号": "GR202421200992"
  },
  {
    "名称": "大连富谷食品有限公司",
    "编号": "GR202421200993"
  },
  {
    "名称": "大连嘉禾通用设备研造有限公司",
    "编号": "GR202421200994"
  },
  {
    "名称": "大连源丰智能科技有限公司",
    "编号": "GR202421200995"
  },
  {
    "名称": "睿联医疗科技(大连)有限公司",
    "编号": "GR202421200996"
  },
  {
    "名称": "大连崎迈机械制造有限公司",
    "编号": "GR202421200997"
  },
  {
    "名称": "大连恒等式信息技术有限公司",
    "编号": "GR202421200998"
  },
  {
    "名称": "冰山松洋冷链（大连）股份有限公司",
    "编号": "GR202421200999"
  },
  {
    "名称": "中科能源材料科技（大连）有限公司",
    "编号": "GR202421201000"
  },
  {
    "名称": "大连科瑞气体有限公司",
    "编号": "GR202421201001"
  },
  {
    "名称": "大连星翼信息技术有限公司",
    "编号": "GR202421201002"
  },
  {
    "名称": "大连鑫普之星节能科技有限公司",
    "编号": "GR202421201003"
  },
  {
    "名称": "大连冶金轴承股份有限公司",
    "编号": "GR202421201004"
  },
  {
    "名称": "大连岩丸机械工业有限公司",
    "编号": "GR202421201005"
  },
  {
    "名称": "大连九八五科技有限公司",
    "编号": "GR202421201006"
  },
  {
    "名称": "大连玉帷软件科技有限公司",
    "编号": "GR202421201007"
  },
  {
    "名称": "大连建锐科技有限公司",
    "编号": "GR202421201008"
  },
  {
    "名称": "大连美工智能科技有限公司",
    "编号": "GR202421201009"
  },
  {
    "名称": "大连爱得科技有限公司",
    "编号": "GR202421201010"
  },
  {
    "名称": "大连永信同心科技有限公司",
    "编号": "GR202421201011"
  },
  {
    "名称": "大连嘉思科技有限公司",
    "编号": "GR202421201012"
  },
  {
    "名称": "信华信(大连)软件服务股份有限公司",
    "编号": "GR202421201013"
  },
  {
    "名称": "钧天世纪（大连）文化科技有限公司",
    "编号": "GR202421201014"
  },
  {
    "名称": "大连致能装备有限公司",
    "编号": "GR202421201015"
  },
  {
    "名称": "大连益丰物流科技有限公司",
    "编号": "GR202421201016"
  },
  {
    "名称": "大连祥云科技有限公司",
    "编号": "GR202421201017"
  },
  {
    "名称": "大连之声文化产业集团有限公司",
    "编号": "GR202421201018"
  },
  {
    "名称": "大连金车工业有限责任公司",
    "编号": "GR202421201019"
  },
  {
    "名称": "大连佰亿联信息科技有限公司",
    "编号": "GR202421201020"
  },
  {
    "名称": "大连夫诸智能信息科技有限公司",
    "编号": "GR202421201021"
  },
  {
    "名称": "大连顺天兴达特种阀门有限公司",
    "编号": "GR202421201022"
  },
  {
    "名称": "爱伯特教育科技(辽宁)有限公司",
    "编号": "GR202421201023"
  },
  {
    "名称": "大连富洁森环保科技有限公司",
    "编号": "GR202421201024"
  },
  {
    "名称": "大连德文文化科技有限公司",
    "编号": "GR202421201025"
  },
  {
    "名称": "大连易力达环境工程有限公司",
    "编号": "GR202421201026"
  },
  {
    "名称": "奥卡威科技（大连）有限公司",
    "编号": "GR202421201027"
  },
  {
    "名称": "大连泽运科技有限公司",
    "编号": "GR202421201028"
  },
  {
    "名称": "德尔迅技术（大连）有限公司",
    "编号": "GR202421201029"
  },
  {
    "名称": "大连林桥木业有限公司",
    "编号": "GR202421201030"
  },
  {
    "名称": "大连经济技术开发区信诚纸制品有限公司",
    "编号": "GR202421201031"
  },
  {
    "名称": "精心电气自动化设备（大连）有限公司",
    "编号": "GR202421201032"
  },
  {
    "名称": "大连前程钢管制造有限公司",
    "编号": "GR202421201033"
  },
  {
    "名称": "大连研林工业有限公司",
    "编号": "GR202421201034"
  },
  {
    "名称": "大连长顺机电科技有限公司",
    "编号": "GR202421201035"
  },
  {
    "名称": "大连亿旺机械模具有限公司",
    "编号": "GR202421201036"
  },
  {
    "名称": "觅视科技（大连）有限公司",
    "编号": "GR202421201037"
  },
  {
    "名称": "大连日恒机械有限公司",
    "编号": "GR202421201038"
  },
  {
    "名称": "大连大信热处理有限公司",
    "编号": "GR202421201039"
  },
  {
    "名称": "大连合力信软件有限公司",
    "编号": "GR202421201040"
  },
  {
    "名称": "大连网月科技股份有限公司",
    "编号": "GR202421201041"
  },
  {
    "名称": "大连全顿检疫消杀技术服务有限责任公司",
    "编号": "GR202421201042"
  },
  {
    "名称": "瓦房店金冠达轴承制造有限公司",
    "编号": "GR202421201043"
  },
  {
    "名称": "氧筋堂(辽宁)健康产业发展有限公司",
    "编号": "GR202421201044"
  },
  {
    "名称": "中科糠醛（辽宁）技术服务中心有限公司",
    "编号": "GR202421201045"
  },
  {
    "名称": "优尼恩电机（大连）有限公司",
    "编号": "GR202421201046"
  },
  {
    "名称": "大连源辉汽车零部件有限公司",
    "编号": "GR202421201047"
  },
  {
    "名称": "大连丹珂服饰有限公司",
    "编号": "GR202421201048"
  },
  {
    "名称": "大连中智精工科技有限责任公司",
    "编号": "GR202421201049"
  },
  {
    "名称": "大连多团软件科技有限公司",
    "编号": "GR202421201050"
  },
  {
    "名称": "大连诚宇软件科技有限公司",
    "编号": "GR202421201051"
  },
  {
    "名称": "大连联羽阁科技有限公司",
    "编号": "GR202421201052"
  },
  {
    "名称": "大连宝锋机器制造有限公司",
    "编号": "GR202421201053"
  },
  {
    "名称": "云米启明(大连)智能光电有限公司",
    "编号": "GR202421201054"
  },
  {
    "名称": "大连汤亚科技有限公司",
    "编号": "GR202421201055"
  },
  {
    "名称": "大连群英同享科技有限公司",
    "编号": "GR202421201056"
  },
  {
    "名称": "大连景萍车晓科技有限公司",
    "编号": "GR202421201057"
  },
  {
    "名称": "中科帆凯(大连)新材料有限公司",
    "编号": "GR202421201058"
  },
  {
    "名称": "大连沃奇尔科技发展有限公司",
    "编号": "GR202421201059"
  },
  {
    "名称": "辽宁路易华泰能源有限公司",
    "编号": "GR202421201060"
  },
  {
    "名称": "大连博远罐头食品有限公司",
    "编号": "GR202421201061"
  },
  {
    "名称": "大连忆科峰晨科技有限公司",
    "编号": "GR202421201062"
  },
  {
    "名称": "大连星梦世纪物联网信息技术有限公司",
    "编号": "GR202421201063"
  },
  {
    "名称": "大连远东特种钢有限公司",
    "编号": "GR202421201064"
  },
  {
    "名称": "大连市建筑工程质量检测中心有限公司",
    "编号": "GR202421201065"
  },
  {
    "名称": "大连恒川汽车零部件有限公司",
    "编号": "GR202421201066"
  },
  {
    "名称": "大连乾豪动漫有限公司",
    "编号": "GR202421201067"
  },
  {
    "名称": "大连智捷优创网络科技有限公司",
    "编号": "GR202421201068"
  },
  {
    "名称": "大连维远智能科技有限公司",
    "编号": "GR202421201069"
  },
  {
    "名称": "大连华威机器有限公司",
    "编号": "GR202421201070"
  },
  {
    "名称": "传朗工业(大连)有限公司",
    "编号": "GR202421201071"
  },
  {
    "名称": "大连弗贝科技有限公司",
    "编号": "GR202421201072"
  },
  {
    "名称": "大连川旭工艺品有限公司",
    "编号": "GR202421201073"
  },
  {
    "名称": "大连通达矿冶机械有限公司",
    "编号": "GR202421201074"
  },
  {
    "名称": "大连佳鑫金属制品有限公司",
    "编号": "GR202421201075"
  },
  {
    "名称": "大连汇鸿盛科技有限公司",
    "编号": "GR202421201076"
  },
  {
    "名称": "大连元梁冶金设备有限公司",
    "编号": "GR202421201077"
  },
  {
    "名称": "大连吉瑞刀具技术股份有限公司",
    "编号": "GR202421201078"
  },
  {
    "名称": "全博（大连）教育咨询有限公司",
    "编号": "GR202421201079"
  },
  {
    "名称": "大连中韵文化科技有限公司",
    "编号": "GR202421201080"
  },
  {
    "名称": "大连通晓科技发展有限公司",
    "编号": "GR202421201081"
  },
  {
    "名称": "大连施奈莱克创新汽车零部件有限公司",
    "编号": "GR202421201082"
  },
  {
    "名称": "大连市思奇木业有限公司",
    "编号": "GR202421201083"
  },
  {
    "名称": "大连四达高技术发展有限公司",
    "编号": "GR202421201084"
  },
  {
    "名称": "通用技术集团大连机床有限责任公司",
    "编号": "GR202421201085"
  },
  {
    "名称": "携创创新科技(大连)有限公司",
    "编号": "GR202421201086"
  },
  {
    "名称": "金铠仪器（大连）股份有限公司",
    "编号": "GR202421201087"
  },
  {
    "名称": "大连开物承作精密制造有限公司",
    "编号": "GR202421201088"
  },
  {
    "名称": "大连星辉电控设备有限公司",
    "编号": "GR202421201089"
  },
  {
    "名称": "辽宁睿航新能源有限公司",
    "编号": "GR202421201090"
  },
  {
    "名称": "大连盛青科技有限公司",
    "编号": "GR202421201091"
  },
  {
    "名称": "蓝渤湾海洋食品(大连)有限公司",
    "编号": "GR202421201092"
  },
  {
    "名称": "大连佳百兆科技有限公司",
    "编号": "GR202421201093"
  },
  {
    "名称": "大连和研智能装备有限公司",
    "编号": "GR202421201094"
  },
  {
    "名称": "大连海尔电冰箱有限公司",
    "编号": "GR202421201095"
  },
  {
    "名称": "大连昊凯网络科技有限公司",
    "编号": "GR202421201096"
  },
  {
    "名称": "大连东友信息技术有限公司",
    "编号": "GR202421201097"
  },
  {
    "名称": "大连纳源机械有限公司",
    "编号": "GR202421201098"
  },
  {
    "名称": "大连世凡网络科技有限公司",
    "编号": "GR202421201099"
  },
  {
    "名称": "大连畅泰船用推进器有限公司",
    "编号": "GR202421201100"
  },
  {
    "名称": "辽宁众亿会议会展服务有限公司",
    "编号": "GR202421201101"
  },
  {
    "名称": "大连山一环保设备有限公司",
    "编号": "GR202421201102"
  },
  {
    "名称": "大连辉达科技有限公司",
    "编号": "GR202421201103"
  },
  {
    "名称": "大连金华录数码科技有限公司",
    "编号": "GR202421201104"
  },
  {
    "名称": "连拓汽车技术(大连)有限公司",
    "编号": "GR202421201105"
  },
  {
    "名称": "大连中发互感器有限公司",
    "编号": "GR202421201106"
  },
  {
    "名称": "大连华开网络有限公司",
    "编号": "GR202421201107"
  },
  {
    "名称": "大连红顺电控设备制造有限公司",
    "编号": "GR202421201108"
  },
  {
    "名称": "大连杰伍科技有限公司",
    "编号": "GR202421201109"
  },
  {
    "名称": "大连三利塑料制品有限公司",
    "编号": "GR202421201110"
  },
  {
    "名称": "大连恒友精密机械有限公司",
    "编号": "GR202421201111"
  },
  {
    "名称": "大连辽南船厂",
    "编号": "GR202421201112"
  },
  {
    "名称": "大连五八八中控信息技术有限公司",
    "编号": "GR202421201113"
  },
  {
    "名称": "大连火星自动化工程技术有限公司",
    "编号": "GR202421201114"
  },
  {
    "名称": "大连壹致科技有限公司",
    "编号": "GR202421201115"
  },
  {
    "名称": "大连戴睿信息科技有限公司",
    "编号": "GR202421201116"
  },
  {
    "名称": "大连凤翔机械有限公司",
    "编号": "GR202421201117"
  },
  {
    "名称": "大连三木环保科技有限公司",
    "编号": "GR202421201118"
  },
  {
    "名称": "大连新桥塑料制品有限公司",
    "编号": "GR202421201119"
  },
  {
    "名称": "辽宁美意高环境工程有限公司",
    "编号": "GR202421201120"
  },
  {
    "名称": "大连林祥包装有限公司",
    "编号": "GR202421201121"
  },
  {
    "名称": "海恒（大连）科技有限公司",
    "编号": "GR202421201122"
  },
  {
    "名称": "大连盖得到科技有限公司",
    "编号": "GR202421201123"
  },
  {
    "名称": "大连九州联云科技有限公司",
    "编号": "GR202421201124"
  },
  {
    "名称": "大连佳塬科技发展有限公司",
    "编号": "GR202421201125"
  },
  {
    "名称": "大连壮元海生态苗业股份有限公司",
    "编号": "GR202421201126"
  },
  {
    "名称": "大连恒晖工业有限公司",
    "编号": "GR202421201127"
  },
  {
    "名称": "华百特科技(大连)有限公司",
    "编号": "GR202421201128"
  },
  {
    "名称": "大连融智互动科技有限公司",
    "编号": "GR202421201129"
  },
  {
    "名称": "大连环盾防雷科技有限公司",
    "编号": "GR202421201130"
  },
  {
    "名称": "大连兴辉化工有限公司",
    "编号": "GR202421201131"
  },
  {
    "名称": "中金时代(辽宁)新能源有限公司",
    "编号": "GR202421201132"
  },
  {
    "名称": "大连君诺汽车零部件有限公司",
    "编号": "GR202421201133"
  },
  {
    "名称": "光拓智能科技(大连)有限公司",
    "编号": "GR202421201134"
  },
  {
    "名称": "金榜出品科技(大连)有限公司",
    "编号": "GR202421201135"
  },
  {
    "名称": "众鑫和生态环境科技(大连)集团有限公司",
    "编号": "GR202421201136"
  },
  {
    "名称": "大连优晶芯维科技有限公司",
    "编号": "GR202421201137"
  },
  {
    "名称": "大连忠信圆通金属科技有限公司",
    "编号": "GR202421201138"
  },
  {
    "名称": "辽宁卓肯项目管理有限公司",
    "编号": "GR202421201139"
  },
  {
    "名称": "大连钜智信息科技有限公司",
    "编号": "GR202421201140"
  },
  {
    "名称": "大连万方船舶技术有限公司",
    "编号": "GR202421201141"
  },
  {
    "名称": "大连众达昇科技服务有限公司",
    "编号": "GR202421201142"
  },
  {
    "名称": "小野(大连)科技有限公司",
    "编号": "GR202421201143"
  },
  {
    "名称": "瓦房店永兴爆破工程有限公司",
    "编号": "GR202421201144"
  },
  {
    "名称": "中触媒新材料股份有限公司",
    "编号": "GR202421201145"
  },
  {
    "名称": "大连金盛永源玻璃股份有限公司",
    "编号": "GR202421201146"
  },
  {
    "名称": "玮业生态环境工程(大连)集团有限公司",
    "编号": "GR202421201147"
  },
  {
    "名称": "泰沃尔科技(大连)有限公司",
    "编号": "GR202421201148"
  },
  {
    "名称": "大连翔羽真空技术有限公司",
    "编号": "GR202421201149"
  },
  {
    "名称": "大连软东中昊科技有限公司",
    "编号": "GR202421201150"
  },
  {
    "名称": "大连瑞谷科技有限公司",
    "编号": "GR202421201151"
  },
  {
    "名称": "大连广顺源发计算机科技有限公司",
    "编号": "GR202421201152"
  },
  {
    "名称": "大连蓝赛斯无纺布制品有限公司",
    "编号": "GR202421201153"
  },
  {
    "名称": "大连新瑞晨自动化科技有限公司",
    "编号": "GR202421201154"
  },
  {
    "名称": "大连昌林科技有限公司",
    "编号": "GR202421201155"
  },
  {
    "名称": "大连神通模具有限公司",
    "编号": "GR202421201156"
  },
  {
    "名称": "大连安进食品有限公司",
    "编号": "GR202421201157"
  },
  {
    "名称": "大连国豪精密制造有限公司",
    "编号": "GR202421201158"
  },
  {
    "名称": "大连生雨科技开发有限公司",
    "编号": "GR202421201159"
  },
  {
    "名称": "大连振江海绵有限公司",
    "编号": "GR202421201160"
  },
  {
    "名称": "大连五洲公路工程有限公司",
    "编号": "GR202421201161"
  },
  {
    "名称": "杰西圈（大连）科技有限公司",
    "编号": "GR202421201162"
  },
  {
    "名称": "大连东锐软件有限公司",
    "编号": "GR202421201163"
  },
  {
    "名称": "大连沃克财税管理有限公司",
    "编号": "GR202421201164"
  },
  {
    "名称": "大连嘉龙国际贸易有限公司",
    "编号": "GR202421201165"
  },
  {
    "名称": "大连厚宇科技有限公司",
    "编号": "GR202421201166"
  },
  {
    "名称": "大连达硕信息技术有限公司",
    "编号": "GR202421201167"
  },
  {
    "名称": "大连立纫机械制造有限公司",
    "编号": "GR202421201168"
  },
  {
    "名称": "大连旋科空调压缩机有限公司",
    "编号": "GR202421201169"
  },
  {
    "名称": "大连汇力宝新材料科技有限公司",
    "编号": "GR202421201170"
  },
  {
    "名称": "大连鸿圆精密模塑有限公司",
    "编号": "GR202421201171"
  },
  {
    "名称": "豫九通风设备（大连）有限公司",
    "编号": "GR202421201172"
  },
  {
    "名称": "琸信科技(大连)有限公司",
    "编号": "GR202421201173"
  },
  {
    "名称": "韩精野村(大连)精密机械有限公司",
    "编号": "GR202421201174"
  },
  {
    "名称": "大连市荣鑫包装材料有限公司",
    "编号": "GR202421201175"
  },
  {
    "名称": "大连雪梅自动化设备有限公司",
    "编号": "GR202421201176"
  },
  {
    "名称": "大连圣锋物联科技股份有限公司",
    "编号": "GR202421201177"
  },
  {
    "名称": "共同食品（大连）有限公司",
    "编号": "GR202421201178"
  },
  {
    "名称": "辽宁特普工业有限公司",
    "编号": "GR202421201179"
  },
  {
    "名称": "诚晟软件科技发展（大连）有限公司",
    "编号": "GR202421201180"
  },
  {
    "名称": "大连尚耘机械制造有限公司",
    "编号": "GR202421201181"
  },
  {
    "名称": "大连华达文化传媒有限公司",
    "编号": "GR202421201182"
  },
  {
    "名称": "大连冠维科技有限公司",
    "编号": "GR202421201183"
  },
  {
    "名称": "大连隆盛顺达仪表有限公司",
    "编号": "GR202421201184"
  },
  {
    "名称": "大连赛潽朗科环保科技有限公司",
    "编号": "GR202421201185"
  },
  {
    "名称": "大连华控工业装备有限公司",
    "编号": "GR202421201186"
  },
  {
    "名称": "米源联合科技(大连)有限公司",
    "编号": "GR202421201187"
  },
  {
    "名称": "大连新锐智能光电有限公司",
    "编号": "GR202421201188"
  },
  {
    "名称": "大连泳泉安全玻璃有限公司",
    "编号": "GR202421201189"
  },
  {
    "名称": "大连鸿升机械有限公司",
    "编号": "GR202421201190"
  },
  {
    "名称": "大连百超激光精密钣金加工有限公司",
    "编号": "GR202421201191"
  },
  {
    "名称": "大连浩辰科技有限公司",
    "编号": "GR202421201192"
  },
  {
    "名称": "大连戬谷网络科技有限公司",
    "编号": "GR202421201193"
  },
  {
    "名称": "大连七彩科技有限公司",
    "编号": "GR202421201194"
  },
  {
    "名称": "大连恒益精密部件有限公司",
    "编号": "GR202421201195"
  },
  {
    "名称": "大连圣浡尔电机有限公司",
    "编号": "GR202421201196"
  },
  {
    "名称": "大连睦舟新研科技有限公司",
    "编号": "GR202421201197"
  },
  {
    "名称": "大连精派计算机科技有限公司",
    "编号": "GR202421201198"
  },
  {
    "名称": "久鼎三利建工集团有限公司",
    "编号": "GR202421201199"
  },
  {
    "名称": "企铭星(大连)科技服务有限公司",
    "编号": "GR202421201200"
  },
  {
    "名称": "大连千玺网络科技有限公司",
    "编号": "GR202421201201"
  },
  {
    "名称": "华研风电设备制造（大连）有限公司",
    "编号": "GR202421201202"
  },
  {
    "名称": "大连明德节能环保工程技术有限公司",
    "编号": "GR202421201203"
  },
  {
    "名称": "大连卓威工业有限公司",
    "编号": "GR202421201204"
  },
  {
    "名称": "大连杰铭科技有限责任公司",
    "编号": "GR202421201205"
  },
  {
    "名称": "大连连昇新材料有限公司",
    "编号": "GR202421201206"
  },
  {
    "名称": "信创科技（大连）有限公司",
    "编号": "GR202421201207"
  },
  {
    "名称": "大连东泰有机废物处理有限公司",
    "编号": "GR202421201208"
  },
  {
    "名称": "兴辉（大连）新材料有限公司",
    "编号": "GR202421201209"
  },
  {
    "名称": "大连罗安科技有限公司",
    "编号": "GR202421201210"
  },
  {
    "名称": "环邦检验检测有限责任公司",
    "编号": "GR202421201211"
  },
  {
    "名称": "大连快牌润滑油有限公司",
    "编号": "GR202421201212"
  },
  {
    "名称": "辽宁九州网络建设集团有限公司",
    "编号": "GR202421201213"
  },
  {
    "名称": "大连龙岩精密滚动体有限责任公司",
    "编号": "GR202421201214"
  },
  {
    "名称": "大连柏川精密机械有限公司",
    "编号": "GR202421201215"
  },
  {
    "名称": "大连启锋信息科技有限公司",
    "编号": "GR202421201216"
  },
  {
    "名称": "大连鑫洁机械设备有限公司",
    "编号": "GR202421201217"
  },
  {
    "名称": "大连伟业华泰冶金设备有限公司",
    "编号": "GR202421201218"
  },
  {
    "名称": "大连三协精密模具有限公司",
    "编号": "GR202421201219"
  },
  {
    "名称": "大连泽宇钢结构工程有限公司",
    "编号": "GR202421201220"
  },
  {
    "名称": "大连鑫普新能源技术有限公司",
    "编号": "GR202421201221"
  },
  {
    "名称": "中宝通信设备制造(大连)有限公司",
    "编号": "GR202421201222"
  },
  {
    "名称": "知蜻（大连）科技有限公司",
    "编号": "GR202421201223"
  },
  {
    "名称": "大连立寻咨询服务有限公司",
    "编号": "GR202421201224"
  },
  {
    "名称": "大连大河教育科技有限公司",
    "编号": "GR202421201225"
  },
  {
    "名称": "大连双高企业管理有限公司",
    "编号": "GR202421201226"
  },
  {
    "名称": "大连悦慈科技有限公司",
    "编号": "GR202421201227"
  },
  {
    "名称": "大连华茂科技有限公司",
    "编号": "GR202421201228"
  },
  {
    "名称": "大连捷汇达环境科技有限公司",
    "编号": "GR202421201229"
  },
  {
    "名称": "大连威亚特金属有限公司",
    "编号": "GR202421201230"
  },
  {
    "名称": "大连圣杰机械制造有限公司",
    "编号": "GR202421201231"
  },
  {
    "名称": "大连艺起雕塑工程有限公司",
    "编号": "GR202421201232"
  },
  {
    "名称": "大连聚兴科技有限公司",
    "编号": "GR202421201233"
  },
  {
    "名称": "大连威戈工业有限公司",
    "编号": "GR202421201234"
  },
  {
    "名称": "大连恒恩环保科技有限公司",
    "编号": "GR202421201235"
  },
  {
    "名称": "大连船舶重工集团有限公司",
    "编号": "GR202421201236"
  },
  {
    "名称": "辽宁信达志成高科技有限公司",
    "编号": "GR202421201237"
  },
  {
    "名称": "大连极善食品科技有限公司",
    "编号": "GR202421201238"
  },
  {
    "名称": "大连隆源达通信工程有限公司",
    "编号": "GR202421201239"
  },
  {
    "名称": "大连鸿润机车配件有限公司",
    "编号": "GR202421201240"
  },
  {
    "名称": "澳马教育科技（大连）有限公司",
    "编号": "GR202421201241"
  },
  {
    "名称": "华录云涛科技（大连）有限公司",
    "编号": "GR202421201242"
  },
  {
    "名称": "大连市金州腾达金属构件有限公司",
    "编号": "GR202421201243"
  },
  {
    "名称": "天颐科技(大连)有限公司",
    "编号": "GR202421201244"
  },
  {
    "名称": "大连世凡机械有限公司",
    "编号": "GR202421201245"
  },
  {
    "名称": "大连天晞科技有限公司",
    "编号": "GR202421201246"
  },
  {
    "名称": "大连锦立德新材料科技有限公司",
    "编号": "GR202421201247"
  },
  {
    "名称": "大连英奇科技发展有限公司",
    "编号": "GR202421201248"
  },
  {
    "名称": "大连星耀机械有限公司",
    "编号": "GR202421201249"
  },
  {
    "名称": "汉高科技（大连）有限公司",
    "编号": "GR202421201250"
  },
  {
    "名称": "大连暠霸旅行车制造有限公司",
    "编号": "GR202421201251"
  },
  {
    "名称": "大连宇琦科技有限公司",
    "编号": "GR202421201252"
  },
  {
    "名称": "大连美天三有电子仪表有限公司",
    "编号": "GR202421201253"
  },
  {
    "名称": "大连天和泵业有限公司",
    "编号": "GR202421201254"
  },
  {
    "名称": "大连诺阳模塑有限公司",
    "编号": "GR202421201255"
  },
  {
    "名称": "大连仁邦农业科技集团有限公司",
    "编号": "GR202421201256"
  },
  {
    "名称": "大连融科储能装备有限公司",
    "编号": "GR202421201257"
  },
  {
    "名称": "精锐科技(大连)有限公司",
    "编号": "GR202421201258"
  },
  {
    "名称": "大连金泽安全环境科技有限公司",
    "编号": "GR202421201259"
  },
  {
    "名称": "大连初辰晨曦科技有限公司",
    "编号": "GR202421201260"
  },
  {
    "名称": "大连吴歌影视文化科技有限公司",
    "编号": "GR202421201261"
  },
  {
    "名称": "大连易卡安全防护系统有限公司",
    "编号": "GR202421201262"
  },
  {
    "名称": "信华信（大连）数字技术有限公司",
    "编号": "GR202421201263"
  },
  {
    "名称": "大连宝祥包装制品有限公司",
    "编号": "GR202421201264"
  },
  {
    "名称": "大连一娃科技有限公司",
    "编号": "GR202421201265"
  },
  {
    "名称": "大连傲盈科技有限公司",
    "编号": "GR202421201266"
  },
  {
    "名称": "大连彼姆科技有限公司",
    "编号": "GR202421201267"
  },
  {
    "名称": "大连建维材料科技有限公司",
    "编号": "GR202421201268"
  },
  {
    "名称": "伊博电子科技(大连)有限公司",
    "编号": "GR202421201269"
  },
  {
    "名称": "合际(大连)建筑工程有限公司",
    "编号": "GR202421201270"
  },
  {
    "名称": "大连宇奥机械设备制造有限公司",
    "编号": "GR202421201271"
  },
  {
    "名称": "大连滨海砂轮有限公司",
    "编号": "GR202421201272"
  },
  {
    "名称": "大连鸿之发机械制造有限公司",
    "编号": "GR202421201273"
  },
  {
    "名称": "华夏天信传感科技（大连）有限公司",
    "编号": "GR202421201274"
  },
  {
    "名称": "鑫能达智能装备(大连)有限公司",
    "编号": "GR202421201275"
  },
  {
    "名称": "大连恒达通通信技术有限公司",
    "编号": "GR202421201276"
  },
  {
    "名称": "大连宝晶艺术装饰工程有限公司",
    "编号": "GR202421201277"
  },
  {
    "名称": "合禾模具(大连)有限公司",
    "编号": "GR202421201278"
  },
  {
    "名称": "大连荣昊科技有限公司",
    "编号": "GR202421201279"
  },
  {
    "名称": "大连宝信起重技术有限公司",
    "编号": "GR202421201280"
  },
  {
    "名称": "大连万方动力技术有限公司",
    "编号": "GR202421201281"
  },
  {
    "名称": "大连相泽科技有限公司",
    "编号": "GR202421201282"
  },
  {
    "名称": "大连理工大学出版社有限公司",
    "编号": "GR202421201283"
  },
  {
    "名称": "大连方伟机械制造有限公司",
    "编号": "GR202421201284"
  },
  {
    "名称": "大连正源精密部件有限公司",
    "编号": "GR202421201285"
  },
  {
    "名称": "大连市鼎熙新能源设备技术有限公司",
    "编号": "GR202421201286"
  },
  {
    "名称": "大连骏铭船舶起重机械有限公司",
    "编号": "GR202421201287"
  },
  {
    "名称": "大连诺豪联恒电子科技有限公司",
    "编号": "GR202421201288"
  },
  {
    "名称": "大连通惠工业设备有限公司",
    "编号": "GR202421201289"
  },
  {
    "名称": "大连现代高技术集团有限公司",
    "编号": "GR202421201290"
  },
  {
    "名称": "大连鑫雨轴承有限公司",
    "编号": "GR202421201291"
  },
  {
    "名称": "大连金云创通科技有限公司",
    "编号": "GR202421201292"
  },
  {
    "名称": "约翰哈特科技（大连）有限公司",
    "编号": "GR202421201293"
  },
  {
    "名称": "东北特钢集团大连特殊钢制品有限公司",
    "编号": "GR202421201294"
  },
  {
    "名称": "大连森利科技有限公司",
    "编号": "GR202421201295"
  },
  {
    "名称": "大连龙图信息技术股份有限公司",
    "编号": "GR202421201296"
  },
  {
    "名称": "大连合创设计有限公司",
    "编号": "GR202421201297"
  },
  {
    "名称": "大连博晟鑫文化科技有限公司",
    "编号": "GR202421201298"
  },
  {
    "名称": "大连创新零部件制造公司",
    "编号": "GR202421201299"
  },
  {
    "名称": "大连盈科模塑有限公司",
    "编号": "GR202421201300"
  },
  {
    "名称": "大连威科特锐研磨有限公司",
    "编号": "GR202421201301"
  },
  {
    "名称": "大连霞发科技有限公司",
    "编号": "GR202421201302"
  },
  {
    "名称": "大连砺剑防务科技有限公司",
    "编号": "GR202421201303"
  },
  {
    "名称": "大连创明机械有限公司",
    "编号": "GR202421201304"
  },
  {
    "名称": "大连竹华科技有限公司",
    "编号": "GR202421201305"
  },
  {
    "名称": "大连皓悦信息技术有限公司",
    "编号": "GR202421201306"
  },
  {
    "名称": "视美尔（大连）生物科技有限公司",
    "编号": "GR202421201307"
  },
  {
    "名称": "数智汇能(大连)科技发展有限公司",
    "编号": "GR202421201308"
  },
  {
    "名称": "大连市自来水集团水表有限公司",
    "编号": "GR202421201309"
  },
  {
    "名称": "大连天极科技有限公司",
    "编号": "GR202421201310"
  },
  {
    "名称": "大连金钰诚新能源有限公司",
    "编号": "GR202421201311"
  },
  {
    "名称": "大连智崇科技有限公司",
    "编号": "GR202421201312"
  },
  {
    "名称": "大连亮涵特殊钢有限公司",
    "编号": "GR202421201313"
  },
  {
    "名称": "大连环控技术有限公司",
    "编号": "GR202421201314"
  },
  {
    "名称": "栈程(大连)科技有限公司",
    "编号": "GR202421201315"
  },
  {
    "名称": "大连德恒商务信息服务有限公司",
    "编号": "GR202421201316"
  },
  {
    "名称": "大连翰歆科技有限公司",
    "编号": "GR202421201317"
  },
  {
    "名称": "大连汉意精工有限公司",
    "编号": "GR202421201318"
  },
  {
    "名称": "铭润(大连)油脂有限公司",
    "编号": "GR202421201319"
  },
  {
    "名称": "普仕达医疗服务(大连)有限公司",
    "编号": "GR202421201320"
  },
  {
    "名称": "大连华锐重工集团股份有限公司",
    "编号": "GR202421201321"
  },
  {
    "名称": "大连智通信息技术有限公司",
    "编号": "GR202421201322"
  },
  {
    "名称": "大连中天项目管理有限公司",
    "编号": "GR202421201323"
  },
  {
    "名称": "诚晟企业管理服务(大连)有限公司",
    "编号": "GR202421201324"
  },
  {
    "名称": "大连新众智能装备有限公司",
    "编号": "GR202421201325"
  },
  {
    "名称": "长川制靴（大连）有限公司",
    "编号": "GR202421201326"
  },
  {
    "名称": "大连梓安网络科技有限公司",
    "编号": "GR202421201327"
  },
  {
    "名称": "大连德朗水务有限公司",
    "编号": "GR202421201328"
  },
  {
    "名称": "大连智云科技有限公司",
    "编号": "GR202421201329"
  },
  {
    "名称": "桑原电机(大连)有限公司",
    "编号": "GR202421201330"
  },
  {
    "名称": "大连益鹏泵业配件有限公司",
    "编号": "GR202421201331"
  },
  {
    "名称": "大连辽南计量检测院有限公司",
    "编号": "GR202421201332"
  },
  {
    "名称": "辽宁众联机电工程有限公司",
    "编号": "GR202421201333"
  },
  {
    "名称": "大连坤鹏文档技术服务有限公司",
    "编号": "GR202421201334"
  },
  {
    "名称": "大连中富友泰网络科技有限公司",
    "编号": "GR202421201335"
  },
  {
    "名称": "大连丰歌服装有限公司",
    "编号": "GR202421201336"
  },
  {
    "名称": "大连圣丰包装集团有限公司",
    "编号": "GR202421201337"
  },
  {
    "名称": "大连迪安缇科技有限公司",
    "编号": "GR202421201338"
  },
  {
    "名称": "大连岗冶锻造有限公司",
    "编号": "GR202421201339"
  },
  {
    "名称": "大连睿海信息科技有限公司",
    "编号": "GR202421201340"
  },
  {
    "名称": "大连海跃船舶装备有限公司",
    "编号": "GR202421201341"
  },
  {
    "名称": "大连安信泽科技有限公司",
    "编号": "GR202421201342"
  },
  {
    "名称": "大连海天兴业科技有限公司",
    "编号": "GR202421201343"
  },
  {
    "名称": "佰利鑫科技（大连）有限公司",
    "编号": "GR202421201344"
  },
  {
    "名称": "辽宁富鸿源实业集团有限公司",
    "编号": "GR202421201345"
  },
  {
    "名称": "大连盈迅轨道交通科技有限公司",
    "编号": "GR202421201346"
  },
  {
    "名称": "大连美宝文化传媒发展有限公司",
    "编号": "GR202421201347"
  },
  {
    "名称": "大连三厦智能科技装备有限公司",
    "编号": "GR202421201348"
  },
  {
    "名称": "屹联科技(大连)有限公司",
    "编号": "GR202421201349"
  },
  {
    "名称": "西门子传感器与通讯有限公司",
    "编号": "GR202421201350"
  },
  {
    "名称": "大连兴隆金属制造有限公司",
    "编号": "GR202421201351"
  },
  {
    "名称": "大连博源医学科技有限公司",
    "编号": "GR202421201352"
  },
  {
    "名称": "科威达工业（大连）有限公司",
    "编号": "GR202421201353"
  },
  {
    "名称": "兴泰食品(大连)有限公司",
    "编号": "GR202421201354"
  },
  {
    "名称": "大连市润环环保产业基地管理有限公司",
    "编号": "GR202421201355"
  },
  {
    "名称": "大连瓦机数控机床有限公司",
    "编号": "GR202421201356"
  },
  {
    "名称": "辽宁任方圆教育科技有限公司",
    "编号": "GR202421201357"
  },
  {
    "名称": "大连汇腾精工机械制造有限公司",
    "编号": "GR202421201358"
  },
  {
    "名称": "大连麦花食品集团有限公司",
    "编号": "GR202421201359"
  },
  {
    "名称": "大连方宸云海科技有限公司",
    "编号": "GR202421201360"
  },
  {
    "名称": "大连大锻锻造有限公司",
    "编号": "GR202421201361"
  },
  {
    "名称": "大连浩艺义齿有限公司",
    "编号": "GR202421201362"
  },
  {
    "名称": "大连鸿顺开信息技术有限公司",
    "编号": "GR202421201363"
  },
  {
    "名称": "大连万有君和通用设备制造有限公司",
    "编号": "GR202421201364"
  },
  {
    "名称": "众述行科技（大连）有限公司",
    "编号": "GR202421201365"
  },
  {
    "名称": "大连康拾科技有限公司",
    "编号": "GR202421201366"
  },
  {
    "名称": "大连勤德科技有限公司",
    "编号": "GR202421201367"
  },
  {
    "名称": "大连云观信息技术有限公司",
    "编号": "GR202421201368"
  },
  {
    "名称": "大连中瑞科技有限公司",
    "编号": "GR202421201369"
  },
  {
    "名称": "大连盛世营销策划有限公司",
    "编号": "GR202421201370"
  },
  {
    "名称": "和捷科技（辽宁）集团有限公司",
    "编号": "GR202421201371"
  },
  {
    "名称": "英之杰建设工程有限公司",
    "编号": "GR202421201372"
  },
  {
    "名称": "文思海辉元辉科技（大连）有限公司",
    "编号": "GR202421201373"
  },
  {
    "名称": "大连益驰思安全环境技术有限公司",
    "编号": "GR202421201374"
  },
  {
    "名称": "大连科华热力管道有限公司",
    "编号": "GR202421201375"
  },
  {
    "名称": "德昊通机电（大连）有限公司",
    "编号": "GR202421201376"
  },
  {
    "名称": "诠思科技（大连）有限公司",
    "编号": "GR202421201377"
  },
  {
    "名称": "汇辰科技（大连）有限公司",
    "编号": "GR202421201378"
  },
  {
    "名称": "大连同创君信科技发展有限公司",
    "编号": "GR202421201379"
  },
  {
    "名称": "大连中惠灌溉设备有限公司",
    "编号": "GR202421201380"
  },
  {
    "名称": "大连九云网络科技有限公司",
    "编号": "GR202421201381"
  },
  {
    "名称": "郡邑信息科技(大连)有限公司",
    "编号": "GR202421201382"
  },
  {
    "名称": "大连童乐汇科技有限公司",
    "编号": "GR202421201383"
  },
  {
    "名称": "大连晟艺焊接自动化设备有限公司",
    "编号": "GR202421201384"
  },
  {
    "名称": "大连泷锋精密智造有限公司",
    "编号": "GR202421201385"
  },
  {
    "名称": "大连良辉精密机械有限公司",
    "编号": "GR202421201386"
  },
  {
    "名称": "大连新华医疗设备有限公司",
    "编号": "GR202421201387"
  },
  {
    "名称": "大连橙客电子科技有限公司",
    "编号": "GR202421201388"
  },
  {
    "名称": "大连华齐泰精密仪器有限公司",
    "编号": "GR202421201389"
  },
  {
    "名称": "月露星(大连)科技有限公司",
    "编号": "GR202421201390"
  },
  {
    "名称": "大连奥艺科技有限公司",
    "编号": "GR202421201391"
  },
  {
    "名称": "大连博远技术发展有限公司",
    "编号": "GR202421201392"
  },
  {
    "名称": "大连淡宁实业发展有限公司",
    "编号": "GR202421201393"
  },
  {
    "名称": "博锋智能科技（大连）有限公司",
    "编号": "GR202421201394"
  },
  {
    "名称": "三田科技(大连)有限公司",
    "编号": "GR202421201395"
  },
  {
    "名称": "大连迦飞翔胶粘制品有限公司",
    "编号": "GR202421201396"
  },
  {
    "名称": "大连闻汇教育科技有限公司",
    "编号": "GR202421201397"
  },
  {
    "名称": "越勇（大连）科技有限公司",
    "编号": "GR202421201398"
  },
  {
    "名称": "大连禾雀网络科技有限公司",
    "编号": "GR202421201399"
  },
  {
    "名称": "超亿螺丝工业（大连）有限公司",
    "编号": "GR202421201400"
  },
  {
    "名称": "大连惠生泵业有限公司",
    "编号": "GR202421201401"
  },
  {
    "名称": "大连昊天广益机械设备制造有限公司",
    "编号": "GR202421201402"
  },
  {
    "名称": "大连日嘉低碳新能源科技有限公司",
    "编号": "GR202421201403"
  },
  {
    "名称": "大连蓝德科技有限公司",
    "编号": "GR202421201404"
  },
  {
    "名称": "大连圣薪设备有限公司",
    "编号": "GR202421201405"
  },
  {
    "名称": "大连联合高分子材料有限公司",
    "编号": "GR202421201406"
  },
  {
    "名称": "大连凯普乐液压设备有限公司",
    "编号": "GR202421201407"
  },
  {
    "名称": "云端志尚（大连）科技有限公司",
    "编号": "GR202421201408"
  },
  {
    "名称": "大连同飞金属制品有限公司",
    "编号": "GR202421201409"
  },
  {
    "名称": "遇见未来(大连)数字科技有限公司",
    "编号": "GR202421201410"
  },
  {
    "名称": "大连昌田服装科技有限公司",
    "编号": "GR202421201411"
  },
  {
    "名称": "大连联鑫机械有限公司",
    "编号": "GR202421201412"
  },
  {
    "名称": "大连宇都环境技术材料有限公司",
    "编号": "GR202421201413"
  },
  {
    "名称": "大连皆必喜机械有限公司",
    "编号": "GR202421201414"
  },
  {
    "名称": "阿安帝科技（大连）有限公司",
    "编号": "GR202421201415"
  },
  {
    "名称": "大连晟洋重工有限公司",
    "编号": "GR202421201416"
  },
  {
    "名称": "大连金豪空调技术有限公司",
    "编号": "GR202421201417"
  },
  {
    "名称": "大连仁宏冲压模具有限公司",
    "编号": "GR202421201418"
  },
  {
    "名称": "华光高科特种材料（大连）有限公司",
    "编号": "GR202421201419"
  },
  {
    "名称": "大连创升科技有限公司",
    "编号": "GR202421201420"
  },
  {
    "名称": "大连佰强电子科技有限公司",
    "编号": "GR202421201421"
  },
  {
    "名称": "大连市大数据运营有限公司",
    "编号": "GR202421201422"
  },
  {
    "名称": "海狸(大连)科技有限公司",
    "编号": "GR202421201423"
  },
  {
    "名称": "大连顺强泵业制造有限公司",
    "编号": "GR202421201424"
  },
  {
    "名称": "大连七方科技有限公司",
    "编号": "GR202421201425"
  },
  {
    "名称": "大连金恒工业有限公司",
    "编号": "GR202421201426"
  },
  {
    "名称": "大连华起科技有限公司",
    "编号": "GR202421201427"
  },
  {
    "名称": "大连锐齿龙磨具科技有限公司",
    "编号": "GR202421201428"
  },
  {
    "名称": "大连圣享智创科技有限公司",
    "编号": "GR202421201429"
  },
  {
    "名称": "大连普道安达特种设备安全技术服务有限公司",
    "编号": "GR202421201430"
  },
  {
    "名称": "大连惠英机械有限公司",
    "编号": "GR202421201431"
  },
  {
    "名称": "道生壹科技（大连）有限公司",
    "编号": "GR202421201432"
  },
  {
    "名称": "标点符号(大连)科技有限公司",
    "编号": "GR202421201433"
  },
  {
    "名称": "大连通科应用技术有限公司",
    "编号": "GR202421201434"
  },
  {
    "名称": "瓦房店硕原矿业有限公司",
    "编号": "GR202421201435"
  },
  {
    "名称": "大连喜报来科技有限公司",
    "编号": "GR202421201436"
  },
  {
    "名称": "大连双华永欣木业有限公司",
    "编号": "GR202421201437"
  },
  {
    "名称": "大连金华德精密轴有限公司",
    "编号": "GR202421201438"
  },
  {
    "名称": "澳瑞环保(大连)有限公司",
    "编号": "GR202421201439"
  },
  {
    "名称": "大连绿禾环保科技有限公司",
    "编号": "GR202421201440"
  },
  {
    "名称": "大连奥速仪表有限公司",
    "编号": "GR202421201441"
  },
  {
    "名称": "大连凯烽机械制造有限公司",
    "编号": "GR202421201442"
  },
  {
    "名称": "大连中联生态科技有限公司",
    "编号": "GR202421201443"
  },
  {
    "名称": "大连地拓精密科技股份有限公司",
    "编号": "GR202421201444"
  },
  {
    "名称": "大连成信科技有限公司",
    "编号": "GR202421201445"
  },
  {
    "名称": "大连美盛电通科技有限公司",
    "编号": "GR202421201446"
  },
  {
    "名称": "大连新重集团有限公司",
    "编号": "GR202421201447"
  },
  {
    "名称": "大连盛源工贸有限公司",
    "编号": "GR202421201448"
  },
  {
    "名称": "大连喜浩机械制造有限公司",
    "编号": "GR202421201449"
  },
  {
    "名称": "大连捷晟机械设备有限公司",
    "编号": "GR202421201450"
  },
  {
    "名称": "大连即时智能科技有限公司",
    "编号": "GR202421201451"
  },
  {
    "名称": "大连大功鸿嘉环境科技有限公司",
    "编号": "GR202421201452"
  },
  {
    "名称": "大连精良机械设备安装有限公司",
    "编号": "GR202421201453"
  },
  {
    "名称": "大连长丰实业总公司",
    "编号": "GR202421201454"
  },
  {
    "名称": "大连惠众模塑制造有限公司",
    "编号": "GR202421201455"
  },
  {
    "名称": "辽参经营管理(大连)集团有限公司",
    "编号": "GR202421201456"
  },
  {
    "名称": "大连鹏隆密封技术有限公司",
    "编号": "GR202421201457"
  },
  {
    "名称": "瓦房店宏瑞孚轴承制造有限公司",
    "编号": "GR202421201458"
  },
  {
    "名称": "企创融智科技服务(大连)有限公司",
    "编号": "GR202421201459"
  },
  {
    "名称": "大连芯技研工业有限公司",
    "编号": "GR202421201460"
  },
  {
    "名称": "云智天成（大连）信息技术有限公司",
    "编号": "GR202421201461"
  },
  {
    "名称": "大连大重检测技术服务有限公司",
    "编号": "GR202421201462"
  },
  {
    "名称": "大连天平软件工程有限公司",
    "编号": "GR202421201463"
  },
  {
    "名称": "大连明科自动化设备有限公司",
    "编号": "GR202421201464"
  },
  {
    "名称": "大连梁诚项目管理有限公司",
    "编号": "GR202421201465"
  },
  {
    "名称": "大连松志家具有限公司",
    "编号": "GR202421201466"
  },
  {
    "名称": "东亚自动化设备（大连）有限公司",
    "编号": "GR202421201467"
  },
  {
    "名称": "大连睿恒机械有限公司",
    "编号": "GR202421201468"
  },
  {
    "名称": "大连古德威机械有限公司",
    "编号": "GR202421201469"
  },
  {
    "名称": "大连圣博尔测绘仪器科技有限公司",
    "编号": "GR202421201470"
  },
  {
    "名称": "恒劲生物技术（大连）有限公司",
    "编号": "GR202421201471"
  },
  {
    "名称": "大连永朋金诺重型封头有限公司",
    "编号": "GR202421201472"
  },
  {
    "名称": "涵宇教育咨询(大连)有限公司",
    "编号": "GR202421201473"
  },
  {
    "名称": "大连易汇节能科技有限公司",
    "编号": "GR202421201474"
  },
  {
    "名称": "大连森永机械制造有限公司",
    "编号": "GR202421201475"
  },
  {
    "名称": "大连强力旭彩电子科技有限公司",
    "编号": "GR202421201476"
  },
  {
    "名称": "大连亿方精密钣金制造有限公司",
    "编号": "GR202421201477"
  },
  {
    "名称": "大连龙源包装材料有限公司",
    "编号": "GR202421201478"
  },
  {
    "名称": "大连博岳智能装备有限公司",
    "编号": "GR202421201479"
  },
  {
    "名称": "大连浩远精密部件有限公司",
    "编号": "GR202421201480"
  },
  {
    "名称": "大连阿普软件信息技术有限公司",
    "编号": "GR202421201481"
  },
  {
    "名称": "大连涵亿德钢材有限公司",
    "编号": "GR202421201482"
  },
  {
    "名称": "大连百年渔港科技有限公司",
    "编号": "GR202421201483"
  },
  {
    "名称": "大连麦洁卡科技有限公司",
    "编号": "GR202421201484"
  },
  {
    "名称": "大连鑫柏环境工程有限公司",
    "编号": "GR202421201485"
  },
  {
    "名称": "大连协同工业设备有限公司",
    "编号": "GR202421201486"
  },
  {
    "名称": "大连连理海洋工程有限公司",
    "编号": "GR202421201487"
  },
  {
    "名称": "大连晟鑫鎏海船舶机械设备有限公司",
    "编号": "GR202421201488"
  },
  {
    "名称": "大连东昂机电有限公司",
    "编号": "GR202421201489"
  },
  {
    "名称": "大连画田建筑设计有限公司",
    "编号": "GR202421201490"
  },
  {
    "名称": "兴科物联科技（大连）有限公司",
    "编号": "GR202421201491"
  },
  {
    "名称": "大连大特气体有限公司",
    "编号": "GR202421201492"
  },
  {
    "名称": "大连名德精密机械有限公司",
    "编号": "GR202421201493"
  },
  {
    "名称": "滕泰科技发展（大连）有限责任公司",
    "编号": "GR202421201494"
  },
  {
    "名称": "大连巴图信息技术有限责任公司",
    "编号": "GR202421201495"
  },
  {
    "名称": "大连德迈仕精密科技股份有限公司",
    "编号": "GR202421201496"
  },
  {
    "名称": "大连浩昌机械有限公司",
    "编号": "GR202421201497"
  },
  {
    "名称": "大连明德机电设备安装工程有限公司",
    "编号": "GR202421201498"
  },
  {
    "名称": "大连华冶联自动化有限公司",
    "编号": "GR202421201499"
  },
  {
    "名称": "大连华亿电力电器有限公司",
    "编号": "GR202421201500"
  },
  {
    "名称": "大连中石环保科技有限公司",
    "编号": "GR202421201501"
  },
  {
    "名称": "大连名阳实业有限公司",
    "编号": "GR202421201502"
  },
  {
    "名称": "华录云工场科技服务（大连）有限公司",
    "编号": "GR202421201503"
  },
  {
    "名称": "大连丰帆木制品有限公司",
    "编号": "GR202421201504"
  },
  {
    "名称": "大连宇都环境工程技术有限公司",
    "编号": "GR202421201505"
  },
  {
    "名称": "禾马教育科技(大连)有限公司",
    "编号": "GR202421201506"
  },
  {
    "名称": "大连乾尚源信息技术有限公司",
    "编号": "GR202421201507"
  },
  {
    "名称": "大连德洋自动化技术有限公司",
    "编号": "GR202421201508"
  },
  {
    "名称": "大连鑫塔通信建设工程有限公司",
    "编号": "GR202421201509"
  },
  {
    "名称": "大连雅谷信息科技有限公司",
    "编号": "GR202421201510"
  },
  {
    "名称": "大连软驰科技有限公司",
    "编号": "GR202421201511"
  },
  {
    "名称": "大连金猫鼠药有限公司",
    "编号": "GR202421201512"
  },
  {
    "名称": "大连好之源农产品有限公司",
    "编号": "GR202421201513"
  },
  {
    "名称": "大连兴发机械有限公司",
    "编号": "GR202421201514"
  },
  {
    "名称": "大连真心罐头食品有限公司",
    "编号": "GR202421201515"
  },
  {
    "名称": "大连新美汇能动力装备有限公司",
    "编号": "GR202421201516"
  },
  {
    "名称": "大连恒基新润水务有限公司",
    "编号": "GR202421201517"
  },
  {
    "名称": "三古科技(大连)有限公司",
    "编号": "GR202421201518"
  },
  {
    "名称": "大连易路达工程机械有限公司",
    "编号": "GR202421201519"
  },
  {
    "名称": "大连日辉模具科技有限公司",
    "编号": "GR202421201520"
  },
  {
    "名称": "大连融达供应链有限公司",
    "编号": "GR202421201521"
  },
  {
    "名称": "大连德特联合工业技术有限公司",
    "编号": "GR202421201522"
  },
  {
    "名称": "大连博控科技股份有限公司",
    "编号": "GR202421201523"
  },
  {
    "名称": "大连网易科技有限公司",
    "编号": "GR202421201524"
  },
  {
    "名称": "大连钰海科技有限公司",
    "编号": "GR202421201525"
  },
  {
    "名称": "大连天鸣科技有限公司",
    "编号": "GR202421201526"
  },
  {
    "名称": "大连海沃汽车部件有限公司",
    "编号": "GR202421201527"
  },
  {
    "名称": "大连诚亦联金属制品有限公司",
    "编号": "GR202421201528"
  },
  {
    "名称": "大连奥铭志远金属制品有限公司",
    "编号": "GR202421201529"
  },
  {
    "名称": "安源生物科技（大连）有限公司",
    "编号": "GR202421201530"
  },
  {
    "名称": "九城工业（大连）有限公司",
    "编号": "GR202421201531"
  },
  {
    "名称": "大连市锦泽制造有限公司",
    "编号": "GR202421201532"
  },
  {
    "名称": "大连威克达机械设备制造有限公司",
    "编号": "GR202421201533"
  },
  {
    "名称": "大连中远服装有限公司",
    "编号": "GR202421201534"
  },
  {
    "名称": "大连金航船机有限公司",
    "编号": "GR202421201535"
  },
  {
    "名称": "马可咨询服务(大连)有限公司",
    "编号": "GR202421201536"
  },
  {
    "名称": "大连力得现代科技有限公司",
    "编号": "GR202421201537"
  },
  {
    "名称": "大连轩昂科技有限公司",
    "编号": "GR202421201538"
  },
  {
    "名称": "大连思维通用技术研制有限公司",
    "编号": "GR202421201539"
  },
  {
    "名称": "大连新工设备有限公司",
    "编号": "GR202421201540"
  },
  {
    "名称": "捷诚晟（大连）科技有限公司",
    "编号": "GR202421201541"
  },
  {
    "名称": "大连珩盛工程造价咨询有限公司",
    "编号": "GR202421201542"
  },
  {
    "名称": "大连弘大特种风机有限公司",
    "编号": "GR202421201543"
  },
  {
    "名称": "大连理工加华环境科技有限公司",
    "编号": "GR202421201544"
  },
  {
    "名称": "东软教育科技集团有限公司",
    "编号": "GR202421201545"
  },
  {
    "名称": "大连金马衡器有限公司",
    "编号": "GR202421201546"
  },
  {
    "名称": "大连品弘制药机械有限公司",
    "编号": "GR202421201547"
  },
  {
    "名称": "逸盛大化石化有限公司",
    "编号": "GR202421201548"
  },
  {
    "名称": "大连鸿鹏塑料包装有限公司",
    "编号": "GR202421201549"
  },
  {
    "名称": "大连海奥膜技术有限公司",
    "编号": "GR202421201550"
  },
  {
    "名称": "大连工研精密机械有限公司",
    "编号": "GR202421201551"
  },
  {
    "名称": "大连海新工程技术有限公司",
    "编号": "GR202421201552"
  },
  {
    "名称": "盘古北方军戎(大连)创业孵化管理有限公司",
    "编号": "GR202421201553"
  },
  {
    "名称": "大连科萌工程材料有限公司",
    "编号": "GR202421201554"
  },
  {
    "名称": "大连千侯网络科技有限公司",
    "编号": "GR202421201555"
  },
  {
    "名称": "艾连科技(大连)有限公司",
    "编号": "GR202421201556"
  },
  {
    "名称": "大连司科赛斯科技有限公司",
    "编号": "GR202421201557"
  },
  {
    "名称": "大连智水慧成科技有限责任公司",
    "编号": "GR202421201558"
  },
  {
    "名称": "鸿睿昌精密模具(大连)有限公司",
    "编号": "GR202421201559"
  },
  {
    "名称": "大连天赢知识产权代理有限公司",
    "编号": "GR202421201560"
  },
  {
    "名称": "大连沃嘉科技有限公司",
    "编号": "GR202421201561"
  },
  {
    "名称": "大连蓝域精密仪器有限公司",
    "编号": "GR202421201562"
  },
  {
    "名称": "大连寺大汽车配件有限公司",
    "编号": "GR202421201563"
  },
  {
    "名称": "大连腾屹信科技有限公司",
    "编号": "GR202421201564"
  },
  {
    "名称": "大连同悦机械有限公司",
    "编号": "GR202421201565"
  },
  {
    "名称": "大连胜乾紫科技发展有限公司",
    "编号": "GR202421201566"
  },
  {
    "名称": "原点数创（大连）科技有限公司",
    "编号": "GR202421201567"
  },
  {
    "名称": "大连坤城工业有限公司",
    "编号": "GR202421201568"
  },
  {
    "名称": "大连盛邦恒驰数字技术有限公司",
    "编号": "GR202421201569"
  },
  {
    "名称": "渊东（大连）集团有限公司",
    "编号": "GR202421201570"
  },
  {
    "名称": "大连兆云科技有限公司",
    "编号": "GR202421201571"
  },
  {
    "名称": "大连梵希模塑有限责任公司",
    "编号": "GR202421201572"
  },
  {
    "名称": "大连新伟精密机械制造有限公司",
    "编号": "GR202421201573"
  },
  {
    "名称": "大连鑫玺铸造有限公司",
    "编号": "GR202421201574"
  },
  {
    "名称": "大连银安金融服务有限公司",
    "编号": "GR202421201575"
  },
  {
    "名称": "大连佳锐斯科技有限公司",
    "编号": "GR202421201576"
  },
  {
    "名称": "大连誉烽机械设备有限公司",
    "编号": "GR202421201577"
  },
  {
    "名称": "禾合永益（大连）环保科技有限公司",
    "编号": "GR202421201578"
  },
  {
    "名称": "禾下土（大连）生态农业有限公司",
    "编号": "GR202421201579"
  }
]